package com.google.android.gms.common.internal;

import android.os.Binder;
import android.os.Bundle;
import android.os.IBinder;
import android.os.IInterface;
import android.os.Parcel;
import android.os.Parcelable.Creator;
import android.os.RemoteException;

public abstract interface l
  extends IInterface
{
  public abstract void a(k paramk, int paramInt)
    throws RemoteException;
  
  public abstract void a(k paramk, int paramInt, String paramString)
    throws RemoteException;
  
  public abstract void a(k paramk, int paramInt, String paramString, Bundle paramBundle)
    throws RemoteException;
  
  public abstract void a(k paramk, int paramInt, String paramString, IBinder paramIBinder, Bundle paramBundle)
    throws RemoteException;
  
  public abstract void a(k paramk, int paramInt, String paramString1, String paramString2)
    throws RemoteException;
  
  public abstract void a(k paramk, int paramInt, String paramString1, String paramString2, String paramString3, String[] paramArrayOfString)
    throws RemoteException;
  
  public abstract void a(k paramk, int paramInt, String paramString1, String paramString2, String[] paramArrayOfString)
    throws RemoteException;
  
  public abstract void a(k paramk, int paramInt, String paramString1, String paramString2, String[] paramArrayOfString, Bundle paramBundle)
    throws RemoteException;
  
  public abstract void a(k paramk, int paramInt, String paramString1, String paramString2, String[] paramArrayOfString, String paramString3, Bundle paramBundle)
    throws RemoteException;
  
  public abstract void a(k paramk, int paramInt, String paramString1, String paramString2, String[] paramArrayOfString, String paramString3, IBinder paramIBinder, String paramString4, Bundle paramBundle)
    throws RemoteException;
  
  public abstract void a(k paramk, int paramInt, String paramString1, String[] paramArrayOfString, String paramString2, Bundle paramBundle)
    throws RemoteException;
  
  public abstract void b(k paramk, int paramInt, String paramString)
    throws RemoteException;
  
  public abstract void b(k paramk, int paramInt, String paramString, Bundle paramBundle)
    throws RemoteException;
  
  public abstract void b(k paramk, int paramInt, String paramString1, String paramString2, String[] paramArrayOfString)
    throws RemoteException;
  
  public abstract void c(k paramk, int paramInt, String paramString)
    throws RemoteException;
  
  public abstract void c(k paramk, int paramInt, String paramString, Bundle paramBundle)
    throws RemoteException;
  
  public abstract void d(k paramk, int paramInt, String paramString)
    throws RemoteException;
  
  public abstract void d(k paramk, int paramInt, String paramString, Bundle paramBundle)
    throws RemoteException;
  
  public abstract void e(k paramk, int paramInt, String paramString)
    throws RemoteException;
  
  public abstract void e(k paramk, int paramInt, String paramString, Bundle paramBundle)
    throws RemoteException;
  
  public abstract void f(k paramk, int paramInt, String paramString)
    throws RemoteException;
  
  public abstract void f(k paramk, int paramInt, String paramString, Bundle paramBundle)
    throws RemoteException;
  
  public abstract void g(k paramk, int paramInt, String paramString)
    throws RemoteException;
  
  public abstract void g(k paramk, int paramInt, String paramString, Bundle paramBundle)
    throws RemoteException;
  
  public abstract void h(k paramk, int paramInt, String paramString)
    throws RemoteException;
  
  public abstract void h(k paramk, int paramInt, String paramString, Bundle paramBundle)
    throws RemoteException;
  
  public abstract void i(k paramk, int paramInt, String paramString)
    throws RemoteException;
  
  public abstract void i(k paramk, int paramInt, String paramString, Bundle paramBundle)
    throws RemoteException;
  
  public abstract void j(k paramk, int paramInt, String paramString)
    throws RemoteException;
  
  public abstract void j(k paramk, int paramInt, String paramString, Bundle paramBundle)
    throws RemoteException;
  
  public abstract void k(k paramk, int paramInt, String paramString)
    throws RemoteException;
  
  public abstract void k(k paramk, int paramInt, String paramString, Bundle paramBundle)
    throws RemoteException;
  
  public abstract void l(k paramk, int paramInt, String paramString, Bundle paramBundle)
    throws RemoteException;
  
  public abstract void m(k paramk, int paramInt, String paramString, Bundle paramBundle)
    throws RemoteException;
  
  public abstract void n(k paramk, int paramInt, String paramString, Bundle paramBundle)
    throws RemoteException;
  
  public abstract void o(k paramk, int paramInt, String paramString, Bundle paramBundle)
    throws RemoteException;
  
  public abstract void p(k paramk, int paramInt, String paramString, Bundle paramBundle)
    throws RemoteException;
  
  public abstract void q(k paramk, int paramInt, String paramString, Bundle paramBundle)
    throws RemoteException;
  
  public abstract void r(k paramk, int paramInt, String paramString, Bundle paramBundle)
    throws RemoteException;
  
  public abstract void s(k paramk, int paramInt, String paramString, Bundle paramBundle)
    throws RemoteException;
  
  public abstract void t(k paramk, int paramInt, String paramString, Bundle paramBundle)
    throws RemoteException;
  
  public static abstract class a
    extends Binder
    implements l
  {
    public static l Q(IBinder paramIBinder)
    {
      if (paramIBinder == null) {
        paramIBinder = null;
      }
      for (;;)
      {
        return paramIBinder;
        IInterface localIInterface = paramIBinder.queryLocalInterface("com.google.android.gms.common.internal.IGmsServiceBroker");
        if ((localIInterface != null) && ((localIInterface instanceof l))) {
          paramIBinder = (l)localIInterface;
        } else {
          paramIBinder = new a(paramIBinder);
        }
      }
    }
    
    public boolean onTransact(int paramInt1, Parcel paramParcel1, Parcel paramParcel2, int paramInt2)
      throws RemoteException
    {
      Object localObject2 = null;
      Object localObject3 = null;
      Object localObject4 = null;
      Object localObject5 = null;
      k localk = null;
      String str = null;
      Object localObject6 = null;
      Object localObject7 = null;
      Object localObject8 = null;
      Object localObject9 = null;
      Object localObject10 = null;
      Object localObject11 = null;
      Object localObject12 = null;
      Object localObject13 = null;
      Object localObject14 = null;
      Object localObject15 = null;
      Object localObject16 = null;
      Object localObject17 = null;
      Object localObject18 = null;
      Object localObject1 = null;
      boolean bool;
      switch (paramInt1)
      {
      default: 
        bool = super.onTransact(paramInt1, paramParcel1, paramParcel2, paramInt2);
      }
      for (;;)
      {
        return bool;
        paramParcel2.writeString("com.google.android.gms.common.internal.IGmsServiceBroker");
        bool = true;
        continue;
        paramParcel1.enforceInterface("com.google.android.gms.common.internal.IGmsServiceBroker");
        localObject5 = k.a.P(paramParcel1.readStrongBinder());
        paramInt1 = paramParcel1.readInt();
        localObject2 = paramParcel1.readString();
        localObject4 = paramParcel1.readString();
        localObject3 = paramParcel1.createStringArray();
        localObject1 = paramParcel1.readString();
        if (paramParcel1.readInt() != 0) {}
        for (paramParcel1 = (Bundle)Bundle.CREATOR.createFromParcel(paramParcel1);; paramParcel1 = null)
        {
          a((k)localObject5, paramInt1, (String)localObject2, (String)localObject4, (String[])localObject3, (String)localObject1, paramParcel1);
          paramParcel2.writeNoException();
          bool = true;
          break;
        }
        paramParcel1.enforceInterface("com.google.android.gms.common.internal.IGmsServiceBroker");
        localObject2 = k.a.P(paramParcel1.readStrongBinder());
        paramInt1 = paramParcel1.readInt();
        localObject3 = paramParcel1.readString();
        if (paramParcel1.readInt() != 0) {
          localObject1 = (Bundle)Bundle.CREATOR.createFromParcel(paramParcel1);
        }
        a((k)localObject2, paramInt1, (String)localObject3, (Bundle)localObject1);
        paramParcel2.writeNoException();
        bool = true;
        continue;
        paramParcel1.enforceInterface("com.google.android.gms.common.internal.IGmsServiceBroker");
        a(k.a.P(paramParcel1.readStrongBinder()), paramParcel1.readInt(), paramParcel1.readString());
        paramParcel2.writeNoException();
        bool = true;
        continue;
        paramParcel1.enforceInterface("com.google.android.gms.common.internal.IGmsServiceBroker");
        a(k.a.P(paramParcel1.readStrongBinder()), paramParcel1.readInt());
        paramParcel2.writeNoException();
        bool = true;
        continue;
        paramParcel1.enforceInterface("com.google.android.gms.common.internal.IGmsServiceBroker");
        localObject3 = k.a.P(paramParcel1.readStrongBinder());
        paramInt1 = paramParcel1.readInt();
        localObject4 = paramParcel1.readString();
        localObject1 = localObject2;
        if (paramParcel1.readInt() != 0) {
          localObject1 = (Bundle)Bundle.CREATOR.createFromParcel(paramParcel1);
        }
        b((k)localObject3, paramInt1, (String)localObject4, (Bundle)localObject1);
        paramParcel2.writeNoException();
        bool = true;
        continue;
        paramParcel1.enforceInterface("com.google.android.gms.common.internal.IGmsServiceBroker");
        localObject2 = k.a.P(paramParcel1.readStrongBinder());
        paramInt1 = paramParcel1.readInt();
        localObject4 = paramParcel1.readString();
        localObject1 = localObject3;
        if (paramParcel1.readInt() != 0) {
          localObject1 = (Bundle)Bundle.CREATOR.createFromParcel(paramParcel1);
        }
        c((k)localObject2, paramInt1, (String)localObject4, (Bundle)localObject1);
        paramParcel2.writeNoException();
        bool = true;
        continue;
        paramParcel1.enforceInterface("com.google.android.gms.common.internal.IGmsServiceBroker");
        localObject3 = k.a.P(paramParcel1.readStrongBinder());
        paramInt1 = paramParcel1.readInt();
        localObject2 = paramParcel1.readString();
        localObject1 = localObject4;
        if (paramParcel1.readInt() != 0) {
          localObject1 = (Bundle)Bundle.CREATOR.createFromParcel(paramParcel1);
        }
        d((k)localObject3, paramInt1, (String)localObject2, (Bundle)localObject1);
        paramParcel2.writeNoException();
        bool = true;
        continue;
        paramParcel1.enforceInterface("com.google.android.gms.common.internal.IGmsServiceBroker");
        localObject2 = k.a.P(paramParcel1.readStrongBinder());
        paramInt1 = paramParcel1.readInt();
        localObject3 = paramParcel1.readString();
        localObject1 = localObject5;
        if (paramParcel1.readInt() != 0) {
          localObject1 = (Bundle)Bundle.CREATOR.createFromParcel(paramParcel1);
        }
        e((k)localObject2, paramInt1, (String)localObject3, (Bundle)localObject1);
        paramParcel2.writeNoException();
        bool = true;
        continue;
        paramParcel1.enforceInterface("com.google.android.gms.common.internal.IGmsServiceBroker");
        localk = k.a.P(paramParcel1.readStrongBinder());
        paramInt1 = paramParcel1.readInt();
        str = paramParcel1.readString();
        localObject2 = paramParcel1.readString();
        localObject1 = paramParcel1.createStringArray();
        localObject3 = paramParcel1.readString();
        localObject4 = paramParcel1.readStrongBinder();
        localObject5 = paramParcel1.readString();
        if (paramParcel1.readInt() != 0) {}
        for (paramParcel1 = (Bundle)Bundle.CREATOR.createFromParcel(paramParcel1);; paramParcel1 = null)
        {
          a(localk, paramInt1, str, (String)localObject2, (String[])localObject1, (String)localObject3, (IBinder)localObject4, (String)localObject5, paramParcel1);
          paramParcel2.writeNoException();
          bool = true;
          break;
        }
        paramParcel1.enforceInterface("com.google.android.gms.common.internal.IGmsServiceBroker");
        a(k.a.P(paramParcel1.readStrongBinder()), paramParcel1.readInt(), paramParcel1.readString(), paramParcel1.readString(), paramParcel1.createStringArray());
        paramParcel2.writeNoException();
        bool = true;
        continue;
        paramParcel1.enforceInterface("com.google.android.gms.common.internal.IGmsServiceBroker");
        localObject2 = k.a.P(paramParcel1.readStrongBinder());
        paramInt1 = paramParcel1.readInt();
        localObject3 = paramParcel1.readString();
        localObject1 = localk;
        if (paramParcel1.readInt() != 0) {
          localObject1 = (Bundle)Bundle.CREATOR.createFromParcel(paramParcel1);
        }
        f((k)localObject2, paramInt1, (String)localObject3, (Bundle)localObject1);
        paramParcel2.writeNoException();
        bool = true;
        continue;
        paramParcel1.enforceInterface("com.google.android.gms.common.internal.IGmsServiceBroker");
        localObject3 = k.a.P(paramParcel1.readStrongBinder());
        paramInt1 = paramParcel1.readInt();
        localObject2 = paramParcel1.readString();
        localObject1 = str;
        if (paramParcel1.readInt() != 0) {
          localObject1 = (Bundle)Bundle.CREATOR.createFromParcel(paramParcel1);
        }
        g((k)localObject3, paramInt1, (String)localObject2, (Bundle)localObject1);
        paramParcel2.writeNoException();
        bool = true;
        continue;
        paramParcel1.enforceInterface("com.google.android.gms.common.internal.IGmsServiceBroker");
        localObject2 = k.a.P(paramParcel1.readStrongBinder());
        paramInt1 = paramParcel1.readInt();
        localObject3 = paramParcel1.readString();
        localObject1 = localObject6;
        if (paramParcel1.readInt() != 0) {
          localObject1 = (Bundle)Bundle.CREATOR.createFromParcel(paramParcel1);
        }
        h((k)localObject2, paramInt1, (String)localObject3, (Bundle)localObject1);
        paramParcel2.writeNoException();
        bool = true;
        continue;
        paramParcel1.enforceInterface("com.google.android.gms.common.internal.IGmsServiceBroker");
        localObject3 = k.a.P(paramParcel1.readStrongBinder());
        paramInt1 = paramParcel1.readInt();
        localObject2 = paramParcel1.readString();
        localObject1 = localObject7;
        if (paramParcel1.readInt() != 0) {
          localObject1 = (Bundle)Bundle.CREATOR.createFromParcel(paramParcel1);
        }
        i((k)localObject3, paramInt1, (String)localObject2, (Bundle)localObject1);
        paramParcel2.writeNoException();
        bool = true;
        continue;
        paramParcel1.enforceInterface("com.google.android.gms.common.internal.IGmsServiceBroker");
        localObject3 = k.a.P(paramParcel1.readStrongBinder());
        paramInt1 = paramParcel1.readInt();
        localObject2 = paramParcel1.readString();
        localObject1 = localObject8;
        if (paramParcel1.readInt() != 0) {
          localObject1 = (Bundle)Bundle.CREATOR.createFromParcel(paramParcel1);
        }
        j((k)localObject3, paramInt1, (String)localObject2, (Bundle)localObject1);
        paramParcel2.writeNoException();
        bool = true;
        continue;
        paramParcel1.enforceInterface("com.google.android.gms.common.internal.IGmsServiceBroker");
        localObject3 = k.a.P(paramParcel1.readStrongBinder());
        paramInt1 = paramParcel1.readInt();
        localObject2 = paramParcel1.readString();
        localObject1 = localObject9;
        if (paramParcel1.readInt() != 0) {
          localObject1 = (Bundle)Bundle.CREATOR.createFromParcel(paramParcel1);
        }
        k((k)localObject3, paramInt1, (String)localObject2, (Bundle)localObject1);
        paramParcel2.writeNoException();
        bool = true;
        continue;
        paramParcel1.enforceInterface("com.google.android.gms.common.internal.IGmsServiceBroker");
        localObject2 = k.a.P(paramParcel1.readStrongBinder());
        paramInt1 = paramParcel1.readInt();
        localObject3 = paramParcel1.readString();
        localObject1 = localObject10;
        if (paramParcel1.readInt() != 0) {
          localObject1 = (Bundle)Bundle.CREATOR.createFromParcel(paramParcel1);
        }
        l((k)localObject2, paramInt1, (String)localObject3, (Bundle)localObject1);
        paramParcel2.writeNoException();
        bool = true;
        continue;
        paramParcel1.enforceInterface("com.google.android.gms.common.internal.IGmsServiceBroker");
        localObject2 = k.a.P(paramParcel1.readStrongBinder());
        paramInt1 = paramParcel1.readInt();
        localObject3 = paramParcel1.readString();
        localObject1 = localObject11;
        if (paramParcel1.readInt() != 0) {
          localObject1 = (Bundle)Bundle.CREATOR.createFromParcel(paramParcel1);
        }
        m((k)localObject2, paramInt1, (String)localObject3, (Bundle)localObject1);
        paramParcel2.writeNoException();
        bool = true;
        continue;
        paramParcel1.enforceInterface("com.google.android.gms.common.internal.IGmsServiceBroker");
        localObject1 = k.a.P(paramParcel1.readStrongBinder());
        paramInt1 = paramParcel1.readInt();
        localObject2 = paramParcel1.readString();
        localObject3 = paramParcel1.readStrongBinder();
        if (paramParcel1.readInt() != 0) {}
        for (paramParcel1 = (Bundle)Bundle.CREATOR.createFromParcel(paramParcel1);; paramParcel1 = null)
        {
          a((k)localObject1, paramInt1, (String)localObject2, (IBinder)localObject3, paramParcel1);
          paramParcel2.writeNoException();
          bool = true;
          break;
        }
        paramParcel1.enforceInterface("com.google.android.gms.common.internal.IGmsServiceBroker");
        localObject3 = k.a.P(paramParcel1.readStrongBinder());
        paramInt1 = paramParcel1.readInt();
        localObject1 = paramParcel1.readString();
        localObject4 = paramParcel1.createStringArray();
        localObject2 = paramParcel1.readString();
        if (paramParcel1.readInt() != 0) {}
        for (paramParcel1 = (Bundle)Bundle.CREATOR.createFromParcel(paramParcel1);; paramParcel1 = null)
        {
          a((k)localObject3, paramInt1, (String)localObject1, (String[])localObject4, (String)localObject2, paramParcel1);
          paramParcel2.writeNoException();
          bool = true;
          break;
        }
        paramParcel1.enforceInterface("com.google.android.gms.common.internal.IGmsServiceBroker");
        b(k.a.P(paramParcel1.readStrongBinder()), paramParcel1.readInt(), paramParcel1.readString());
        paramParcel2.writeNoException();
        bool = true;
        continue;
        paramParcel1.enforceInterface("com.google.android.gms.common.internal.IGmsServiceBroker");
        c(k.a.P(paramParcel1.readStrongBinder()), paramParcel1.readInt(), paramParcel1.readString());
        paramParcel2.writeNoException();
        bool = true;
        continue;
        paramParcel1.enforceInterface("com.google.android.gms.common.internal.IGmsServiceBroker");
        localObject2 = k.a.P(paramParcel1.readStrongBinder());
        paramInt1 = paramParcel1.readInt();
        localObject3 = paramParcel1.readString();
        localObject1 = localObject12;
        if (paramParcel1.readInt() != 0) {
          localObject1 = (Bundle)Bundle.CREATOR.createFromParcel(paramParcel1);
        }
        n((k)localObject2, paramInt1, (String)localObject3, (Bundle)localObject1);
        paramParcel2.writeNoException();
        bool = true;
        continue;
        paramParcel1.enforceInterface("com.google.android.gms.common.internal.IGmsServiceBroker");
        d(k.a.P(paramParcel1.readStrongBinder()), paramParcel1.readInt(), paramParcel1.readString());
        paramParcel2.writeNoException();
        bool = true;
        continue;
        paramParcel1.enforceInterface("com.google.android.gms.common.internal.IGmsServiceBroker");
        localObject2 = k.a.P(paramParcel1.readStrongBinder());
        paramInt1 = paramParcel1.readInt();
        localObject3 = paramParcel1.readString();
        localObject1 = localObject13;
        if (paramParcel1.readInt() != 0) {
          localObject1 = (Bundle)Bundle.CREATOR.createFromParcel(paramParcel1);
        }
        o((k)localObject2, paramInt1, (String)localObject3, (Bundle)localObject1);
        paramParcel2.writeNoException();
        bool = true;
        continue;
        paramParcel1.enforceInterface("com.google.android.gms.common.internal.IGmsServiceBroker");
        e(k.a.P(paramParcel1.readStrongBinder()), paramParcel1.readInt(), paramParcel1.readString());
        paramParcel2.writeNoException();
        bool = true;
        continue;
        paramParcel1.enforceInterface("com.google.android.gms.common.internal.IGmsServiceBroker");
        localObject2 = k.a.P(paramParcel1.readStrongBinder());
        paramInt1 = paramParcel1.readInt();
        localObject3 = paramParcel1.readString();
        localObject1 = localObject14;
        if (paramParcel1.readInt() != 0) {
          localObject1 = (Bundle)Bundle.CREATOR.createFromParcel(paramParcel1);
        }
        p((k)localObject2, paramInt1, (String)localObject3, (Bundle)localObject1);
        paramParcel2.writeNoException();
        bool = true;
        continue;
        paramParcel1.enforceInterface("com.google.android.gms.common.internal.IGmsServiceBroker");
        b(k.a.P(paramParcel1.readStrongBinder()), paramParcel1.readInt(), paramParcel1.readString(), paramParcel1.readString(), paramParcel1.createStringArray());
        paramParcel2.writeNoException();
        bool = true;
        continue;
        paramParcel1.enforceInterface("com.google.android.gms.common.internal.IGmsServiceBroker");
        localObject2 = k.a.P(paramParcel1.readStrongBinder());
        paramInt1 = paramParcel1.readInt();
        localObject4 = paramParcel1.readString();
        localObject3 = paramParcel1.readString();
        localObject1 = paramParcel1.createStringArray();
        if (paramParcel1.readInt() != 0) {}
        for (paramParcel1 = (Bundle)Bundle.CREATOR.createFromParcel(paramParcel1);; paramParcel1 = null)
        {
          a((k)localObject2, paramInt1, (String)localObject4, (String)localObject3, (String[])localObject1, paramParcel1);
          paramParcel2.writeNoException();
          bool = true;
          break;
        }
        paramParcel1.enforceInterface("com.google.android.gms.common.internal.IGmsServiceBroker");
        f(k.a.P(paramParcel1.readStrongBinder()), paramParcel1.readInt(), paramParcel1.readString());
        paramParcel2.writeNoException();
        bool = true;
        continue;
        paramParcel1.enforceInterface("com.google.android.gms.common.internal.IGmsServiceBroker");
        g(k.a.P(paramParcel1.readStrongBinder()), paramParcel1.readInt(), paramParcel1.readString());
        paramParcel2.writeNoException();
        bool = true;
        continue;
        paramParcel1.enforceInterface("com.google.android.gms.common.internal.IGmsServiceBroker");
        a(k.a.P(paramParcel1.readStrongBinder()), paramParcel1.readInt(), paramParcel1.readString(), paramParcel1.readString(), paramParcel1.readString(), paramParcel1.createStringArray());
        paramParcel2.writeNoException();
        bool = true;
        continue;
        paramParcel1.enforceInterface("com.google.android.gms.common.internal.IGmsServiceBroker");
        a(k.a.P(paramParcel1.readStrongBinder()), paramParcel1.readInt(), paramParcel1.readString(), paramParcel1.readString());
        paramParcel2.writeNoException();
        bool = true;
        continue;
        paramParcel1.enforceInterface("com.google.android.gms.common.internal.IGmsServiceBroker");
        h(k.a.P(paramParcel1.readStrongBinder()), paramParcel1.readInt(), paramParcel1.readString());
        paramParcel2.writeNoException();
        bool = true;
        continue;
        paramParcel1.enforceInterface("com.google.android.gms.common.internal.IGmsServiceBroker");
        i(k.a.P(paramParcel1.readStrongBinder()), paramParcel1.readInt(), paramParcel1.readString());
        paramParcel2.writeNoException();
        bool = true;
        continue;
        paramParcel1.enforceInterface("com.google.android.gms.common.internal.IGmsServiceBroker");
        localObject3 = k.a.P(paramParcel1.readStrongBinder());
        paramInt1 = paramParcel1.readInt();
        localObject2 = paramParcel1.readString();
        localObject1 = localObject15;
        if (paramParcel1.readInt() != 0) {
          localObject1 = (Bundle)Bundle.CREATOR.createFromParcel(paramParcel1);
        }
        q((k)localObject3, paramInt1, (String)localObject2, (Bundle)localObject1);
        paramParcel2.writeNoException();
        bool = true;
        continue;
        paramParcel1.enforceInterface("com.google.android.gms.common.internal.IGmsServiceBroker");
        localObject2 = k.a.P(paramParcel1.readStrongBinder());
        paramInt1 = paramParcel1.readInt();
        localObject3 = paramParcel1.readString();
        localObject1 = localObject16;
        if (paramParcel1.readInt() != 0) {
          localObject1 = (Bundle)Bundle.CREATOR.createFromParcel(paramParcel1);
        }
        r((k)localObject2, paramInt1, (String)localObject3, (Bundle)localObject1);
        paramParcel2.writeNoException();
        bool = true;
        continue;
        paramParcel1.enforceInterface("com.google.android.gms.common.internal.IGmsServiceBroker");
        j(k.a.P(paramParcel1.readStrongBinder()), paramParcel1.readInt(), paramParcel1.readString());
        paramParcel2.writeNoException();
        bool = true;
        continue;
        paramParcel1.enforceInterface("com.google.android.gms.common.internal.IGmsServiceBroker");
        localObject3 = k.a.P(paramParcel1.readStrongBinder());
        paramInt1 = paramParcel1.readInt();
        localObject2 = paramParcel1.readString();
        localObject1 = localObject17;
        if (paramParcel1.readInt() != 0) {
          localObject1 = (Bundle)Bundle.CREATOR.createFromParcel(paramParcel1);
        }
        s((k)localObject3, paramInt1, (String)localObject2, (Bundle)localObject1);
        paramParcel2.writeNoException();
        bool = true;
        continue;
        paramParcel1.enforceInterface("com.google.android.gms.common.internal.IGmsServiceBroker");
        k(k.a.P(paramParcel1.readStrongBinder()), paramParcel1.readInt(), paramParcel1.readString());
        paramParcel2.writeNoException();
        bool = true;
        continue;
        paramParcel1.enforceInterface("com.google.android.gms.common.internal.IGmsServiceBroker");
        localObject2 = k.a.P(paramParcel1.readStrongBinder());
        paramInt1 = paramParcel1.readInt();
        localObject3 = paramParcel1.readString();
        localObject1 = localObject18;
        if (paramParcel1.readInt() != 0) {
          localObject1 = (Bundle)Bundle.CREATOR.createFromParcel(paramParcel1);
        }
        t((k)localObject2, paramInt1, (String)localObject3, (Bundle)localObject1);
        paramParcel2.writeNoException();
        bool = true;
      }
    }
    
    private static class a
      implements l
    {
      private IBinder lb;
      
      a(IBinder paramIBinder)
      {
        this.lb = paramIBinder;
      }
      
      /* Error */
      public void a(k paramk, int paramInt)
        throws RemoteException
      {
        // Byte code:
        //   0: invokestatic 28	android/os/Parcel:obtain	()Landroid/os/Parcel;
        //   3: astore 4
        //   5: invokestatic 28	android/os/Parcel:obtain	()Landroid/os/Parcel;
        //   8: astore_3
        //   9: aload 4
        //   11: ldc 30
        //   13: invokevirtual 34	android/os/Parcel:writeInterfaceToken	(Ljava/lang/String;)V
        //   16: aload_1
        //   17: ifnull +51 -> 68
        //   20: aload_1
        //   21: invokeinterface 40 1 0
        //   26: astore_1
        //   27: aload 4
        //   29: aload_1
        //   30: invokevirtual 43	android/os/Parcel:writeStrongBinder	(Landroid/os/IBinder;)V
        //   33: aload 4
        //   35: iload_2
        //   36: invokevirtual 47	android/os/Parcel:writeInt	(I)V
        //   39: aload_0
        //   40: getfield 18	com/google/android/gms/common/internal/l$a$a:lb	Landroid/os/IBinder;
        //   43: iconst_4
        //   44: aload 4
        //   46: aload_3
        //   47: iconst_0
        //   48: invokeinterface 53 5 0
        //   53: pop
        //   54: aload_3
        //   55: invokevirtual 56	android/os/Parcel:readException	()V
        //   58: aload_3
        //   59: invokevirtual 59	android/os/Parcel:recycle	()V
        //   62: aload 4
        //   64: invokevirtual 59	android/os/Parcel:recycle	()V
        //   67: return
        //   68: aconst_null
        //   69: astore_1
        //   70: goto -43 -> 27
        //   73: astore_1
        //   74: aload_3
        //   75: invokevirtual 59	android/os/Parcel:recycle	()V
        //   78: aload 4
        //   80: invokevirtual 59	android/os/Parcel:recycle	()V
        //   83: aload_1
        //   84: athrow
        // Local variable table:
        //   start	length	slot	name	signature
        //   0	85	0	this	a
        //   0	85	1	paramk	k
        //   0	85	2	paramInt	int
        //   8	67	3	localParcel1	Parcel
        //   3	76	4	localParcel2	Parcel
        // Exception table:
        //   from	to	target	type
        //   9	16	73	finally
        //   20	27	73	finally
        //   27	58	73	finally
      }
      
      /* Error */
      public void a(k paramk, int paramInt, String paramString)
        throws RemoteException
      {
        // Byte code:
        //   0: invokestatic 28	android/os/Parcel:obtain	()Landroid/os/Parcel;
        //   3: astore 5
        //   5: invokestatic 28	android/os/Parcel:obtain	()Landroid/os/Parcel;
        //   8: astore 4
        //   10: aload 5
        //   12: ldc 30
        //   14: invokevirtual 34	android/os/Parcel:writeInterfaceToken	(Ljava/lang/String;)V
        //   17: aload_1
        //   18: ifnull +60 -> 78
        //   21: aload_1
        //   22: invokeinterface 40 1 0
        //   27: astore_1
        //   28: aload 5
        //   30: aload_1
        //   31: invokevirtual 43	android/os/Parcel:writeStrongBinder	(Landroid/os/IBinder;)V
        //   34: aload 5
        //   36: iload_2
        //   37: invokevirtual 47	android/os/Parcel:writeInt	(I)V
        //   40: aload 5
        //   42: aload_3
        //   43: invokevirtual 64	android/os/Parcel:writeString	(Ljava/lang/String;)V
        //   46: aload_0
        //   47: getfield 18	com/google/android/gms/common/internal/l$a$a:lb	Landroid/os/IBinder;
        //   50: iconst_3
        //   51: aload 5
        //   53: aload 4
        //   55: iconst_0
        //   56: invokeinterface 53 5 0
        //   61: pop
        //   62: aload 4
        //   64: invokevirtual 56	android/os/Parcel:readException	()V
        //   67: aload 4
        //   69: invokevirtual 59	android/os/Parcel:recycle	()V
        //   72: aload 5
        //   74: invokevirtual 59	android/os/Parcel:recycle	()V
        //   77: return
        //   78: aconst_null
        //   79: astore_1
        //   80: goto -52 -> 28
        //   83: astore_1
        //   84: aload 4
        //   86: invokevirtual 59	android/os/Parcel:recycle	()V
        //   89: aload 5
        //   91: invokevirtual 59	android/os/Parcel:recycle	()V
        //   94: aload_1
        //   95: athrow
        // Local variable table:
        //   start	length	slot	name	signature
        //   0	96	0	this	a
        //   0	96	1	paramk	k
        //   0	96	2	paramInt	int
        //   0	96	3	paramString	String
        //   8	77	4	localParcel1	Parcel
        //   3	87	5	localParcel2	Parcel
        // Exception table:
        //   from	to	target	type
        //   10	17	83	finally
        //   21	28	83	finally
        //   28	67	83	finally
      }
      
      /* Error */
      public void a(k paramk, int paramInt, String paramString, Bundle paramBundle)
        throws RemoteException
      {
        // Byte code:
        //   0: invokestatic 28	android/os/Parcel:obtain	()Landroid/os/Parcel;
        //   3: astore 5
        //   5: invokestatic 28	android/os/Parcel:obtain	()Landroid/os/Parcel;
        //   8: astore 6
        //   10: aload 5
        //   12: ldc 30
        //   14: invokevirtual 34	android/os/Parcel:writeInterfaceToken	(Ljava/lang/String;)V
        //   17: aload_1
        //   18: ifnull +79 -> 97
        //   21: aload_1
        //   22: invokeinterface 40 1 0
        //   27: astore_1
        //   28: aload 5
        //   30: aload_1
        //   31: invokevirtual 43	android/os/Parcel:writeStrongBinder	(Landroid/os/IBinder;)V
        //   34: aload 5
        //   36: iload_2
        //   37: invokevirtual 47	android/os/Parcel:writeInt	(I)V
        //   40: aload 5
        //   42: aload_3
        //   43: invokevirtual 64	android/os/Parcel:writeString	(Ljava/lang/String;)V
        //   46: aload 4
        //   48: ifnull +54 -> 102
        //   51: aload 5
        //   53: iconst_1
        //   54: invokevirtual 47	android/os/Parcel:writeInt	(I)V
        //   57: aload 4
        //   59: aload 5
        //   61: iconst_0
        //   62: invokevirtual 71	android/os/Bundle:writeToParcel	(Landroid/os/Parcel;I)V
        //   65: aload_0
        //   66: getfield 18	com/google/android/gms/common/internal/l$a$a:lb	Landroid/os/IBinder;
        //   69: iconst_2
        //   70: aload 5
        //   72: aload 6
        //   74: iconst_0
        //   75: invokeinterface 53 5 0
        //   80: pop
        //   81: aload 6
        //   83: invokevirtual 56	android/os/Parcel:readException	()V
        //   86: aload 6
        //   88: invokevirtual 59	android/os/Parcel:recycle	()V
        //   91: aload 5
        //   93: invokevirtual 59	android/os/Parcel:recycle	()V
        //   96: return
        //   97: aconst_null
        //   98: astore_1
        //   99: goto -71 -> 28
        //   102: aload 5
        //   104: iconst_0
        //   105: invokevirtual 47	android/os/Parcel:writeInt	(I)V
        //   108: goto -43 -> 65
        //   111: astore_1
        //   112: aload 6
        //   114: invokevirtual 59	android/os/Parcel:recycle	()V
        //   117: aload 5
        //   119: invokevirtual 59	android/os/Parcel:recycle	()V
        //   122: aload_1
        //   123: athrow
        // Local variable table:
        //   start	length	slot	name	signature
        //   0	124	0	this	a
        //   0	124	1	paramk	k
        //   0	124	2	paramInt	int
        //   0	124	3	paramString	String
        //   0	124	4	paramBundle	Bundle
        //   3	115	5	localParcel1	Parcel
        //   8	105	6	localParcel2	Parcel
        // Exception table:
        //   from	to	target	type
        //   10	17	111	finally
        //   21	28	111	finally
        //   28	46	111	finally
        //   51	65	111	finally
        //   65	86	111	finally
        //   102	108	111	finally
      }
      
      /* Error */
      public void a(k paramk, int paramInt, String paramString, IBinder paramIBinder, Bundle paramBundle)
        throws RemoteException
      {
        // Byte code:
        //   0: invokestatic 28	android/os/Parcel:obtain	()Landroid/os/Parcel;
        //   3: astore 7
        //   5: invokestatic 28	android/os/Parcel:obtain	()Landroid/os/Parcel;
        //   8: astore 6
        //   10: aload 7
        //   12: ldc 30
        //   14: invokevirtual 34	android/os/Parcel:writeInterfaceToken	(Ljava/lang/String;)V
        //   17: aload_1
        //   18: ifnull +87 -> 105
        //   21: aload_1
        //   22: invokeinterface 40 1 0
        //   27: astore_1
        //   28: aload 7
        //   30: aload_1
        //   31: invokevirtual 43	android/os/Parcel:writeStrongBinder	(Landroid/os/IBinder;)V
        //   34: aload 7
        //   36: iload_2
        //   37: invokevirtual 47	android/os/Parcel:writeInt	(I)V
        //   40: aload 7
        //   42: aload_3
        //   43: invokevirtual 64	android/os/Parcel:writeString	(Ljava/lang/String;)V
        //   46: aload 7
        //   48: aload 4
        //   50: invokevirtual 43	android/os/Parcel:writeStrongBinder	(Landroid/os/IBinder;)V
        //   53: aload 5
        //   55: ifnull +55 -> 110
        //   58: aload 7
        //   60: iconst_1
        //   61: invokevirtual 47	android/os/Parcel:writeInt	(I)V
        //   64: aload 5
        //   66: aload 7
        //   68: iconst_0
        //   69: invokevirtual 71	android/os/Bundle:writeToParcel	(Landroid/os/Parcel;I)V
        //   72: aload_0
        //   73: getfield 18	com/google/android/gms/common/internal/l$a$a:lb	Landroid/os/IBinder;
        //   76: bipush 19
        //   78: aload 7
        //   80: aload 6
        //   82: iconst_0
        //   83: invokeinterface 53 5 0
        //   88: pop
        //   89: aload 6
        //   91: invokevirtual 56	android/os/Parcel:readException	()V
        //   94: aload 6
        //   96: invokevirtual 59	android/os/Parcel:recycle	()V
        //   99: aload 7
        //   101: invokevirtual 59	android/os/Parcel:recycle	()V
        //   104: return
        //   105: aconst_null
        //   106: astore_1
        //   107: goto -79 -> 28
        //   110: aload 7
        //   112: iconst_0
        //   113: invokevirtual 47	android/os/Parcel:writeInt	(I)V
        //   116: goto -44 -> 72
        //   119: astore_1
        //   120: aload 6
        //   122: invokevirtual 59	android/os/Parcel:recycle	()V
        //   125: aload 7
        //   127: invokevirtual 59	android/os/Parcel:recycle	()V
        //   130: aload_1
        //   131: athrow
        // Local variable table:
        //   start	length	slot	name	signature
        //   0	132	0	this	a
        //   0	132	1	paramk	k
        //   0	132	2	paramInt	int
        //   0	132	3	paramString	String
        //   0	132	4	paramIBinder	IBinder
        //   0	132	5	paramBundle	Bundle
        //   8	113	6	localParcel1	Parcel
        //   3	123	7	localParcel2	Parcel
        // Exception table:
        //   from	to	target	type
        //   10	17	119	finally
        //   21	28	119	finally
        //   28	53	119	finally
        //   58	72	119	finally
        //   72	94	119	finally
        //   110	116	119	finally
      }
      
      /* Error */
      public void a(k paramk, int paramInt, String paramString1, String paramString2)
        throws RemoteException
      {
        // Byte code:
        //   0: invokestatic 28	android/os/Parcel:obtain	()Landroid/os/Parcel;
        //   3: astore 5
        //   5: invokestatic 28	android/os/Parcel:obtain	()Landroid/os/Parcel;
        //   8: astore 6
        //   10: aload 5
        //   12: ldc 30
        //   14: invokevirtual 34	android/os/Parcel:writeInterfaceToken	(Ljava/lang/String;)V
        //   17: aload_1
        //   18: ifnull +68 -> 86
        //   21: aload_1
        //   22: invokeinterface 40 1 0
        //   27: astore_1
        //   28: aload 5
        //   30: aload_1
        //   31: invokevirtual 43	android/os/Parcel:writeStrongBinder	(Landroid/os/IBinder;)V
        //   34: aload 5
        //   36: iload_2
        //   37: invokevirtual 47	android/os/Parcel:writeInt	(I)V
        //   40: aload 5
        //   42: aload_3
        //   43: invokevirtual 64	android/os/Parcel:writeString	(Ljava/lang/String;)V
        //   46: aload 5
        //   48: aload 4
        //   50: invokevirtual 64	android/os/Parcel:writeString	(Ljava/lang/String;)V
        //   53: aload_0
        //   54: getfield 18	com/google/android/gms/common/internal/l$a$a:lb	Landroid/os/IBinder;
        //   57: bipush 34
        //   59: aload 5
        //   61: aload 6
        //   63: iconst_0
        //   64: invokeinterface 53 5 0
        //   69: pop
        //   70: aload 6
        //   72: invokevirtual 56	android/os/Parcel:readException	()V
        //   75: aload 6
        //   77: invokevirtual 59	android/os/Parcel:recycle	()V
        //   80: aload 5
        //   82: invokevirtual 59	android/os/Parcel:recycle	()V
        //   85: return
        //   86: aconst_null
        //   87: astore_1
        //   88: goto -60 -> 28
        //   91: astore_1
        //   92: aload 6
        //   94: invokevirtual 59	android/os/Parcel:recycle	()V
        //   97: aload 5
        //   99: invokevirtual 59	android/os/Parcel:recycle	()V
        //   102: aload_1
        //   103: athrow
        // Local variable table:
        //   start	length	slot	name	signature
        //   0	104	0	this	a
        //   0	104	1	paramk	k
        //   0	104	2	paramInt	int
        //   0	104	3	paramString1	String
        //   0	104	4	paramString2	String
        //   3	95	5	localParcel1	Parcel
        //   8	85	6	localParcel2	Parcel
        // Exception table:
        //   from	to	target	type
        //   10	17	91	finally
        //   21	28	91	finally
        //   28	75	91	finally
      }
      
      /* Error */
      public void a(k paramk, int paramInt, String paramString1, String paramString2, String paramString3, String[] paramArrayOfString)
        throws RemoteException
      {
        // Byte code:
        //   0: invokestatic 28	android/os/Parcel:obtain	()Landroid/os/Parcel;
        //   3: astore 7
        //   5: invokestatic 28	android/os/Parcel:obtain	()Landroid/os/Parcel;
        //   8: astore 8
        //   10: aload 7
        //   12: ldc 30
        //   14: invokevirtual 34	android/os/Parcel:writeInterfaceToken	(Ljava/lang/String;)V
        //   17: aload_1
        //   18: ifnull +82 -> 100
        //   21: aload_1
        //   22: invokeinterface 40 1 0
        //   27: astore_1
        //   28: aload 7
        //   30: aload_1
        //   31: invokevirtual 43	android/os/Parcel:writeStrongBinder	(Landroid/os/IBinder;)V
        //   34: aload 7
        //   36: iload_2
        //   37: invokevirtual 47	android/os/Parcel:writeInt	(I)V
        //   40: aload 7
        //   42: aload_3
        //   43: invokevirtual 64	android/os/Parcel:writeString	(Ljava/lang/String;)V
        //   46: aload 7
        //   48: aload 4
        //   50: invokevirtual 64	android/os/Parcel:writeString	(Ljava/lang/String;)V
        //   53: aload 7
        //   55: aload 5
        //   57: invokevirtual 64	android/os/Parcel:writeString	(Ljava/lang/String;)V
        //   60: aload 7
        //   62: aload 6
        //   64: invokevirtual 78	android/os/Parcel:writeStringArray	([Ljava/lang/String;)V
        //   67: aload_0
        //   68: getfield 18	com/google/android/gms/common/internal/l$a$a:lb	Landroid/os/IBinder;
        //   71: bipush 33
        //   73: aload 7
        //   75: aload 8
        //   77: iconst_0
        //   78: invokeinterface 53 5 0
        //   83: pop
        //   84: aload 8
        //   86: invokevirtual 56	android/os/Parcel:readException	()V
        //   89: aload 8
        //   91: invokevirtual 59	android/os/Parcel:recycle	()V
        //   94: aload 7
        //   96: invokevirtual 59	android/os/Parcel:recycle	()V
        //   99: return
        //   100: aconst_null
        //   101: astore_1
        //   102: goto -74 -> 28
        //   105: astore_1
        //   106: aload 8
        //   108: invokevirtual 59	android/os/Parcel:recycle	()V
        //   111: aload 7
        //   113: invokevirtual 59	android/os/Parcel:recycle	()V
        //   116: aload_1
        //   117: athrow
        // Local variable table:
        //   start	length	slot	name	signature
        //   0	118	0	this	a
        //   0	118	1	paramk	k
        //   0	118	2	paramInt	int
        //   0	118	3	paramString1	String
        //   0	118	4	paramString2	String
        //   0	118	5	paramString3	String
        //   0	118	6	paramArrayOfString	String[]
        //   3	109	7	localParcel1	Parcel
        //   8	99	8	localParcel2	Parcel
        // Exception table:
        //   from	to	target	type
        //   10	17	105	finally
        //   21	28	105	finally
        //   28	89	105	finally
      }
      
      /* Error */
      public void a(k paramk, int paramInt, String paramString1, String paramString2, String[] paramArrayOfString)
        throws RemoteException
      {
        // Byte code:
        //   0: invokestatic 28	android/os/Parcel:obtain	()Landroid/os/Parcel;
        //   3: astore 7
        //   5: invokestatic 28	android/os/Parcel:obtain	()Landroid/os/Parcel;
        //   8: astore 6
        //   10: aload 7
        //   12: ldc 30
        //   14: invokevirtual 34	android/os/Parcel:writeInterfaceToken	(Ljava/lang/String;)V
        //   17: aload_1
        //   18: ifnull +75 -> 93
        //   21: aload_1
        //   22: invokeinterface 40 1 0
        //   27: astore_1
        //   28: aload 7
        //   30: aload_1
        //   31: invokevirtual 43	android/os/Parcel:writeStrongBinder	(Landroid/os/IBinder;)V
        //   34: aload 7
        //   36: iload_2
        //   37: invokevirtual 47	android/os/Parcel:writeInt	(I)V
        //   40: aload 7
        //   42: aload_3
        //   43: invokevirtual 64	android/os/Parcel:writeString	(Ljava/lang/String;)V
        //   46: aload 7
        //   48: aload 4
        //   50: invokevirtual 64	android/os/Parcel:writeString	(Ljava/lang/String;)V
        //   53: aload 7
        //   55: aload 5
        //   57: invokevirtual 78	android/os/Parcel:writeStringArray	([Ljava/lang/String;)V
        //   60: aload_0
        //   61: getfield 18	com/google/android/gms/common/internal/l$a$a:lb	Landroid/os/IBinder;
        //   64: bipush 10
        //   66: aload 7
        //   68: aload 6
        //   70: iconst_0
        //   71: invokeinterface 53 5 0
        //   76: pop
        //   77: aload 6
        //   79: invokevirtual 56	android/os/Parcel:readException	()V
        //   82: aload 6
        //   84: invokevirtual 59	android/os/Parcel:recycle	()V
        //   87: aload 7
        //   89: invokevirtual 59	android/os/Parcel:recycle	()V
        //   92: return
        //   93: aconst_null
        //   94: astore_1
        //   95: goto -67 -> 28
        //   98: astore_1
        //   99: aload 6
        //   101: invokevirtual 59	android/os/Parcel:recycle	()V
        //   104: aload 7
        //   106: invokevirtual 59	android/os/Parcel:recycle	()V
        //   109: aload_1
        //   110: athrow
        // Local variable table:
        //   start	length	slot	name	signature
        //   0	111	0	this	a
        //   0	111	1	paramk	k
        //   0	111	2	paramInt	int
        //   0	111	3	paramString1	String
        //   0	111	4	paramString2	String
        //   0	111	5	paramArrayOfString	String[]
        //   8	92	6	localParcel1	Parcel
        //   3	102	7	localParcel2	Parcel
        // Exception table:
        //   from	to	target	type
        //   10	17	98	finally
        //   21	28	98	finally
        //   28	82	98	finally
      }
      
      /* Error */
      public void a(k paramk, int paramInt, String paramString1, String paramString2, String[] paramArrayOfString, Bundle paramBundle)
        throws RemoteException
      {
        // Byte code:
        //   0: invokestatic 28	android/os/Parcel:obtain	()Landroid/os/Parcel;
        //   3: astore 7
        //   5: invokestatic 28	android/os/Parcel:obtain	()Landroid/os/Parcel;
        //   8: astore 8
        //   10: aload 7
        //   12: ldc 30
        //   14: invokevirtual 34	android/os/Parcel:writeInterfaceToken	(Ljava/lang/String;)V
        //   17: aload_1
        //   18: ifnull +94 -> 112
        //   21: aload_1
        //   22: invokeinterface 40 1 0
        //   27: astore_1
        //   28: aload 7
        //   30: aload_1
        //   31: invokevirtual 43	android/os/Parcel:writeStrongBinder	(Landroid/os/IBinder;)V
        //   34: aload 7
        //   36: iload_2
        //   37: invokevirtual 47	android/os/Parcel:writeInt	(I)V
        //   40: aload 7
        //   42: aload_3
        //   43: invokevirtual 64	android/os/Parcel:writeString	(Ljava/lang/String;)V
        //   46: aload 7
        //   48: aload 4
        //   50: invokevirtual 64	android/os/Parcel:writeString	(Ljava/lang/String;)V
        //   53: aload 7
        //   55: aload 5
        //   57: invokevirtual 78	android/os/Parcel:writeStringArray	([Ljava/lang/String;)V
        //   60: aload 6
        //   62: ifnull +55 -> 117
        //   65: aload 7
        //   67: iconst_1
        //   68: invokevirtual 47	android/os/Parcel:writeInt	(I)V
        //   71: aload 6
        //   73: aload 7
        //   75: iconst_0
        //   76: invokevirtual 71	android/os/Bundle:writeToParcel	(Landroid/os/Parcel;I)V
        //   79: aload_0
        //   80: getfield 18	com/google/android/gms/common/internal/l$a$a:lb	Landroid/os/IBinder;
        //   83: bipush 30
        //   85: aload 7
        //   87: aload 8
        //   89: iconst_0
        //   90: invokeinterface 53 5 0
        //   95: pop
        //   96: aload 8
        //   98: invokevirtual 56	android/os/Parcel:readException	()V
        //   101: aload 8
        //   103: invokevirtual 59	android/os/Parcel:recycle	()V
        //   106: aload 7
        //   108: invokevirtual 59	android/os/Parcel:recycle	()V
        //   111: return
        //   112: aconst_null
        //   113: astore_1
        //   114: goto -86 -> 28
        //   117: aload 7
        //   119: iconst_0
        //   120: invokevirtual 47	android/os/Parcel:writeInt	(I)V
        //   123: goto -44 -> 79
        //   126: astore_1
        //   127: aload 8
        //   129: invokevirtual 59	android/os/Parcel:recycle	()V
        //   132: aload 7
        //   134: invokevirtual 59	android/os/Parcel:recycle	()V
        //   137: aload_1
        //   138: athrow
        // Local variable table:
        //   start	length	slot	name	signature
        //   0	139	0	this	a
        //   0	139	1	paramk	k
        //   0	139	2	paramInt	int
        //   0	139	3	paramString1	String
        //   0	139	4	paramString2	String
        //   0	139	5	paramArrayOfString	String[]
        //   0	139	6	paramBundle	Bundle
        //   3	130	7	localParcel1	Parcel
        //   8	120	8	localParcel2	Parcel
        // Exception table:
        //   from	to	target	type
        //   10	17	126	finally
        //   21	28	126	finally
        //   28	60	126	finally
        //   65	79	126	finally
        //   79	101	126	finally
        //   117	123	126	finally
      }
      
      /* Error */
      public void a(k paramk, int paramInt, String paramString1, String paramString2, String[] paramArrayOfString, String paramString3, Bundle paramBundle)
        throws RemoteException
      {
        // Byte code:
        //   0: invokestatic 28	android/os/Parcel:obtain	()Landroid/os/Parcel;
        //   3: astore 9
        //   5: invokestatic 28	android/os/Parcel:obtain	()Landroid/os/Parcel;
        //   8: astore 8
        //   10: aload 9
        //   12: ldc 30
        //   14: invokevirtual 34	android/os/Parcel:writeInterfaceToken	(Ljava/lang/String;)V
        //   17: aload_1
        //   18: ifnull +100 -> 118
        //   21: aload_1
        //   22: invokeinterface 40 1 0
        //   27: astore_1
        //   28: aload 9
        //   30: aload_1
        //   31: invokevirtual 43	android/os/Parcel:writeStrongBinder	(Landroid/os/IBinder;)V
        //   34: aload 9
        //   36: iload_2
        //   37: invokevirtual 47	android/os/Parcel:writeInt	(I)V
        //   40: aload 9
        //   42: aload_3
        //   43: invokevirtual 64	android/os/Parcel:writeString	(Ljava/lang/String;)V
        //   46: aload 9
        //   48: aload 4
        //   50: invokevirtual 64	android/os/Parcel:writeString	(Ljava/lang/String;)V
        //   53: aload 9
        //   55: aload 5
        //   57: invokevirtual 78	android/os/Parcel:writeStringArray	([Ljava/lang/String;)V
        //   60: aload 9
        //   62: aload 6
        //   64: invokevirtual 64	android/os/Parcel:writeString	(Ljava/lang/String;)V
        //   67: aload 7
        //   69: ifnull +54 -> 123
        //   72: aload 9
        //   74: iconst_1
        //   75: invokevirtual 47	android/os/Parcel:writeInt	(I)V
        //   78: aload 7
        //   80: aload 9
        //   82: iconst_0
        //   83: invokevirtual 71	android/os/Bundle:writeToParcel	(Landroid/os/Parcel;I)V
        //   86: aload_0
        //   87: getfield 18	com/google/android/gms/common/internal/l$a$a:lb	Landroid/os/IBinder;
        //   90: iconst_1
        //   91: aload 9
        //   93: aload 8
        //   95: iconst_0
        //   96: invokeinterface 53 5 0
        //   101: pop
        //   102: aload 8
        //   104: invokevirtual 56	android/os/Parcel:readException	()V
        //   107: aload 8
        //   109: invokevirtual 59	android/os/Parcel:recycle	()V
        //   112: aload 9
        //   114: invokevirtual 59	android/os/Parcel:recycle	()V
        //   117: return
        //   118: aconst_null
        //   119: astore_1
        //   120: goto -92 -> 28
        //   123: aload 9
        //   125: iconst_0
        //   126: invokevirtual 47	android/os/Parcel:writeInt	(I)V
        //   129: goto -43 -> 86
        //   132: astore_1
        //   133: aload 8
        //   135: invokevirtual 59	android/os/Parcel:recycle	()V
        //   138: aload 9
        //   140: invokevirtual 59	android/os/Parcel:recycle	()V
        //   143: aload_1
        //   144: athrow
        // Local variable table:
        //   start	length	slot	name	signature
        //   0	145	0	this	a
        //   0	145	1	paramk	k
        //   0	145	2	paramInt	int
        //   0	145	3	paramString1	String
        //   0	145	4	paramString2	String
        //   0	145	5	paramArrayOfString	String[]
        //   0	145	6	paramString3	String
        //   0	145	7	paramBundle	Bundle
        //   8	126	8	localParcel1	Parcel
        //   3	136	9	localParcel2	Parcel
        // Exception table:
        //   from	to	target	type
        //   10	17	132	finally
        //   21	28	132	finally
        //   28	67	132	finally
        //   72	86	132	finally
        //   86	107	132	finally
        //   123	129	132	finally
      }
      
      /* Error */
      public void a(k paramk, int paramInt, String paramString1, String paramString2, String[] paramArrayOfString, String paramString3, IBinder paramIBinder, String paramString4, Bundle paramBundle)
        throws RemoteException
      {
        // Byte code:
        //   0: invokestatic 28	android/os/Parcel:obtain	()Landroid/os/Parcel;
        //   3: astore 10
        //   5: invokestatic 28	android/os/Parcel:obtain	()Landroid/os/Parcel;
        //   8: astore 11
        //   10: aload 10
        //   12: ldc 30
        //   14: invokevirtual 34	android/os/Parcel:writeInterfaceToken	(Ljava/lang/String;)V
        //   17: aload_1
        //   18: ifnull +115 -> 133
        //   21: aload_1
        //   22: invokeinterface 40 1 0
        //   27: astore_1
        //   28: aload 10
        //   30: aload_1
        //   31: invokevirtual 43	android/os/Parcel:writeStrongBinder	(Landroid/os/IBinder;)V
        //   34: aload 10
        //   36: iload_2
        //   37: invokevirtual 47	android/os/Parcel:writeInt	(I)V
        //   40: aload 10
        //   42: aload_3
        //   43: invokevirtual 64	android/os/Parcel:writeString	(Ljava/lang/String;)V
        //   46: aload 10
        //   48: aload 4
        //   50: invokevirtual 64	android/os/Parcel:writeString	(Ljava/lang/String;)V
        //   53: aload 10
        //   55: aload 5
        //   57: invokevirtual 78	android/os/Parcel:writeStringArray	([Ljava/lang/String;)V
        //   60: aload 10
        //   62: aload 6
        //   64: invokevirtual 64	android/os/Parcel:writeString	(Ljava/lang/String;)V
        //   67: aload 10
        //   69: aload 7
        //   71: invokevirtual 43	android/os/Parcel:writeStrongBinder	(Landroid/os/IBinder;)V
        //   74: aload 10
        //   76: aload 8
        //   78: invokevirtual 64	android/os/Parcel:writeString	(Ljava/lang/String;)V
        //   81: aload 9
        //   83: ifnull +55 -> 138
        //   86: aload 10
        //   88: iconst_1
        //   89: invokevirtual 47	android/os/Parcel:writeInt	(I)V
        //   92: aload 9
        //   94: aload 10
        //   96: iconst_0
        //   97: invokevirtual 71	android/os/Bundle:writeToParcel	(Landroid/os/Parcel;I)V
        //   100: aload_0
        //   101: getfield 18	com/google/android/gms/common/internal/l$a$a:lb	Landroid/os/IBinder;
        //   104: bipush 9
        //   106: aload 10
        //   108: aload 11
        //   110: iconst_0
        //   111: invokeinterface 53 5 0
        //   116: pop
        //   117: aload 11
        //   119: invokevirtual 56	android/os/Parcel:readException	()V
        //   122: aload 11
        //   124: invokevirtual 59	android/os/Parcel:recycle	()V
        //   127: aload 10
        //   129: invokevirtual 59	android/os/Parcel:recycle	()V
        //   132: return
        //   133: aconst_null
        //   134: astore_1
        //   135: goto -107 -> 28
        //   138: aload 10
        //   140: iconst_0
        //   141: invokevirtual 47	android/os/Parcel:writeInt	(I)V
        //   144: goto -44 -> 100
        //   147: astore_1
        //   148: aload 11
        //   150: invokevirtual 59	android/os/Parcel:recycle	()V
        //   153: aload 10
        //   155: invokevirtual 59	android/os/Parcel:recycle	()V
        //   158: aload_1
        //   159: athrow
        // Local variable table:
        //   start	length	slot	name	signature
        //   0	160	0	this	a
        //   0	160	1	paramk	k
        //   0	160	2	paramInt	int
        //   0	160	3	paramString1	String
        //   0	160	4	paramString2	String
        //   0	160	5	paramArrayOfString	String[]
        //   0	160	6	paramString3	String
        //   0	160	7	paramIBinder	IBinder
        //   0	160	8	paramString4	String
        //   0	160	9	paramBundle	Bundle
        //   3	151	10	localParcel1	Parcel
        //   8	141	11	localParcel2	Parcel
        // Exception table:
        //   from	to	target	type
        //   10	17	147	finally
        //   21	28	147	finally
        //   28	81	147	finally
        //   86	100	147	finally
        //   100	122	147	finally
        //   138	144	147	finally
      }
      
      /* Error */
      public void a(k paramk, int paramInt, String paramString1, String[] paramArrayOfString, String paramString2, Bundle paramBundle)
        throws RemoteException
      {
        // Byte code:
        //   0: invokestatic 28	android/os/Parcel:obtain	()Landroid/os/Parcel;
        //   3: astore 8
        //   5: invokestatic 28	android/os/Parcel:obtain	()Landroid/os/Parcel;
        //   8: astore 7
        //   10: aload 8
        //   12: ldc 30
        //   14: invokevirtual 34	android/os/Parcel:writeInterfaceToken	(Ljava/lang/String;)V
        //   17: aload_1
        //   18: ifnull +94 -> 112
        //   21: aload_1
        //   22: invokeinterface 40 1 0
        //   27: astore_1
        //   28: aload 8
        //   30: aload_1
        //   31: invokevirtual 43	android/os/Parcel:writeStrongBinder	(Landroid/os/IBinder;)V
        //   34: aload 8
        //   36: iload_2
        //   37: invokevirtual 47	android/os/Parcel:writeInt	(I)V
        //   40: aload 8
        //   42: aload_3
        //   43: invokevirtual 64	android/os/Parcel:writeString	(Ljava/lang/String;)V
        //   46: aload 8
        //   48: aload 4
        //   50: invokevirtual 78	android/os/Parcel:writeStringArray	([Ljava/lang/String;)V
        //   53: aload 8
        //   55: aload 5
        //   57: invokevirtual 64	android/os/Parcel:writeString	(Ljava/lang/String;)V
        //   60: aload 6
        //   62: ifnull +55 -> 117
        //   65: aload 8
        //   67: iconst_1
        //   68: invokevirtual 47	android/os/Parcel:writeInt	(I)V
        //   71: aload 6
        //   73: aload 8
        //   75: iconst_0
        //   76: invokevirtual 71	android/os/Bundle:writeToParcel	(Landroid/os/Parcel;I)V
        //   79: aload_0
        //   80: getfield 18	com/google/android/gms/common/internal/l$a$a:lb	Landroid/os/IBinder;
        //   83: bipush 20
        //   85: aload 8
        //   87: aload 7
        //   89: iconst_0
        //   90: invokeinterface 53 5 0
        //   95: pop
        //   96: aload 7
        //   98: invokevirtual 56	android/os/Parcel:readException	()V
        //   101: aload 7
        //   103: invokevirtual 59	android/os/Parcel:recycle	()V
        //   106: aload 8
        //   108: invokevirtual 59	android/os/Parcel:recycle	()V
        //   111: return
        //   112: aconst_null
        //   113: astore_1
        //   114: goto -86 -> 28
        //   117: aload 8
        //   119: iconst_0
        //   120: invokevirtual 47	android/os/Parcel:writeInt	(I)V
        //   123: goto -44 -> 79
        //   126: astore_1
        //   127: aload 7
        //   129: invokevirtual 59	android/os/Parcel:recycle	()V
        //   132: aload 8
        //   134: invokevirtual 59	android/os/Parcel:recycle	()V
        //   137: aload_1
        //   138: athrow
        // Local variable table:
        //   start	length	slot	name	signature
        //   0	139	0	this	a
        //   0	139	1	paramk	k
        //   0	139	2	paramInt	int
        //   0	139	3	paramString1	String
        //   0	139	4	paramArrayOfString	String[]
        //   0	139	5	paramString2	String
        //   0	139	6	paramBundle	Bundle
        //   8	120	7	localParcel1	Parcel
        //   3	130	8	localParcel2	Parcel
        // Exception table:
        //   from	to	target	type
        //   10	17	126	finally
        //   21	28	126	finally
        //   28	60	126	finally
        //   65	79	126	finally
        //   79	101	126	finally
        //   117	123	126	finally
      }
      
      public IBinder asBinder()
      {
        return this.lb;
      }
      
      /* Error */
      public void b(k paramk, int paramInt, String paramString)
        throws RemoteException
      {
        // Byte code:
        //   0: invokestatic 28	android/os/Parcel:obtain	()Landroid/os/Parcel;
        //   3: astore 4
        //   5: invokestatic 28	android/os/Parcel:obtain	()Landroid/os/Parcel;
        //   8: astore 5
        //   10: aload 4
        //   12: ldc 30
        //   14: invokevirtual 34	android/os/Parcel:writeInterfaceToken	(Ljava/lang/String;)V
        //   17: aload_1
        //   18: ifnull +61 -> 79
        //   21: aload_1
        //   22: invokeinterface 40 1 0
        //   27: astore_1
        //   28: aload 4
        //   30: aload_1
        //   31: invokevirtual 43	android/os/Parcel:writeStrongBinder	(Landroid/os/IBinder;)V
        //   34: aload 4
        //   36: iload_2
        //   37: invokevirtual 47	android/os/Parcel:writeInt	(I)V
        //   40: aload 4
        //   42: aload_3
        //   43: invokevirtual 64	android/os/Parcel:writeString	(Ljava/lang/String;)V
        //   46: aload_0
        //   47: getfield 18	com/google/android/gms/common/internal/l$a$a:lb	Landroid/os/IBinder;
        //   50: bipush 21
        //   52: aload 4
        //   54: aload 5
        //   56: iconst_0
        //   57: invokeinterface 53 5 0
        //   62: pop
        //   63: aload 5
        //   65: invokevirtual 56	android/os/Parcel:readException	()V
        //   68: aload 5
        //   70: invokevirtual 59	android/os/Parcel:recycle	()V
        //   73: aload 4
        //   75: invokevirtual 59	android/os/Parcel:recycle	()V
        //   78: return
        //   79: aconst_null
        //   80: astore_1
        //   81: goto -53 -> 28
        //   84: astore_1
        //   85: aload 5
        //   87: invokevirtual 59	android/os/Parcel:recycle	()V
        //   90: aload 4
        //   92: invokevirtual 59	android/os/Parcel:recycle	()V
        //   95: aload_1
        //   96: athrow
        // Local variable table:
        //   start	length	slot	name	signature
        //   0	97	0	this	a
        //   0	97	1	paramk	k
        //   0	97	2	paramInt	int
        //   0	97	3	paramString	String
        //   3	88	4	localParcel1	Parcel
        //   8	78	5	localParcel2	Parcel
        // Exception table:
        //   from	to	target	type
        //   10	17	84	finally
        //   21	28	84	finally
        //   28	68	84	finally
      }
      
      /* Error */
      public void b(k paramk, int paramInt, String paramString, Bundle paramBundle)
        throws RemoteException
      {
        // Byte code:
        //   0: invokestatic 28	android/os/Parcel:obtain	()Landroid/os/Parcel;
        //   3: astore 6
        //   5: invokestatic 28	android/os/Parcel:obtain	()Landroid/os/Parcel;
        //   8: astore 5
        //   10: aload 6
        //   12: ldc 30
        //   14: invokevirtual 34	android/os/Parcel:writeInterfaceToken	(Ljava/lang/String;)V
        //   17: aload_1
        //   18: ifnull +79 -> 97
        //   21: aload_1
        //   22: invokeinterface 40 1 0
        //   27: astore_1
        //   28: aload 6
        //   30: aload_1
        //   31: invokevirtual 43	android/os/Parcel:writeStrongBinder	(Landroid/os/IBinder;)V
        //   34: aload 6
        //   36: iload_2
        //   37: invokevirtual 47	android/os/Parcel:writeInt	(I)V
        //   40: aload 6
        //   42: aload_3
        //   43: invokevirtual 64	android/os/Parcel:writeString	(Ljava/lang/String;)V
        //   46: aload 4
        //   48: ifnull +54 -> 102
        //   51: aload 6
        //   53: iconst_1
        //   54: invokevirtual 47	android/os/Parcel:writeInt	(I)V
        //   57: aload 4
        //   59: aload 6
        //   61: iconst_0
        //   62: invokevirtual 71	android/os/Bundle:writeToParcel	(Landroid/os/Parcel;I)V
        //   65: aload_0
        //   66: getfield 18	com/google/android/gms/common/internal/l$a$a:lb	Landroid/os/IBinder;
        //   69: iconst_5
        //   70: aload 6
        //   72: aload 5
        //   74: iconst_0
        //   75: invokeinterface 53 5 0
        //   80: pop
        //   81: aload 5
        //   83: invokevirtual 56	android/os/Parcel:readException	()V
        //   86: aload 5
        //   88: invokevirtual 59	android/os/Parcel:recycle	()V
        //   91: aload 6
        //   93: invokevirtual 59	android/os/Parcel:recycle	()V
        //   96: return
        //   97: aconst_null
        //   98: astore_1
        //   99: goto -71 -> 28
        //   102: aload 6
        //   104: iconst_0
        //   105: invokevirtual 47	android/os/Parcel:writeInt	(I)V
        //   108: goto -43 -> 65
        //   111: astore_1
        //   112: aload 5
        //   114: invokevirtual 59	android/os/Parcel:recycle	()V
        //   117: aload 6
        //   119: invokevirtual 59	android/os/Parcel:recycle	()V
        //   122: aload_1
        //   123: athrow
        // Local variable table:
        //   start	length	slot	name	signature
        //   0	124	0	this	a
        //   0	124	1	paramk	k
        //   0	124	2	paramInt	int
        //   0	124	3	paramString	String
        //   0	124	4	paramBundle	Bundle
        //   8	105	5	localParcel1	Parcel
        //   3	115	6	localParcel2	Parcel
        // Exception table:
        //   from	to	target	type
        //   10	17	111	finally
        //   21	28	111	finally
        //   28	46	111	finally
        //   51	65	111	finally
        //   65	86	111	finally
        //   102	108	111	finally
      }
      
      /* Error */
      public void b(k paramk, int paramInt, String paramString1, String paramString2, String[] paramArrayOfString)
        throws RemoteException
      {
        // Byte code:
        //   0: invokestatic 28	android/os/Parcel:obtain	()Landroid/os/Parcel;
        //   3: astore 7
        //   5: invokestatic 28	android/os/Parcel:obtain	()Landroid/os/Parcel;
        //   8: astore 6
        //   10: aload 7
        //   12: ldc 30
        //   14: invokevirtual 34	android/os/Parcel:writeInterfaceToken	(Ljava/lang/String;)V
        //   17: aload_1
        //   18: ifnull +75 -> 93
        //   21: aload_1
        //   22: invokeinterface 40 1 0
        //   27: astore_1
        //   28: aload 7
        //   30: aload_1
        //   31: invokevirtual 43	android/os/Parcel:writeStrongBinder	(Landroid/os/IBinder;)V
        //   34: aload 7
        //   36: iload_2
        //   37: invokevirtual 47	android/os/Parcel:writeInt	(I)V
        //   40: aload 7
        //   42: aload_3
        //   43: invokevirtual 64	android/os/Parcel:writeString	(Ljava/lang/String;)V
        //   46: aload 7
        //   48: aload 4
        //   50: invokevirtual 64	android/os/Parcel:writeString	(Ljava/lang/String;)V
        //   53: aload 7
        //   55: aload 5
        //   57: invokevirtual 78	android/os/Parcel:writeStringArray	([Ljava/lang/String;)V
        //   60: aload_0
        //   61: getfield 18	com/google/android/gms/common/internal/l$a$a:lb	Landroid/os/IBinder;
        //   64: bipush 28
        //   66: aload 7
        //   68: aload 6
        //   70: iconst_0
        //   71: invokeinterface 53 5 0
        //   76: pop
        //   77: aload 6
        //   79: invokevirtual 56	android/os/Parcel:readException	()V
        //   82: aload 6
        //   84: invokevirtual 59	android/os/Parcel:recycle	()V
        //   87: aload 7
        //   89: invokevirtual 59	android/os/Parcel:recycle	()V
        //   92: return
        //   93: aconst_null
        //   94: astore_1
        //   95: goto -67 -> 28
        //   98: astore_1
        //   99: aload 6
        //   101: invokevirtual 59	android/os/Parcel:recycle	()V
        //   104: aload 7
        //   106: invokevirtual 59	android/os/Parcel:recycle	()V
        //   109: aload_1
        //   110: athrow
        // Local variable table:
        //   start	length	slot	name	signature
        //   0	111	0	this	a
        //   0	111	1	paramk	k
        //   0	111	2	paramInt	int
        //   0	111	3	paramString1	String
        //   0	111	4	paramString2	String
        //   0	111	5	paramArrayOfString	String[]
        //   8	92	6	localParcel1	Parcel
        //   3	102	7	localParcel2	Parcel
        // Exception table:
        //   from	to	target	type
        //   10	17	98	finally
        //   21	28	98	finally
        //   28	82	98	finally
      }
      
      /* Error */
      public void c(k paramk, int paramInt, String paramString)
        throws RemoteException
      {
        // Byte code:
        //   0: invokestatic 28	android/os/Parcel:obtain	()Landroid/os/Parcel;
        //   3: astore 5
        //   5: invokestatic 28	android/os/Parcel:obtain	()Landroid/os/Parcel;
        //   8: astore 4
        //   10: aload 5
        //   12: ldc 30
        //   14: invokevirtual 34	android/os/Parcel:writeInterfaceToken	(Ljava/lang/String;)V
        //   17: aload_1
        //   18: ifnull +61 -> 79
        //   21: aload_1
        //   22: invokeinterface 40 1 0
        //   27: astore_1
        //   28: aload 5
        //   30: aload_1
        //   31: invokevirtual 43	android/os/Parcel:writeStrongBinder	(Landroid/os/IBinder;)V
        //   34: aload 5
        //   36: iload_2
        //   37: invokevirtual 47	android/os/Parcel:writeInt	(I)V
        //   40: aload 5
        //   42: aload_3
        //   43: invokevirtual 64	android/os/Parcel:writeString	(Ljava/lang/String;)V
        //   46: aload_0
        //   47: getfield 18	com/google/android/gms/common/internal/l$a$a:lb	Landroid/os/IBinder;
        //   50: bipush 22
        //   52: aload 5
        //   54: aload 4
        //   56: iconst_0
        //   57: invokeinterface 53 5 0
        //   62: pop
        //   63: aload 4
        //   65: invokevirtual 56	android/os/Parcel:readException	()V
        //   68: aload 4
        //   70: invokevirtual 59	android/os/Parcel:recycle	()V
        //   73: aload 5
        //   75: invokevirtual 59	android/os/Parcel:recycle	()V
        //   78: return
        //   79: aconst_null
        //   80: astore_1
        //   81: goto -53 -> 28
        //   84: astore_1
        //   85: aload 4
        //   87: invokevirtual 59	android/os/Parcel:recycle	()V
        //   90: aload 5
        //   92: invokevirtual 59	android/os/Parcel:recycle	()V
        //   95: aload_1
        //   96: athrow
        // Local variable table:
        //   start	length	slot	name	signature
        //   0	97	0	this	a
        //   0	97	1	paramk	k
        //   0	97	2	paramInt	int
        //   0	97	3	paramString	String
        //   8	78	4	localParcel1	Parcel
        //   3	88	5	localParcel2	Parcel
        // Exception table:
        //   from	to	target	type
        //   10	17	84	finally
        //   21	28	84	finally
        //   28	68	84	finally
      }
      
      /* Error */
      public void c(k paramk, int paramInt, String paramString, Bundle paramBundle)
        throws RemoteException
      {
        // Byte code:
        //   0: invokestatic 28	android/os/Parcel:obtain	()Landroid/os/Parcel;
        //   3: astore 6
        //   5: invokestatic 28	android/os/Parcel:obtain	()Landroid/os/Parcel;
        //   8: astore 5
        //   10: aload 6
        //   12: ldc 30
        //   14: invokevirtual 34	android/os/Parcel:writeInterfaceToken	(Ljava/lang/String;)V
        //   17: aload_1
        //   18: ifnull +80 -> 98
        //   21: aload_1
        //   22: invokeinterface 40 1 0
        //   27: astore_1
        //   28: aload 6
        //   30: aload_1
        //   31: invokevirtual 43	android/os/Parcel:writeStrongBinder	(Landroid/os/IBinder;)V
        //   34: aload 6
        //   36: iload_2
        //   37: invokevirtual 47	android/os/Parcel:writeInt	(I)V
        //   40: aload 6
        //   42: aload_3
        //   43: invokevirtual 64	android/os/Parcel:writeString	(Ljava/lang/String;)V
        //   46: aload 4
        //   48: ifnull +55 -> 103
        //   51: aload 6
        //   53: iconst_1
        //   54: invokevirtual 47	android/os/Parcel:writeInt	(I)V
        //   57: aload 4
        //   59: aload 6
        //   61: iconst_0
        //   62: invokevirtual 71	android/os/Bundle:writeToParcel	(Landroid/os/Parcel;I)V
        //   65: aload_0
        //   66: getfield 18	com/google/android/gms/common/internal/l$a$a:lb	Landroid/os/IBinder;
        //   69: bipush 6
        //   71: aload 6
        //   73: aload 5
        //   75: iconst_0
        //   76: invokeinterface 53 5 0
        //   81: pop
        //   82: aload 5
        //   84: invokevirtual 56	android/os/Parcel:readException	()V
        //   87: aload 5
        //   89: invokevirtual 59	android/os/Parcel:recycle	()V
        //   92: aload 6
        //   94: invokevirtual 59	android/os/Parcel:recycle	()V
        //   97: return
        //   98: aconst_null
        //   99: astore_1
        //   100: goto -72 -> 28
        //   103: aload 6
        //   105: iconst_0
        //   106: invokevirtual 47	android/os/Parcel:writeInt	(I)V
        //   109: goto -44 -> 65
        //   112: astore_1
        //   113: aload 5
        //   115: invokevirtual 59	android/os/Parcel:recycle	()V
        //   118: aload 6
        //   120: invokevirtual 59	android/os/Parcel:recycle	()V
        //   123: aload_1
        //   124: athrow
        // Local variable table:
        //   start	length	slot	name	signature
        //   0	125	0	this	a
        //   0	125	1	paramk	k
        //   0	125	2	paramInt	int
        //   0	125	3	paramString	String
        //   0	125	4	paramBundle	Bundle
        //   8	106	5	localParcel1	Parcel
        //   3	116	6	localParcel2	Parcel
        // Exception table:
        //   from	to	target	type
        //   10	17	112	finally
        //   21	28	112	finally
        //   28	46	112	finally
        //   51	65	112	finally
        //   65	87	112	finally
        //   103	109	112	finally
      }
      
      /* Error */
      public void d(k paramk, int paramInt, String paramString)
        throws RemoteException
      {
        // Byte code:
        //   0: invokestatic 28	android/os/Parcel:obtain	()Landroid/os/Parcel;
        //   3: astore 5
        //   5: invokestatic 28	android/os/Parcel:obtain	()Landroid/os/Parcel;
        //   8: astore 4
        //   10: aload 5
        //   12: ldc 30
        //   14: invokevirtual 34	android/os/Parcel:writeInterfaceToken	(Ljava/lang/String;)V
        //   17: aload_1
        //   18: ifnull +61 -> 79
        //   21: aload_1
        //   22: invokeinterface 40 1 0
        //   27: astore_1
        //   28: aload 5
        //   30: aload_1
        //   31: invokevirtual 43	android/os/Parcel:writeStrongBinder	(Landroid/os/IBinder;)V
        //   34: aload 5
        //   36: iload_2
        //   37: invokevirtual 47	android/os/Parcel:writeInt	(I)V
        //   40: aload 5
        //   42: aload_3
        //   43: invokevirtual 64	android/os/Parcel:writeString	(Ljava/lang/String;)V
        //   46: aload_0
        //   47: getfield 18	com/google/android/gms/common/internal/l$a$a:lb	Landroid/os/IBinder;
        //   50: bipush 24
        //   52: aload 5
        //   54: aload 4
        //   56: iconst_0
        //   57: invokeinterface 53 5 0
        //   62: pop
        //   63: aload 4
        //   65: invokevirtual 56	android/os/Parcel:readException	()V
        //   68: aload 4
        //   70: invokevirtual 59	android/os/Parcel:recycle	()V
        //   73: aload 5
        //   75: invokevirtual 59	android/os/Parcel:recycle	()V
        //   78: return
        //   79: aconst_null
        //   80: astore_1
        //   81: goto -53 -> 28
        //   84: astore_1
        //   85: aload 4
        //   87: invokevirtual 59	android/os/Parcel:recycle	()V
        //   90: aload 5
        //   92: invokevirtual 59	android/os/Parcel:recycle	()V
        //   95: aload_1
        //   96: athrow
        // Local variable table:
        //   start	length	slot	name	signature
        //   0	97	0	this	a
        //   0	97	1	paramk	k
        //   0	97	2	paramInt	int
        //   0	97	3	paramString	String
        //   8	78	4	localParcel1	Parcel
        //   3	88	5	localParcel2	Parcel
        // Exception table:
        //   from	to	target	type
        //   10	17	84	finally
        //   21	28	84	finally
        //   28	68	84	finally
      }
      
      /* Error */
      public void d(k paramk, int paramInt, String paramString, Bundle paramBundle)
        throws RemoteException
      {
        // Byte code:
        //   0: invokestatic 28	android/os/Parcel:obtain	()Landroid/os/Parcel;
        //   3: astore 5
        //   5: invokestatic 28	android/os/Parcel:obtain	()Landroid/os/Parcel;
        //   8: astore 6
        //   10: aload 5
        //   12: ldc 30
        //   14: invokevirtual 34	android/os/Parcel:writeInterfaceToken	(Ljava/lang/String;)V
        //   17: aload_1
        //   18: ifnull +80 -> 98
        //   21: aload_1
        //   22: invokeinterface 40 1 0
        //   27: astore_1
        //   28: aload 5
        //   30: aload_1
        //   31: invokevirtual 43	android/os/Parcel:writeStrongBinder	(Landroid/os/IBinder;)V
        //   34: aload 5
        //   36: iload_2
        //   37: invokevirtual 47	android/os/Parcel:writeInt	(I)V
        //   40: aload 5
        //   42: aload_3
        //   43: invokevirtual 64	android/os/Parcel:writeString	(Ljava/lang/String;)V
        //   46: aload 4
        //   48: ifnull +55 -> 103
        //   51: aload 5
        //   53: iconst_1
        //   54: invokevirtual 47	android/os/Parcel:writeInt	(I)V
        //   57: aload 4
        //   59: aload 5
        //   61: iconst_0
        //   62: invokevirtual 71	android/os/Bundle:writeToParcel	(Landroid/os/Parcel;I)V
        //   65: aload_0
        //   66: getfield 18	com/google/android/gms/common/internal/l$a$a:lb	Landroid/os/IBinder;
        //   69: bipush 7
        //   71: aload 5
        //   73: aload 6
        //   75: iconst_0
        //   76: invokeinterface 53 5 0
        //   81: pop
        //   82: aload 6
        //   84: invokevirtual 56	android/os/Parcel:readException	()V
        //   87: aload 6
        //   89: invokevirtual 59	android/os/Parcel:recycle	()V
        //   92: aload 5
        //   94: invokevirtual 59	android/os/Parcel:recycle	()V
        //   97: return
        //   98: aconst_null
        //   99: astore_1
        //   100: goto -72 -> 28
        //   103: aload 5
        //   105: iconst_0
        //   106: invokevirtual 47	android/os/Parcel:writeInt	(I)V
        //   109: goto -44 -> 65
        //   112: astore_1
        //   113: aload 6
        //   115: invokevirtual 59	android/os/Parcel:recycle	()V
        //   118: aload 5
        //   120: invokevirtual 59	android/os/Parcel:recycle	()V
        //   123: aload_1
        //   124: athrow
        // Local variable table:
        //   start	length	slot	name	signature
        //   0	125	0	this	a
        //   0	125	1	paramk	k
        //   0	125	2	paramInt	int
        //   0	125	3	paramString	String
        //   0	125	4	paramBundle	Bundle
        //   3	116	5	localParcel1	Parcel
        //   8	106	6	localParcel2	Parcel
        // Exception table:
        //   from	to	target	type
        //   10	17	112	finally
        //   21	28	112	finally
        //   28	46	112	finally
        //   51	65	112	finally
        //   65	87	112	finally
        //   103	109	112	finally
      }
      
      /* Error */
      public void e(k paramk, int paramInt, String paramString)
        throws RemoteException
      {
        // Byte code:
        //   0: invokestatic 28	android/os/Parcel:obtain	()Landroid/os/Parcel;
        //   3: astore 4
        //   5: invokestatic 28	android/os/Parcel:obtain	()Landroid/os/Parcel;
        //   8: astore 5
        //   10: aload 4
        //   12: ldc 30
        //   14: invokevirtual 34	android/os/Parcel:writeInterfaceToken	(Ljava/lang/String;)V
        //   17: aload_1
        //   18: ifnull +61 -> 79
        //   21: aload_1
        //   22: invokeinterface 40 1 0
        //   27: astore_1
        //   28: aload 4
        //   30: aload_1
        //   31: invokevirtual 43	android/os/Parcel:writeStrongBinder	(Landroid/os/IBinder;)V
        //   34: aload 4
        //   36: iload_2
        //   37: invokevirtual 47	android/os/Parcel:writeInt	(I)V
        //   40: aload 4
        //   42: aload_3
        //   43: invokevirtual 64	android/os/Parcel:writeString	(Ljava/lang/String;)V
        //   46: aload_0
        //   47: getfield 18	com/google/android/gms/common/internal/l$a$a:lb	Landroid/os/IBinder;
        //   50: bipush 26
        //   52: aload 4
        //   54: aload 5
        //   56: iconst_0
        //   57: invokeinterface 53 5 0
        //   62: pop
        //   63: aload 5
        //   65: invokevirtual 56	android/os/Parcel:readException	()V
        //   68: aload 5
        //   70: invokevirtual 59	android/os/Parcel:recycle	()V
        //   73: aload 4
        //   75: invokevirtual 59	android/os/Parcel:recycle	()V
        //   78: return
        //   79: aconst_null
        //   80: astore_1
        //   81: goto -53 -> 28
        //   84: astore_1
        //   85: aload 5
        //   87: invokevirtual 59	android/os/Parcel:recycle	()V
        //   90: aload 4
        //   92: invokevirtual 59	android/os/Parcel:recycle	()V
        //   95: aload_1
        //   96: athrow
        // Local variable table:
        //   start	length	slot	name	signature
        //   0	97	0	this	a
        //   0	97	1	paramk	k
        //   0	97	2	paramInt	int
        //   0	97	3	paramString	String
        //   3	88	4	localParcel1	Parcel
        //   8	78	5	localParcel2	Parcel
        // Exception table:
        //   from	to	target	type
        //   10	17	84	finally
        //   21	28	84	finally
        //   28	68	84	finally
      }
      
      /* Error */
      public void e(k paramk, int paramInt, String paramString, Bundle paramBundle)
        throws RemoteException
      {
        // Byte code:
        //   0: invokestatic 28	android/os/Parcel:obtain	()Landroid/os/Parcel;
        //   3: astore 5
        //   5: invokestatic 28	android/os/Parcel:obtain	()Landroid/os/Parcel;
        //   8: astore 6
        //   10: aload 5
        //   12: ldc 30
        //   14: invokevirtual 34	android/os/Parcel:writeInterfaceToken	(Ljava/lang/String;)V
        //   17: aload_1
        //   18: ifnull +80 -> 98
        //   21: aload_1
        //   22: invokeinterface 40 1 0
        //   27: astore_1
        //   28: aload 5
        //   30: aload_1
        //   31: invokevirtual 43	android/os/Parcel:writeStrongBinder	(Landroid/os/IBinder;)V
        //   34: aload 5
        //   36: iload_2
        //   37: invokevirtual 47	android/os/Parcel:writeInt	(I)V
        //   40: aload 5
        //   42: aload_3
        //   43: invokevirtual 64	android/os/Parcel:writeString	(Ljava/lang/String;)V
        //   46: aload 4
        //   48: ifnull +55 -> 103
        //   51: aload 5
        //   53: iconst_1
        //   54: invokevirtual 47	android/os/Parcel:writeInt	(I)V
        //   57: aload 4
        //   59: aload 5
        //   61: iconst_0
        //   62: invokevirtual 71	android/os/Bundle:writeToParcel	(Landroid/os/Parcel;I)V
        //   65: aload_0
        //   66: getfield 18	com/google/android/gms/common/internal/l$a$a:lb	Landroid/os/IBinder;
        //   69: bipush 8
        //   71: aload 5
        //   73: aload 6
        //   75: iconst_0
        //   76: invokeinterface 53 5 0
        //   81: pop
        //   82: aload 6
        //   84: invokevirtual 56	android/os/Parcel:readException	()V
        //   87: aload 6
        //   89: invokevirtual 59	android/os/Parcel:recycle	()V
        //   92: aload 5
        //   94: invokevirtual 59	android/os/Parcel:recycle	()V
        //   97: return
        //   98: aconst_null
        //   99: astore_1
        //   100: goto -72 -> 28
        //   103: aload 5
        //   105: iconst_0
        //   106: invokevirtual 47	android/os/Parcel:writeInt	(I)V
        //   109: goto -44 -> 65
        //   112: astore_1
        //   113: aload 6
        //   115: invokevirtual 59	android/os/Parcel:recycle	()V
        //   118: aload 5
        //   120: invokevirtual 59	android/os/Parcel:recycle	()V
        //   123: aload_1
        //   124: athrow
        // Local variable table:
        //   start	length	slot	name	signature
        //   0	125	0	this	a
        //   0	125	1	paramk	k
        //   0	125	2	paramInt	int
        //   0	125	3	paramString	String
        //   0	125	4	paramBundle	Bundle
        //   3	116	5	localParcel1	Parcel
        //   8	106	6	localParcel2	Parcel
        // Exception table:
        //   from	to	target	type
        //   10	17	112	finally
        //   21	28	112	finally
        //   28	46	112	finally
        //   51	65	112	finally
        //   65	87	112	finally
        //   103	109	112	finally
      }
      
      /* Error */
      public void f(k paramk, int paramInt, String paramString)
        throws RemoteException
      {
        // Byte code:
        //   0: invokestatic 28	android/os/Parcel:obtain	()Landroid/os/Parcel;
        //   3: astore 5
        //   5: invokestatic 28	android/os/Parcel:obtain	()Landroid/os/Parcel;
        //   8: astore 4
        //   10: aload 5
        //   12: ldc 30
        //   14: invokevirtual 34	android/os/Parcel:writeInterfaceToken	(Ljava/lang/String;)V
        //   17: aload_1
        //   18: ifnull +61 -> 79
        //   21: aload_1
        //   22: invokeinterface 40 1 0
        //   27: astore_1
        //   28: aload 5
        //   30: aload_1
        //   31: invokevirtual 43	android/os/Parcel:writeStrongBinder	(Landroid/os/IBinder;)V
        //   34: aload 5
        //   36: iload_2
        //   37: invokevirtual 47	android/os/Parcel:writeInt	(I)V
        //   40: aload 5
        //   42: aload_3
        //   43: invokevirtual 64	android/os/Parcel:writeString	(Ljava/lang/String;)V
        //   46: aload_0
        //   47: getfield 18	com/google/android/gms/common/internal/l$a$a:lb	Landroid/os/IBinder;
        //   50: bipush 31
        //   52: aload 5
        //   54: aload 4
        //   56: iconst_0
        //   57: invokeinterface 53 5 0
        //   62: pop
        //   63: aload 4
        //   65: invokevirtual 56	android/os/Parcel:readException	()V
        //   68: aload 4
        //   70: invokevirtual 59	android/os/Parcel:recycle	()V
        //   73: aload 5
        //   75: invokevirtual 59	android/os/Parcel:recycle	()V
        //   78: return
        //   79: aconst_null
        //   80: astore_1
        //   81: goto -53 -> 28
        //   84: astore_1
        //   85: aload 4
        //   87: invokevirtual 59	android/os/Parcel:recycle	()V
        //   90: aload 5
        //   92: invokevirtual 59	android/os/Parcel:recycle	()V
        //   95: aload_1
        //   96: athrow
        // Local variable table:
        //   start	length	slot	name	signature
        //   0	97	0	this	a
        //   0	97	1	paramk	k
        //   0	97	2	paramInt	int
        //   0	97	3	paramString	String
        //   8	78	4	localParcel1	Parcel
        //   3	88	5	localParcel2	Parcel
        // Exception table:
        //   from	to	target	type
        //   10	17	84	finally
        //   21	28	84	finally
        //   28	68	84	finally
      }
      
      /* Error */
      public void f(k paramk, int paramInt, String paramString, Bundle paramBundle)
        throws RemoteException
      {
        // Byte code:
        //   0: invokestatic 28	android/os/Parcel:obtain	()Landroid/os/Parcel;
        //   3: astore 5
        //   5: invokestatic 28	android/os/Parcel:obtain	()Landroid/os/Parcel;
        //   8: astore 6
        //   10: aload 5
        //   12: ldc 30
        //   14: invokevirtual 34	android/os/Parcel:writeInterfaceToken	(Ljava/lang/String;)V
        //   17: aload_1
        //   18: ifnull +80 -> 98
        //   21: aload_1
        //   22: invokeinterface 40 1 0
        //   27: astore_1
        //   28: aload 5
        //   30: aload_1
        //   31: invokevirtual 43	android/os/Parcel:writeStrongBinder	(Landroid/os/IBinder;)V
        //   34: aload 5
        //   36: iload_2
        //   37: invokevirtual 47	android/os/Parcel:writeInt	(I)V
        //   40: aload 5
        //   42: aload_3
        //   43: invokevirtual 64	android/os/Parcel:writeString	(Ljava/lang/String;)V
        //   46: aload 4
        //   48: ifnull +55 -> 103
        //   51: aload 5
        //   53: iconst_1
        //   54: invokevirtual 47	android/os/Parcel:writeInt	(I)V
        //   57: aload 4
        //   59: aload 5
        //   61: iconst_0
        //   62: invokevirtual 71	android/os/Bundle:writeToParcel	(Landroid/os/Parcel;I)V
        //   65: aload_0
        //   66: getfield 18	com/google/android/gms/common/internal/l$a$a:lb	Landroid/os/IBinder;
        //   69: bipush 11
        //   71: aload 5
        //   73: aload 6
        //   75: iconst_0
        //   76: invokeinterface 53 5 0
        //   81: pop
        //   82: aload 6
        //   84: invokevirtual 56	android/os/Parcel:readException	()V
        //   87: aload 6
        //   89: invokevirtual 59	android/os/Parcel:recycle	()V
        //   92: aload 5
        //   94: invokevirtual 59	android/os/Parcel:recycle	()V
        //   97: return
        //   98: aconst_null
        //   99: astore_1
        //   100: goto -72 -> 28
        //   103: aload 5
        //   105: iconst_0
        //   106: invokevirtual 47	android/os/Parcel:writeInt	(I)V
        //   109: goto -44 -> 65
        //   112: astore_1
        //   113: aload 6
        //   115: invokevirtual 59	android/os/Parcel:recycle	()V
        //   118: aload 5
        //   120: invokevirtual 59	android/os/Parcel:recycle	()V
        //   123: aload_1
        //   124: athrow
        // Local variable table:
        //   start	length	slot	name	signature
        //   0	125	0	this	a
        //   0	125	1	paramk	k
        //   0	125	2	paramInt	int
        //   0	125	3	paramString	String
        //   0	125	4	paramBundle	Bundle
        //   3	116	5	localParcel1	Parcel
        //   8	106	6	localParcel2	Parcel
        // Exception table:
        //   from	to	target	type
        //   10	17	112	finally
        //   21	28	112	finally
        //   28	46	112	finally
        //   51	65	112	finally
        //   65	87	112	finally
        //   103	109	112	finally
      }
      
      /* Error */
      public void g(k paramk, int paramInt, String paramString)
        throws RemoteException
      {
        // Byte code:
        //   0: invokestatic 28	android/os/Parcel:obtain	()Landroid/os/Parcel;
        //   3: astore 5
        //   5: invokestatic 28	android/os/Parcel:obtain	()Landroid/os/Parcel;
        //   8: astore 4
        //   10: aload 5
        //   12: ldc 30
        //   14: invokevirtual 34	android/os/Parcel:writeInterfaceToken	(Ljava/lang/String;)V
        //   17: aload_1
        //   18: ifnull +61 -> 79
        //   21: aload_1
        //   22: invokeinterface 40 1 0
        //   27: astore_1
        //   28: aload 5
        //   30: aload_1
        //   31: invokevirtual 43	android/os/Parcel:writeStrongBinder	(Landroid/os/IBinder;)V
        //   34: aload 5
        //   36: iload_2
        //   37: invokevirtual 47	android/os/Parcel:writeInt	(I)V
        //   40: aload 5
        //   42: aload_3
        //   43: invokevirtual 64	android/os/Parcel:writeString	(Ljava/lang/String;)V
        //   46: aload_0
        //   47: getfield 18	com/google/android/gms/common/internal/l$a$a:lb	Landroid/os/IBinder;
        //   50: bipush 32
        //   52: aload 5
        //   54: aload 4
        //   56: iconst_0
        //   57: invokeinterface 53 5 0
        //   62: pop
        //   63: aload 4
        //   65: invokevirtual 56	android/os/Parcel:readException	()V
        //   68: aload 4
        //   70: invokevirtual 59	android/os/Parcel:recycle	()V
        //   73: aload 5
        //   75: invokevirtual 59	android/os/Parcel:recycle	()V
        //   78: return
        //   79: aconst_null
        //   80: astore_1
        //   81: goto -53 -> 28
        //   84: astore_1
        //   85: aload 4
        //   87: invokevirtual 59	android/os/Parcel:recycle	()V
        //   90: aload 5
        //   92: invokevirtual 59	android/os/Parcel:recycle	()V
        //   95: aload_1
        //   96: athrow
        // Local variable table:
        //   start	length	slot	name	signature
        //   0	97	0	this	a
        //   0	97	1	paramk	k
        //   0	97	2	paramInt	int
        //   0	97	3	paramString	String
        //   8	78	4	localParcel1	Parcel
        //   3	88	5	localParcel2	Parcel
        // Exception table:
        //   from	to	target	type
        //   10	17	84	finally
        //   21	28	84	finally
        //   28	68	84	finally
      }
      
      /* Error */
      public void g(k paramk, int paramInt, String paramString, Bundle paramBundle)
        throws RemoteException
      {
        // Byte code:
        //   0: invokestatic 28	android/os/Parcel:obtain	()Landroid/os/Parcel;
        //   3: astore 5
        //   5: invokestatic 28	android/os/Parcel:obtain	()Landroid/os/Parcel;
        //   8: astore 6
        //   10: aload 5
        //   12: ldc 30
        //   14: invokevirtual 34	android/os/Parcel:writeInterfaceToken	(Ljava/lang/String;)V
        //   17: aload_1
        //   18: ifnull +80 -> 98
        //   21: aload_1
        //   22: invokeinterface 40 1 0
        //   27: astore_1
        //   28: aload 5
        //   30: aload_1
        //   31: invokevirtual 43	android/os/Parcel:writeStrongBinder	(Landroid/os/IBinder;)V
        //   34: aload 5
        //   36: iload_2
        //   37: invokevirtual 47	android/os/Parcel:writeInt	(I)V
        //   40: aload 5
        //   42: aload_3
        //   43: invokevirtual 64	android/os/Parcel:writeString	(Ljava/lang/String;)V
        //   46: aload 4
        //   48: ifnull +55 -> 103
        //   51: aload 5
        //   53: iconst_1
        //   54: invokevirtual 47	android/os/Parcel:writeInt	(I)V
        //   57: aload 4
        //   59: aload 5
        //   61: iconst_0
        //   62: invokevirtual 71	android/os/Bundle:writeToParcel	(Landroid/os/Parcel;I)V
        //   65: aload_0
        //   66: getfield 18	com/google/android/gms/common/internal/l$a$a:lb	Landroid/os/IBinder;
        //   69: bipush 12
        //   71: aload 5
        //   73: aload 6
        //   75: iconst_0
        //   76: invokeinterface 53 5 0
        //   81: pop
        //   82: aload 6
        //   84: invokevirtual 56	android/os/Parcel:readException	()V
        //   87: aload 6
        //   89: invokevirtual 59	android/os/Parcel:recycle	()V
        //   92: aload 5
        //   94: invokevirtual 59	android/os/Parcel:recycle	()V
        //   97: return
        //   98: aconst_null
        //   99: astore_1
        //   100: goto -72 -> 28
        //   103: aload 5
        //   105: iconst_0
        //   106: invokevirtual 47	android/os/Parcel:writeInt	(I)V
        //   109: goto -44 -> 65
        //   112: astore_1
        //   113: aload 6
        //   115: invokevirtual 59	android/os/Parcel:recycle	()V
        //   118: aload 5
        //   120: invokevirtual 59	android/os/Parcel:recycle	()V
        //   123: aload_1
        //   124: athrow
        // Local variable table:
        //   start	length	slot	name	signature
        //   0	125	0	this	a
        //   0	125	1	paramk	k
        //   0	125	2	paramInt	int
        //   0	125	3	paramString	String
        //   0	125	4	paramBundle	Bundle
        //   3	116	5	localParcel1	Parcel
        //   8	106	6	localParcel2	Parcel
        // Exception table:
        //   from	to	target	type
        //   10	17	112	finally
        //   21	28	112	finally
        //   28	46	112	finally
        //   51	65	112	finally
        //   65	87	112	finally
        //   103	109	112	finally
      }
      
      /* Error */
      public void h(k paramk, int paramInt, String paramString)
        throws RemoteException
      {
        // Byte code:
        //   0: invokestatic 28	android/os/Parcel:obtain	()Landroid/os/Parcel;
        //   3: astore 4
        //   5: invokestatic 28	android/os/Parcel:obtain	()Landroid/os/Parcel;
        //   8: astore 5
        //   10: aload 4
        //   12: ldc 30
        //   14: invokevirtual 34	android/os/Parcel:writeInterfaceToken	(Ljava/lang/String;)V
        //   17: aload_1
        //   18: ifnull +61 -> 79
        //   21: aload_1
        //   22: invokeinterface 40 1 0
        //   27: astore_1
        //   28: aload 4
        //   30: aload_1
        //   31: invokevirtual 43	android/os/Parcel:writeStrongBinder	(Landroid/os/IBinder;)V
        //   34: aload 4
        //   36: iload_2
        //   37: invokevirtual 47	android/os/Parcel:writeInt	(I)V
        //   40: aload 4
        //   42: aload_3
        //   43: invokevirtual 64	android/os/Parcel:writeString	(Ljava/lang/String;)V
        //   46: aload_0
        //   47: getfield 18	com/google/android/gms/common/internal/l$a$a:lb	Landroid/os/IBinder;
        //   50: bipush 35
        //   52: aload 4
        //   54: aload 5
        //   56: iconst_0
        //   57: invokeinterface 53 5 0
        //   62: pop
        //   63: aload 5
        //   65: invokevirtual 56	android/os/Parcel:readException	()V
        //   68: aload 5
        //   70: invokevirtual 59	android/os/Parcel:recycle	()V
        //   73: aload 4
        //   75: invokevirtual 59	android/os/Parcel:recycle	()V
        //   78: return
        //   79: aconst_null
        //   80: astore_1
        //   81: goto -53 -> 28
        //   84: astore_1
        //   85: aload 5
        //   87: invokevirtual 59	android/os/Parcel:recycle	()V
        //   90: aload 4
        //   92: invokevirtual 59	android/os/Parcel:recycle	()V
        //   95: aload_1
        //   96: athrow
        // Local variable table:
        //   start	length	slot	name	signature
        //   0	97	0	this	a
        //   0	97	1	paramk	k
        //   0	97	2	paramInt	int
        //   0	97	3	paramString	String
        //   3	88	4	localParcel1	Parcel
        //   8	78	5	localParcel2	Parcel
        // Exception table:
        //   from	to	target	type
        //   10	17	84	finally
        //   21	28	84	finally
        //   28	68	84	finally
      }
      
      /* Error */
      public void h(k paramk, int paramInt, String paramString, Bundle paramBundle)
        throws RemoteException
      {
        // Byte code:
        //   0: invokestatic 28	android/os/Parcel:obtain	()Landroid/os/Parcel;
        //   3: astore 5
        //   5: invokestatic 28	android/os/Parcel:obtain	()Landroid/os/Parcel;
        //   8: astore 6
        //   10: aload 5
        //   12: ldc 30
        //   14: invokevirtual 34	android/os/Parcel:writeInterfaceToken	(Ljava/lang/String;)V
        //   17: aload_1
        //   18: ifnull +80 -> 98
        //   21: aload_1
        //   22: invokeinterface 40 1 0
        //   27: astore_1
        //   28: aload 5
        //   30: aload_1
        //   31: invokevirtual 43	android/os/Parcel:writeStrongBinder	(Landroid/os/IBinder;)V
        //   34: aload 5
        //   36: iload_2
        //   37: invokevirtual 47	android/os/Parcel:writeInt	(I)V
        //   40: aload 5
        //   42: aload_3
        //   43: invokevirtual 64	android/os/Parcel:writeString	(Ljava/lang/String;)V
        //   46: aload 4
        //   48: ifnull +55 -> 103
        //   51: aload 5
        //   53: iconst_1
        //   54: invokevirtual 47	android/os/Parcel:writeInt	(I)V
        //   57: aload 4
        //   59: aload 5
        //   61: iconst_0
        //   62: invokevirtual 71	android/os/Bundle:writeToParcel	(Landroid/os/Parcel;I)V
        //   65: aload_0
        //   66: getfield 18	com/google/android/gms/common/internal/l$a$a:lb	Landroid/os/IBinder;
        //   69: bipush 13
        //   71: aload 5
        //   73: aload 6
        //   75: iconst_0
        //   76: invokeinterface 53 5 0
        //   81: pop
        //   82: aload 6
        //   84: invokevirtual 56	android/os/Parcel:readException	()V
        //   87: aload 6
        //   89: invokevirtual 59	android/os/Parcel:recycle	()V
        //   92: aload 5
        //   94: invokevirtual 59	android/os/Parcel:recycle	()V
        //   97: return
        //   98: aconst_null
        //   99: astore_1
        //   100: goto -72 -> 28
        //   103: aload 5
        //   105: iconst_0
        //   106: invokevirtual 47	android/os/Parcel:writeInt	(I)V
        //   109: goto -44 -> 65
        //   112: astore_1
        //   113: aload 6
        //   115: invokevirtual 59	android/os/Parcel:recycle	()V
        //   118: aload 5
        //   120: invokevirtual 59	android/os/Parcel:recycle	()V
        //   123: aload_1
        //   124: athrow
        // Local variable table:
        //   start	length	slot	name	signature
        //   0	125	0	this	a
        //   0	125	1	paramk	k
        //   0	125	2	paramInt	int
        //   0	125	3	paramString	String
        //   0	125	4	paramBundle	Bundle
        //   3	116	5	localParcel1	Parcel
        //   8	106	6	localParcel2	Parcel
        // Exception table:
        //   from	to	target	type
        //   10	17	112	finally
        //   21	28	112	finally
        //   28	46	112	finally
        //   51	65	112	finally
        //   65	87	112	finally
        //   103	109	112	finally
      }
      
      /* Error */
      public void i(k paramk, int paramInt, String paramString)
        throws RemoteException
      {
        // Byte code:
        //   0: invokestatic 28	android/os/Parcel:obtain	()Landroid/os/Parcel;
        //   3: astore 4
        //   5: invokestatic 28	android/os/Parcel:obtain	()Landroid/os/Parcel;
        //   8: astore 5
        //   10: aload 4
        //   12: ldc 30
        //   14: invokevirtual 34	android/os/Parcel:writeInterfaceToken	(Ljava/lang/String;)V
        //   17: aload_1
        //   18: ifnull +61 -> 79
        //   21: aload_1
        //   22: invokeinterface 40 1 0
        //   27: astore_1
        //   28: aload 4
        //   30: aload_1
        //   31: invokevirtual 43	android/os/Parcel:writeStrongBinder	(Landroid/os/IBinder;)V
        //   34: aload 4
        //   36: iload_2
        //   37: invokevirtual 47	android/os/Parcel:writeInt	(I)V
        //   40: aload 4
        //   42: aload_3
        //   43: invokevirtual 64	android/os/Parcel:writeString	(Ljava/lang/String;)V
        //   46: aload_0
        //   47: getfield 18	com/google/android/gms/common/internal/l$a$a:lb	Landroid/os/IBinder;
        //   50: bipush 36
        //   52: aload 4
        //   54: aload 5
        //   56: iconst_0
        //   57: invokeinterface 53 5 0
        //   62: pop
        //   63: aload 5
        //   65: invokevirtual 56	android/os/Parcel:readException	()V
        //   68: aload 5
        //   70: invokevirtual 59	android/os/Parcel:recycle	()V
        //   73: aload 4
        //   75: invokevirtual 59	android/os/Parcel:recycle	()V
        //   78: return
        //   79: aconst_null
        //   80: astore_1
        //   81: goto -53 -> 28
        //   84: astore_1
        //   85: aload 5
        //   87: invokevirtual 59	android/os/Parcel:recycle	()V
        //   90: aload 4
        //   92: invokevirtual 59	android/os/Parcel:recycle	()V
        //   95: aload_1
        //   96: athrow
        // Local variable table:
        //   start	length	slot	name	signature
        //   0	97	0	this	a
        //   0	97	1	paramk	k
        //   0	97	2	paramInt	int
        //   0	97	3	paramString	String
        //   3	88	4	localParcel1	Parcel
        //   8	78	5	localParcel2	Parcel
        // Exception table:
        //   from	to	target	type
        //   10	17	84	finally
        //   21	28	84	finally
        //   28	68	84	finally
      }
      
      /* Error */
      public void i(k paramk, int paramInt, String paramString, Bundle paramBundle)
        throws RemoteException
      {
        // Byte code:
        //   0: invokestatic 28	android/os/Parcel:obtain	()Landroid/os/Parcel;
        //   3: astore 6
        //   5: invokestatic 28	android/os/Parcel:obtain	()Landroid/os/Parcel;
        //   8: astore 5
        //   10: aload 6
        //   12: ldc 30
        //   14: invokevirtual 34	android/os/Parcel:writeInterfaceToken	(Ljava/lang/String;)V
        //   17: aload_1
        //   18: ifnull +80 -> 98
        //   21: aload_1
        //   22: invokeinterface 40 1 0
        //   27: astore_1
        //   28: aload 6
        //   30: aload_1
        //   31: invokevirtual 43	android/os/Parcel:writeStrongBinder	(Landroid/os/IBinder;)V
        //   34: aload 6
        //   36: iload_2
        //   37: invokevirtual 47	android/os/Parcel:writeInt	(I)V
        //   40: aload 6
        //   42: aload_3
        //   43: invokevirtual 64	android/os/Parcel:writeString	(Ljava/lang/String;)V
        //   46: aload 4
        //   48: ifnull +55 -> 103
        //   51: aload 6
        //   53: iconst_1
        //   54: invokevirtual 47	android/os/Parcel:writeInt	(I)V
        //   57: aload 4
        //   59: aload 6
        //   61: iconst_0
        //   62: invokevirtual 71	android/os/Bundle:writeToParcel	(Landroid/os/Parcel;I)V
        //   65: aload_0
        //   66: getfield 18	com/google/android/gms/common/internal/l$a$a:lb	Landroid/os/IBinder;
        //   69: bipush 14
        //   71: aload 6
        //   73: aload 5
        //   75: iconst_0
        //   76: invokeinterface 53 5 0
        //   81: pop
        //   82: aload 5
        //   84: invokevirtual 56	android/os/Parcel:readException	()V
        //   87: aload 5
        //   89: invokevirtual 59	android/os/Parcel:recycle	()V
        //   92: aload 6
        //   94: invokevirtual 59	android/os/Parcel:recycle	()V
        //   97: return
        //   98: aconst_null
        //   99: astore_1
        //   100: goto -72 -> 28
        //   103: aload 6
        //   105: iconst_0
        //   106: invokevirtual 47	android/os/Parcel:writeInt	(I)V
        //   109: goto -44 -> 65
        //   112: astore_1
        //   113: aload 5
        //   115: invokevirtual 59	android/os/Parcel:recycle	()V
        //   118: aload 6
        //   120: invokevirtual 59	android/os/Parcel:recycle	()V
        //   123: aload_1
        //   124: athrow
        // Local variable table:
        //   start	length	slot	name	signature
        //   0	125	0	this	a
        //   0	125	1	paramk	k
        //   0	125	2	paramInt	int
        //   0	125	3	paramString	String
        //   0	125	4	paramBundle	Bundle
        //   8	106	5	localParcel1	Parcel
        //   3	116	6	localParcel2	Parcel
        // Exception table:
        //   from	to	target	type
        //   10	17	112	finally
        //   21	28	112	finally
        //   28	46	112	finally
        //   51	65	112	finally
        //   65	87	112	finally
        //   103	109	112	finally
      }
      
      /* Error */
      public void j(k paramk, int paramInt, String paramString)
        throws RemoteException
      {
        // Byte code:
        //   0: invokestatic 28	android/os/Parcel:obtain	()Landroid/os/Parcel;
        //   3: astore 4
        //   5: invokestatic 28	android/os/Parcel:obtain	()Landroid/os/Parcel;
        //   8: astore 5
        //   10: aload 4
        //   12: ldc 30
        //   14: invokevirtual 34	android/os/Parcel:writeInterfaceToken	(Ljava/lang/String;)V
        //   17: aload_1
        //   18: ifnull +61 -> 79
        //   21: aload_1
        //   22: invokeinterface 40 1 0
        //   27: astore_1
        //   28: aload 4
        //   30: aload_1
        //   31: invokevirtual 43	android/os/Parcel:writeStrongBinder	(Landroid/os/IBinder;)V
        //   34: aload 4
        //   36: iload_2
        //   37: invokevirtual 47	android/os/Parcel:writeInt	(I)V
        //   40: aload 4
        //   42: aload_3
        //   43: invokevirtual 64	android/os/Parcel:writeString	(Ljava/lang/String;)V
        //   46: aload_0
        //   47: getfield 18	com/google/android/gms/common/internal/l$a$a:lb	Landroid/os/IBinder;
        //   50: bipush 40
        //   52: aload 4
        //   54: aload 5
        //   56: iconst_0
        //   57: invokeinterface 53 5 0
        //   62: pop
        //   63: aload 5
        //   65: invokevirtual 56	android/os/Parcel:readException	()V
        //   68: aload 5
        //   70: invokevirtual 59	android/os/Parcel:recycle	()V
        //   73: aload 4
        //   75: invokevirtual 59	android/os/Parcel:recycle	()V
        //   78: return
        //   79: aconst_null
        //   80: astore_1
        //   81: goto -53 -> 28
        //   84: astore_1
        //   85: aload 5
        //   87: invokevirtual 59	android/os/Parcel:recycle	()V
        //   90: aload 4
        //   92: invokevirtual 59	android/os/Parcel:recycle	()V
        //   95: aload_1
        //   96: athrow
        // Local variable table:
        //   start	length	slot	name	signature
        //   0	97	0	this	a
        //   0	97	1	paramk	k
        //   0	97	2	paramInt	int
        //   0	97	3	paramString	String
        //   3	88	4	localParcel1	Parcel
        //   8	78	5	localParcel2	Parcel
        // Exception table:
        //   from	to	target	type
        //   10	17	84	finally
        //   21	28	84	finally
        //   28	68	84	finally
      }
      
      /* Error */
      public void j(k paramk, int paramInt, String paramString, Bundle paramBundle)
        throws RemoteException
      {
        // Byte code:
        //   0: invokestatic 28	android/os/Parcel:obtain	()Landroid/os/Parcel;
        //   3: astore 5
        //   5: invokestatic 28	android/os/Parcel:obtain	()Landroid/os/Parcel;
        //   8: astore 6
        //   10: aload 5
        //   12: ldc 30
        //   14: invokevirtual 34	android/os/Parcel:writeInterfaceToken	(Ljava/lang/String;)V
        //   17: aload_1
        //   18: ifnull +80 -> 98
        //   21: aload_1
        //   22: invokeinterface 40 1 0
        //   27: astore_1
        //   28: aload 5
        //   30: aload_1
        //   31: invokevirtual 43	android/os/Parcel:writeStrongBinder	(Landroid/os/IBinder;)V
        //   34: aload 5
        //   36: iload_2
        //   37: invokevirtual 47	android/os/Parcel:writeInt	(I)V
        //   40: aload 5
        //   42: aload_3
        //   43: invokevirtual 64	android/os/Parcel:writeString	(Ljava/lang/String;)V
        //   46: aload 4
        //   48: ifnull +55 -> 103
        //   51: aload 5
        //   53: iconst_1
        //   54: invokevirtual 47	android/os/Parcel:writeInt	(I)V
        //   57: aload 4
        //   59: aload 5
        //   61: iconst_0
        //   62: invokevirtual 71	android/os/Bundle:writeToParcel	(Landroid/os/Parcel;I)V
        //   65: aload_0
        //   66: getfield 18	com/google/android/gms/common/internal/l$a$a:lb	Landroid/os/IBinder;
        //   69: bipush 15
        //   71: aload 5
        //   73: aload 6
        //   75: iconst_0
        //   76: invokeinterface 53 5 0
        //   81: pop
        //   82: aload 6
        //   84: invokevirtual 56	android/os/Parcel:readException	()V
        //   87: aload 6
        //   89: invokevirtual 59	android/os/Parcel:recycle	()V
        //   92: aload 5
        //   94: invokevirtual 59	android/os/Parcel:recycle	()V
        //   97: return
        //   98: aconst_null
        //   99: astore_1
        //   100: goto -72 -> 28
        //   103: aload 5
        //   105: iconst_0
        //   106: invokevirtual 47	android/os/Parcel:writeInt	(I)V
        //   109: goto -44 -> 65
        //   112: astore_1
        //   113: aload 6
        //   115: invokevirtual 59	android/os/Parcel:recycle	()V
        //   118: aload 5
        //   120: invokevirtual 59	android/os/Parcel:recycle	()V
        //   123: aload_1
        //   124: athrow
        // Local variable table:
        //   start	length	slot	name	signature
        //   0	125	0	this	a
        //   0	125	1	paramk	k
        //   0	125	2	paramInt	int
        //   0	125	3	paramString	String
        //   0	125	4	paramBundle	Bundle
        //   3	116	5	localParcel1	Parcel
        //   8	106	6	localParcel2	Parcel
        // Exception table:
        //   from	to	target	type
        //   10	17	112	finally
        //   21	28	112	finally
        //   28	46	112	finally
        //   51	65	112	finally
        //   65	87	112	finally
        //   103	109	112	finally
      }
      
      /* Error */
      public void k(k paramk, int paramInt, String paramString)
        throws RemoteException
      {
        // Byte code:
        //   0: invokestatic 28	android/os/Parcel:obtain	()Landroid/os/Parcel;
        //   3: astore 5
        //   5: invokestatic 28	android/os/Parcel:obtain	()Landroid/os/Parcel;
        //   8: astore 4
        //   10: aload 5
        //   12: ldc 30
        //   14: invokevirtual 34	android/os/Parcel:writeInterfaceToken	(Ljava/lang/String;)V
        //   17: aload_1
        //   18: ifnull +61 -> 79
        //   21: aload_1
        //   22: invokeinterface 40 1 0
        //   27: astore_1
        //   28: aload 5
        //   30: aload_1
        //   31: invokevirtual 43	android/os/Parcel:writeStrongBinder	(Landroid/os/IBinder;)V
        //   34: aload 5
        //   36: iload_2
        //   37: invokevirtual 47	android/os/Parcel:writeInt	(I)V
        //   40: aload 5
        //   42: aload_3
        //   43: invokevirtual 64	android/os/Parcel:writeString	(Ljava/lang/String;)V
        //   46: aload_0
        //   47: getfield 18	com/google/android/gms/common/internal/l$a$a:lb	Landroid/os/IBinder;
        //   50: bipush 42
        //   52: aload 5
        //   54: aload 4
        //   56: iconst_0
        //   57: invokeinterface 53 5 0
        //   62: pop
        //   63: aload 4
        //   65: invokevirtual 56	android/os/Parcel:readException	()V
        //   68: aload 4
        //   70: invokevirtual 59	android/os/Parcel:recycle	()V
        //   73: aload 5
        //   75: invokevirtual 59	android/os/Parcel:recycle	()V
        //   78: return
        //   79: aconst_null
        //   80: astore_1
        //   81: goto -53 -> 28
        //   84: astore_1
        //   85: aload 4
        //   87: invokevirtual 59	android/os/Parcel:recycle	()V
        //   90: aload 5
        //   92: invokevirtual 59	android/os/Parcel:recycle	()V
        //   95: aload_1
        //   96: athrow
        // Local variable table:
        //   start	length	slot	name	signature
        //   0	97	0	this	a
        //   0	97	1	paramk	k
        //   0	97	2	paramInt	int
        //   0	97	3	paramString	String
        //   8	78	4	localParcel1	Parcel
        //   3	88	5	localParcel2	Parcel
        // Exception table:
        //   from	to	target	type
        //   10	17	84	finally
        //   21	28	84	finally
        //   28	68	84	finally
      }
      
      /* Error */
      public void k(k paramk, int paramInt, String paramString, Bundle paramBundle)
        throws RemoteException
      {
        // Byte code:
        //   0: invokestatic 28	android/os/Parcel:obtain	()Landroid/os/Parcel;
        //   3: astore 5
        //   5: invokestatic 28	android/os/Parcel:obtain	()Landroid/os/Parcel;
        //   8: astore 6
        //   10: aload 5
        //   12: ldc 30
        //   14: invokevirtual 34	android/os/Parcel:writeInterfaceToken	(Ljava/lang/String;)V
        //   17: aload_1
        //   18: ifnull +80 -> 98
        //   21: aload_1
        //   22: invokeinterface 40 1 0
        //   27: astore_1
        //   28: aload 5
        //   30: aload_1
        //   31: invokevirtual 43	android/os/Parcel:writeStrongBinder	(Landroid/os/IBinder;)V
        //   34: aload 5
        //   36: iload_2
        //   37: invokevirtual 47	android/os/Parcel:writeInt	(I)V
        //   40: aload 5
        //   42: aload_3
        //   43: invokevirtual 64	android/os/Parcel:writeString	(Ljava/lang/String;)V
        //   46: aload 4
        //   48: ifnull +55 -> 103
        //   51: aload 5
        //   53: iconst_1
        //   54: invokevirtual 47	android/os/Parcel:writeInt	(I)V
        //   57: aload 4
        //   59: aload 5
        //   61: iconst_0
        //   62: invokevirtual 71	android/os/Bundle:writeToParcel	(Landroid/os/Parcel;I)V
        //   65: aload_0
        //   66: getfield 18	com/google/android/gms/common/internal/l$a$a:lb	Landroid/os/IBinder;
        //   69: bipush 16
        //   71: aload 5
        //   73: aload 6
        //   75: iconst_0
        //   76: invokeinterface 53 5 0
        //   81: pop
        //   82: aload 6
        //   84: invokevirtual 56	android/os/Parcel:readException	()V
        //   87: aload 6
        //   89: invokevirtual 59	android/os/Parcel:recycle	()V
        //   92: aload 5
        //   94: invokevirtual 59	android/os/Parcel:recycle	()V
        //   97: return
        //   98: aconst_null
        //   99: astore_1
        //   100: goto -72 -> 28
        //   103: aload 5
        //   105: iconst_0
        //   106: invokevirtual 47	android/os/Parcel:writeInt	(I)V
        //   109: goto -44 -> 65
        //   112: astore_1
        //   113: aload 6
        //   115: invokevirtual 59	android/os/Parcel:recycle	()V
        //   118: aload 5
        //   120: invokevirtual 59	android/os/Parcel:recycle	()V
        //   123: aload_1
        //   124: athrow
        // Local variable table:
        //   start	length	slot	name	signature
        //   0	125	0	this	a
        //   0	125	1	paramk	k
        //   0	125	2	paramInt	int
        //   0	125	3	paramString	String
        //   0	125	4	paramBundle	Bundle
        //   3	116	5	localParcel1	Parcel
        //   8	106	6	localParcel2	Parcel
        // Exception table:
        //   from	to	target	type
        //   10	17	112	finally
        //   21	28	112	finally
        //   28	46	112	finally
        //   51	65	112	finally
        //   65	87	112	finally
        //   103	109	112	finally
      }
      
      /* Error */
      public void l(k paramk, int paramInt, String paramString, Bundle paramBundle)
        throws RemoteException
      {
        // Byte code:
        //   0: invokestatic 28	android/os/Parcel:obtain	()Landroid/os/Parcel;
        //   3: astore 5
        //   5: invokestatic 28	android/os/Parcel:obtain	()Landroid/os/Parcel;
        //   8: astore 6
        //   10: aload 5
        //   12: ldc 30
        //   14: invokevirtual 34	android/os/Parcel:writeInterfaceToken	(Ljava/lang/String;)V
        //   17: aload_1
        //   18: ifnull +80 -> 98
        //   21: aload_1
        //   22: invokeinterface 40 1 0
        //   27: astore_1
        //   28: aload 5
        //   30: aload_1
        //   31: invokevirtual 43	android/os/Parcel:writeStrongBinder	(Landroid/os/IBinder;)V
        //   34: aload 5
        //   36: iload_2
        //   37: invokevirtual 47	android/os/Parcel:writeInt	(I)V
        //   40: aload 5
        //   42: aload_3
        //   43: invokevirtual 64	android/os/Parcel:writeString	(Ljava/lang/String;)V
        //   46: aload 4
        //   48: ifnull +55 -> 103
        //   51: aload 5
        //   53: iconst_1
        //   54: invokevirtual 47	android/os/Parcel:writeInt	(I)V
        //   57: aload 4
        //   59: aload 5
        //   61: iconst_0
        //   62: invokevirtual 71	android/os/Bundle:writeToParcel	(Landroid/os/Parcel;I)V
        //   65: aload_0
        //   66: getfield 18	com/google/android/gms/common/internal/l$a$a:lb	Landroid/os/IBinder;
        //   69: bipush 17
        //   71: aload 5
        //   73: aload 6
        //   75: iconst_0
        //   76: invokeinterface 53 5 0
        //   81: pop
        //   82: aload 6
        //   84: invokevirtual 56	android/os/Parcel:readException	()V
        //   87: aload 6
        //   89: invokevirtual 59	android/os/Parcel:recycle	()V
        //   92: aload 5
        //   94: invokevirtual 59	android/os/Parcel:recycle	()V
        //   97: return
        //   98: aconst_null
        //   99: astore_1
        //   100: goto -72 -> 28
        //   103: aload 5
        //   105: iconst_0
        //   106: invokevirtual 47	android/os/Parcel:writeInt	(I)V
        //   109: goto -44 -> 65
        //   112: astore_1
        //   113: aload 6
        //   115: invokevirtual 59	android/os/Parcel:recycle	()V
        //   118: aload 5
        //   120: invokevirtual 59	android/os/Parcel:recycle	()V
        //   123: aload_1
        //   124: athrow
        // Local variable table:
        //   start	length	slot	name	signature
        //   0	125	0	this	a
        //   0	125	1	paramk	k
        //   0	125	2	paramInt	int
        //   0	125	3	paramString	String
        //   0	125	4	paramBundle	Bundle
        //   3	116	5	localParcel1	Parcel
        //   8	106	6	localParcel2	Parcel
        // Exception table:
        //   from	to	target	type
        //   10	17	112	finally
        //   21	28	112	finally
        //   28	46	112	finally
        //   51	65	112	finally
        //   65	87	112	finally
        //   103	109	112	finally
      }
      
      /* Error */
      public void m(k paramk, int paramInt, String paramString, Bundle paramBundle)
        throws RemoteException
      {
        // Byte code:
        //   0: invokestatic 28	android/os/Parcel:obtain	()Landroid/os/Parcel;
        //   3: astore 5
        //   5: invokestatic 28	android/os/Parcel:obtain	()Landroid/os/Parcel;
        //   8: astore 6
        //   10: aload 5
        //   12: ldc 30
        //   14: invokevirtual 34	android/os/Parcel:writeInterfaceToken	(Ljava/lang/String;)V
        //   17: aload_1
        //   18: ifnull +80 -> 98
        //   21: aload_1
        //   22: invokeinterface 40 1 0
        //   27: astore_1
        //   28: aload 5
        //   30: aload_1
        //   31: invokevirtual 43	android/os/Parcel:writeStrongBinder	(Landroid/os/IBinder;)V
        //   34: aload 5
        //   36: iload_2
        //   37: invokevirtual 47	android/os/Parcel:writeInt	(I)V
        //   40: aload 5
        //   42: aload_3
        //   43: invokevirtual 64	android/os/Parcel:writeString	(Ljava/lang/String;)V
        //   46: aload 4
        //   48: ifnull +55 -> 103
        //   51: aload 5
        //   53: iconst_1
        //   54: invokevirtual 47	android/os/Parcel:writeInt	(I)V
        //   57: aload 4
        //   59: aload 5
        //   61: iconst_0
        //   62: invokevirtual 71	android/os/Bundle:writeToParcel	(Landroid/os/Parcel;I)V
        //   65: aload_0
        //   66: getfield 18	com/google/android/gms/common/internal/l$a$a:lb	Landroid/os/IBinder;
        //   69: bipush 18
        //   71: aload 5
        //   73: aload 6
        //   75: iconst_0
        //   76: invokeinterface 53 5 0
        //   81: pop
        //   82: aload 6
        //   84: invokevirtual 56	android/os/Parcel:readException	()V
        //   87: aload 6
        //   89: invokevirtual 59	android/os/Parcel:recycle	()V
        //   92: aload 5
        //   94: invokevirtual 59	android/os/Parcel:recycle	()V
        //   97: return
        //   98: aconst_null
        //   99: astore_1
        //   100: goto -72 -> 28
        //   103: aload 5
        //   105: iconst_0
        //   106: invokevirtual 47	android/os/Parcel:writeInt	(I)V
        //   109: goto -44 -> 65
        //   112: astore_1
        //   113: aload 6
        //   115: invokevirtual 59	android/os/Parcel:recycle	()V
        //   118: aload 5
        //   120: invokevirtual 59	android/os/Parcel:recycle	()V
        //   123: aload_1
        //   124: athrow
        // Local variable table:
        //   start	length	slot	name	signature
        //   0	125	0	this	a
        //   0	125	1	paramk	k
        //   0	125	2	paramInt	int
        //   0	125	3	paramString	String
        //   0	125	4	paramBundle	Bundle
        //   3	116	5	localParcel1	Parcel
        //   8	106	6	localParcel2	Parcel
        // Exception table:
        //   from	to	target	type
        //   10	17	112	finally
        //   21	28	112	finally
        //   28	46	112	finally
        //   51	65	112	finally
        //   65	87	112	finally
        //   103	109	112	finally
      }
      
      /* Error */
      public void n(k paramk, int paramInt, String paramString, Bundle paramBundle)
        throws RemoteException
      {
        // Byte code:
        //   0: invokestatic 28	android/os/Parcel:obtain	()Landroid/os/Parcel;
        //   3: astore 6
        //   5: invokestatic 28	android/os/Parcel:obtain	()Landroid/os/Parcel;
        //   8: astore 5
        //   10: aload 6
        //   12: ldc 30
        //   14: invokevirtual 34	android/os/Parcel:writeInterfaceToken	(Ljava/lang/String;)V
        //   17: aload_1
        //   18: ifnull +80 -> 98
        //   21: aload_1
        //   22: invokeinterface 40 1 0
        //   27: astore_1
        //   28: aload 6
        //   30: aload_1
        //   31: invokevirtual 43	android/os/Parcel:writeStrongBinder	(Landroid/os/IBinder;)V
        //   34: aload 6
        //   36: iload_2
        //   37: invokevirtual 47	android/os/Parcel:writeInt	(I)V
        //   40: aload 6
        //   42: aload_3
        //   43: invokevirtual 64	android/os/Parcel:writeString	(Ljava/lang/String;)V
        //   46: aload 4
        //   48: ifnull +55 -> 103
        //   51: aload 6
        //   53: iconst_1
        //   54: invokevirtual 47	android/os/Parcel:writeInt	(I)V
        //   57: aload 4
        //   59: aload 6
        //   61: iconst_0
        //   62: invokevirtual 71	android/os/Bundle:writeToParcel	(Landroid/os/Parcel;I)V
        //   65: aload_0
        //   66: getfield 18	com/google/android/gms/common/internal/l$a$a:lb	Landroid/os/IBinder;
        //   69: bipush 23
        //   71: aload 6
        //   73: aload 5
        //   75: iconst_0
        //   76: invokeinterface 53 5 0
        //   81: pop
        //   82: aload 5
        //   84: invokevirtual 56	android/os/Parcel:readException	()V
        //   87: aload 5
        //   89: invokevirtual 59	android/os/Parcel:recycle	()V
        //   92: aload 6
        //   94: invokevirtual 59	android/os/Parcel:recycle	()V
        //   97: return
        //   98: aconst_null
        //   99: astore_1
        //   100: goto -72 -> 28
        //   103: aload 6
        //   105: iconst_0
        //   106: invokevirtual 47	android/os/Parcel:writeInt	(I)V
        //   109: goto -44 -> 65
        //   112: astore_1
        //   113: aload 5
        //   115: invokevirtual 59	android/os/Parcel:recycle	()V
        //   118: aload 6
        //   120: invokevirtual 59	android/os/Parcel:recycle	()V
        //   123: aload_1
        //   124: athrow
        // Local variable table:
        //   start	length	slot	name	signature
        //   0	125	0	this	a
        //   0	125	1	paramk	k
        //   0	125	2	paramInt	int
        //   0	125	3	paramString	String
        //   0	125	4	paramBundle	Bundle
        //   8	106	5	localParcel1	Parcel
        //   3	116	6	localParcel2	Parcel
        // Exception table:
        //   from	to	target	type
        //   10	17	112	finally
        //   21	28	112	finally
        //   28	46	112	finally
        //   51	65	112	finally
        //   65	87	112	finally
        //   103	109	112	finally
      }
      
      /* Error */
      public void o(k paramk, int paramInt, String paramString, Bundle paramBundle)
        throws RemoteException
      {
        // Byte code:
        //   0: invokestatic 28	android/os/Parcel:obtain	()Landroid/os/Parcel;
        //   3: astore 6
        //   5: invokestatic 28	android/os/Parcel:obtain	()Landroid/os/Parcel;
        //   8: astore 5
        //   10: aload 6
        //   12: ldc 30
        //   14: invokevirtual 34	android/os/Parcel:writeInterfaceToken	(Ljava/lang/String;)V
        //   17: aload_1
        //   18: ifnull +80 -> 98
        //   21: aload_1
        //   22: invokeinterface 40 1 0
        //   27: astore_1
        //   28: aload 6
        //   30: aload_1
        //   31: invokevirtual 43	android/os/Parcel:writeStrongBinder	(Landroid/os/IBinder;)V
        //   34: aload 6
        //   36: iload_2
        //   37: invokevirtual 47	android/os/Parcel:writeInt	(I)V
        //   40: aload 6
        //   42: aload_3
        //   43: invokevirtual 64	android/os/Parcel:writeString	(Ljava/lang/String;)V
        //   46: aload 4
        //   48: ifnull +55 -> 103
        //   51: aload 6
        //   53: iconst_1
        //   54: invokevirtual 47	android/os/Parcel:writeInt	(I)V
        //   57: aload 4
        //   59: aload 6
        //   61: iconst_0
        //   62: invokevirtual 71	android/os/Bundle:writeToParcel	(Landroid/os/Parcel;I)V
        //   65: aload_0
        //   66: getfield 18	com/google/android/gms/common/internal/l$a$a:lb	Landroid/os/IBinder;
        //   69: bipush 25
        //   71: aload 6
        //   73: aload 5
        //   75: iconst_0
        //   76: invokeinterface 53 5 0
        //   81: pop
        //   82: aload 5
        //   84: invokevirtual 56	android/os/Parcel:readException	()V
        //   87: aload 5
        //   89: invokevirtual 59	android/os/Parcel:recycle	()V
        //   92: aload 6
        //   94: invokevirtual 59	android/os/Parcel:recycle	()V
        //   97: return
        //   98: aconst_null
        //   99: astore_1
        //   100: goto -72 -> 28
        //   103: aload 6
        //   105: iconst_0
        //   106: invokevirtual 47	android/os/Parcel:writeInt	(I)V
        //   109: goto -44 -> 65
        //   112: astore_1
        //   113: aload 5
        //   115: invokevirtual 59	android/os/Parcel:recycle	()V
        //   118: aload 6
        //   120: invokevirtual 59	android/os/Parcel:recycle	()V
        //   123: aload_1
        //   124: athrow
        // Local variable table:
        //   start	length	slot	name	signature
        //   0	125	0	this	a
        //   0	125	1	paramk	k
        //   0	125	2	paramInt	int
        //   0	125	3	paramString	String
        //   0	125	4	paramBundle	Bundle
        //   8	106	5	localParcel1	Parcel
        //   3	116	6	localParcel2	Parcel
        // Exception table:
        //   from	to	target	type
        //   10	17	112	finally
        //   21	28	112	finally
        //   28	46	112	finally
        //   51	65	112	finally
        //   65	87	112	finally
        //   103	109	112	finally
      }
      
      /* Error */
      public void p(k paramk, int paramInt, String paramString, Bundle paramBundle)
        throws RemoteException
      {
        // Byte code:
        //   0: invokestatic 28	android/os/Parcel:obtain	()Landroid/os/Parcel;
        //   3: astore 5
        //   5: invokestatic 28	android/os/Parcel:obtain	()Landroid/os/Parcel;
        //   8: astore 6
        //   10: aload 5
        //   12: ldc 30
        //   14: invokevirtual 34	android/os/Parcel:writeInterfaceToken	(Ljava/lang/String;)V
        //   17: aload_1
        //   18: ifnull +80 -> 98
        //   21: aload_1
        //   22: invokeinterface 40 1 0
        //   27: astore_1
        //   28: aload 5
        //   30: aload_1
        //   31: invokevirtual 43	android/os/Parcel:writeStrongBinder	(Landroid/os/IBinder;)V
        //   34: aload 5
        //   36: iload_2
        //   37: invokevirtual 47	android/os/Parcel:writeInt	(I)V
        //   40: aload 5
        //   42: aload_3
        //   43: invokevirtual 64	android/os/Parcel:writeString	(Ljava/lang/String;)V
        //   46: aload 4
        //   48: ifnull +55 -> 103
        //   51: aload 5
        //   53: iconst_1
        //   54: invokevirtual 47	android/os/Parcel:writeInt	(I)V
        //   57: aload 4
        //   59: aload 5
        //   61: iconst_0
        //   62: invokevirtual 71	android/os/Bundle:writeToParcel	(Landroid/os/Parcel;I)V
        //   65: aload_0
        //   66: getfield 18	com/google/android/gms/common/internal/l$a$a:lb	Landroid/os/IBinder;
        //   69: bipush 27
        //   71: aload 5
        //   73: aload 6
        //   75: iconst_0
        //   76: invokeinterface 53 5 0
        //   81: pop
        //   82: aload 6
        //   84: invokevirtual 56	android/os/Parcel:readException	()V
        //   87: aload 6
        //   89: invokevirtual 59	android/os/Parcel:recycle	()V
        //   92: aload 5
        //   94: invokevirtual 59	android/os/Parcel:recycle	()V
        //   97: return
        //   98: aconst_null
        //   99: astore_1
        //   100: goto -72 -> 28
        //   103: aload 5
        //   105: iconst_0
        //   106: invokevirtual 47	android/os/Parcel:writeInt	(I)V
        //   109: goto -44 -> 65
        //   112: astore_1
        //   113: aload 6
        //   115: invokevirtual 59	android/os/Parcel:recycle	()V
        //   118: aload 5
        //   120: invokevirtual 59	android/os/Parcel:recycle	()V
        //   123: aload_1
        //   124: athrow
        // Local variable table:
        //   start	length	slot	name	signature
        //   0	125	0	this	a
        //   0	125	1	paramk	k
        //   0	125	2	paramInt	int
        //   0	125	3	paramString	String
        //   0	125	4	paramBundle	Bundle
        //   3	116	5	localParcel1	Parcel
        //   8	106	6	localParcel2	Parcel
        // Exception table:
        //   from	to	target	type
        //   10	17	112	finally
        //   21	28	112	finally
        //   28	46	112	finally
        //   51	65	112	finally
        //   65	87	112	finally
        //   103	109	112	finally
      }
      
      /* Error */
      public void q(k paramk, int paramInt, String paramString, Bundle paramBundle)
        throws RemoteException
      {
        // Byte code:
        //   0: invokestatic 28	android/os/Parcel:obtain	()Landroid/os/Parcel;
        //   3: astore 6
        //   5: invokestatic 28	android/os/Parcel:obtain	()Landroid/os/Parcel;
        //   8: astore 5
        //   10: aload 6
        //   12: ldc 30
        //   14: invokevirtual 34	android/os/Parcel:writeInterfaceToken	(Ljava/lang/String;)V
        //   17: aload_1
        //   18: ifnull +80 -> 98
        //   21: aload_1
        //   22: invokeinterface 40 1 0
        //   27: astore_1
        //   28: aload 6
        //   30: aload_1
        //   31: invokevirtual 43	android/os/Parcel:writeStrongBinder	(Landroid/os/IBinder;)V
        //   34: aload 6
        //   36: iload_2
        //   37: invokevirtual 47	android/os/Parcel:writeInt	(I)V
        //   40: aload 6
        //   42: aload_3
        //   43: invokevirtual 64	android/os/Parcel:writeString	(Ljava/lang/String;)V
        //   46: aload 4
        //   48: ifnull +55 -> 103
        //   51: aload 6
        //   53: iconst_1
        //   54: invokevirtual 47	android/os/Parcel:writeInt	(I)V
        //   57: aload 4
        //   59: aload 6
        //   61: iconst_0
        //   62: invokevirtual 71	android/os/Bundle:writeToParcel	(Landroid/os/Parcel;I)V
        //   65: aload_0
        //   66: getfield 18	com/google/android/gms/common/internal/l$a$a:lb	Landroid/os/IBinder;
        //   69: bipush 37
        //   71: aload 6
        //   73: aload 5
        //   75: iconst_0
        //   76: invokeinterface 53 5 0
        //   81: pop
        //   82: aload 5
        //   84: invokevirtual 56	android/os/Parcel:readException	()V
        //   87: aload 5
        //   89: invokevirtual 59	android/os/Parcel:recycle	()V
        //   92: aload 6
        //   94: invokevirtual 59	android/os/Parcel:recycle	()V
        //   97: return
        //   98: aconst_null
        //   99: astore_1
        //   100: goto -72 -> 28
        //   103: aload 6
        //   105: iconst_0
        //   106: invokevirtual 47	android/os/Parcel:writeInt	(I)V
        //   109: goto -44 -> 65
        //   112: astore_1
        //   113: aload 5
        //   115: invokevirtual 59	android/os/Parcel:recycle	()V
        //   118: aload 6
        //   120: invokevirtual 59	android/os/Parcel:recycle	()V
        //   123: aload_1
        //   124: athrow
        // Local variable table:
        //   start	length	slot	name	signature
        //   0	125	0	this	a
        //   0	125	1	paramk	k
        //   0	125	2	paramInt	int
        //   0	125	3	paramString	String
        //   0	125	4	paramBundle	Bundle
        //   8	106	5	localParcel1	Parcel
        //   3	116	6	localParcel2	Parcel
        // Exception table:
        //   from	to	target	type
        //   10	17	112	finally
        //   21	28	112	finally
        //   28	46	112	finally
        //   51	65	112	finally
        //   65	87	112	finally
        //   103	109	112	finally
      }
      
      /* Error */
      public void r(k paramk, int paramInt, String paramString, Bundle paramBundle)
        throws RemoteException
      {
        // Byte code:
        //   0: invokestatic 28	android/os/Parcel:obtain	()Landroid/os/Parcel;
        //   3: astore 6
        //   5: invokestatic 28	android/os/Parcel:obtain	()Landroid/os/Parcel;
        //   8: astore 5
        //   10: aload 6
        //   12: ldc 30
        //   14: invokevirtual 34	android/os/Parcel:writeInterfaceToken	(Ljava/lang/String;)V
        //   17: aload_1
        //   18: ifnull +80 -> 98
        //   21: aload_1
        //   22: invokeinterface 40 1 0
        //   27: astore_1
        //   28: aload 6
        //   30: aload_1
        //   31: invokevirtual 43	android/os/Parcel:writeStrongBinder	(Landroid/os/IBinder;)V
        //   34: aload 6
        //   36: iload_2
        //   37: invokevirtual 47	android/os/Parcel:writeInt	(I)V
        //   40: aload 6
        //   42: aload_3
        //   43: invokevirtual 64	android/os/Parcel:writeString	(Ljava/lang/String;)V
        //   46: aload 4
        //   48: ifnull +55 -> 103
        //   51: aload 6
        //   53: iconst_1
        //   54: invokevirtual 47	android/os/Parcel:writeInt	(I)V
        //   57: aload 4
        //   59: aload 6
        //   61: iconst_0
        //   62: invokevirtual 71	android/os/Bundle:writeToParcel	(Landroid/os/Parcel;I)V
        //   65: aload_0
        //   66: getfield 18	com/google/android/gms/common/internal/l$a$a:lb	Landroid/os/IBinder;
        //   69: bipush 38
        //   71: aload 6
        //   73: aload 5
        //   75: iconst_0
        //   76: invokeinterface 53 5 0
        //   81: pop
        //   82: aload 5
        //   84: invokevirtual 56	android/os/Parcel:readException	()V
        //   87: aload 5
        //   89: invokevirtual 59	android/os/Parcel:recycle	()V
        //   92: aload 6
        //   94: invokevirtual 59	android/os/Parcel:recycle	()V
        //   97: return
        //   98: aconst_null
        //   99: astore_1
        //   100: goto -72 -> 28
        //   103: aload 6
        //   105: iconst_0
        //   106: invokevirtual 47	android/os/Parcel:writeInt	(I)V
        //   109: goto -44 -> 65
        //   112: astore_1
        //   113: aload 5
        //   115: invokevirtual 59	android/os/Parcel:recycle	()V
        //   118: aload 6
        //   120: invokevirtual 59	android/os/Parcel:recycle	()V
        //   123: aload_1
        //   124: athrow
        // Local variable table:
        //   start	length	slot	name	signature
        //   0	125	0	this	a
        //   0	125	1	paramk	k
        //   0	125	2	paramInt	int
        //   0	125	3	paramString	String
        //   0	125	4	paramBundle	Bundle
        //   8	106	5	localParcel1	Parcel
        //   3	116	6	localParcel2	Parcel
        // Exception table:
        //   from	to	target	type
        //   10	17	112	finally
        //   21	28	112	finally
        //   28	46	112	finally
        //   51	65	112	finally
        //   65	87	112	finally
        //   103	109	112	finally
      }
      
      /* Error */
      public void s(k paramk, int paramInt, String paramString, Bundle paramBundle)
        throws RemoteException
      {
        // Byte code:
        //   0: invokestatic 28	android/os/Parcel:obtain	()Landroid/os/Parcel;
        //   3: astore 6
        //   5: invokestatic 28	android/os/Parcel:obtain	()Landroid/os/Parcel;
        //   8: astore 5
        //   10: aload 6
        //   12: ldc 30
        //   14: invokevirtual 34	android/os/Parcel:writeInterfaceToken	(Ljava/lang/String;)V
        //   17: aload_1
        //   18: ifnull +80 -> 98
        //   21: aload_1
        //   22: invokeinterface 40 1 0
        //   27: astore_1
        //   28: aload 6
        //   30: aload_1
        //   31: invokevirtual 43	android/os/Parcel:writeStrongBinder	(Landroid/os/IBinder;)V
        //   34: aload 6
        //   36: iload_2
        //   37: invokevirtual 47	android/os/Parcel:writeInt	(I)V
        //   40: aload 6
        //   42: aload_3
        //   43: invokevirtual 64	android/os/Parcel:writeString	(Ljava/lang/String;)V
        //   46: aload 4
        //   48: ifnull +55 -> 103
        //   51: aload 6
        //   53: iconst_1
        //   54: invokevirtual 47	android/os/Parcel:writeInt	(I)V
        //   57: aload 4
        //   59: aload 6
        //   61: iconst_0
        //   62: invokevirtual 71	android/os/Bundle:writeToParcel	(Landroid/os/Parcel;I)V
        //   65: aload_0
        //   66: getfield 18	com/google/android/gms/common/internal/l$a$a:lb	Landroid/os/IBinder;
        //   69: bipush 41
        //   71: aload 6
        //   73: aload 5
        //   75: iconst_0
        //   76: invokeinterface 53 5 0
        //   81: pop
        //   82: aload 5
        //   84: invokevirtual 56	android/os/Parcel:readException	()V
        //   87: aload 5
        //   89: invokevirtual 59	android/os/Parcel:recycle	()V
        //   92: aload 6
        //   94: invokevirtual 59	android/os/Parcel:recycle	()V
        //   97: return
        //   98: aconst_null
        //   99: astore_1
        //   100: goto -72 -> 28
        //   103: aload 6
        //   105: iconst_0
        //   106: invokevirtual 47	android/os/Parcel:writeInt	(I)V
        //   109: goto -44 -> 65
        //   112: astore_1
        //   113: aload 5
        //   115: invokevirtual 59	android/os/Parcel:recycle	()V
        //   118: aload 6
        //   120: invokevirtual 59	android/os/Parcel:recycle	()V
        //   123: aload_1
        //   124: athrow
        // Local variable table:
        //   start	length	slot	name	signature
        //   0	125	0	this	a
        //   0	125	1	paramk	k
        //   0	125	2	paramInt	int
        //   0	125	3	paramString	String
        //   0	125	4	paramBundle	Bundle
        //   8	106	5	localParcel1	Parcel
        //   3	116	6	localParcel2	Parcel
        // Exception table:
        //   from	to	target	type
        //   10	17	112	finally
        //   21	28	112	finally
        //   28	46	112	finally
        //   51	65	112	finally
        //   65	87	112	finally
        //   103	109	112	finally
      }
      
      /* Error */
      public void t(k paramk, int paramInt, String paramString, Bundle paramBundle)
        throws RemoteException
      {
        // Byte code:
        //   0: invokestatic 28	android/os/Parcel:obtain	()Landroid/os/Parcel;
        //   3: astore 5
        //   5: invokestatic 28	android/os/Parcel:obtain	()Landroid/os/Parcel;
        //   8: astore 6
        //   10: aload 5
        //   12: ldc 30
        //   14: invokevirtual 34	android/os/Parcel:writeInterfaceToken	(Ljava/lang/String;)V
        //   17: aload_1
        //   18: ifnull +80 -> 98
        //   21: aload_1
        //   22: invokeinterface 40 1 0
        //   27: astore_1
        //   28: aload 5
        //   30: aload_1
        //   31: invokevirtual 43	android/os/Parcel:writeStrongBinder	(Landroid/os/IBinder;)V
        //   34: aload 5
        //   36: iload_2
        //   37: invokevirtual 47	android/os/Parcel:writeInt	(I)V
        //   40: aload 5
        //   42: aload_3
        //   43: invokevirtual 64	android/os/Parcel:writeString	(Ljava/lang/String;)V
        //   46: aload 4
        //   48: ifnull +55 -> 103
        //   51: aload 5
        //   53: iconst_1
        //   54: invokevirtual 47	android/os/Parcel:writeInt	(I)V
        //   57: aload 4
        //   59: aload 5
        //   61: iconst_0
        //   62: invokevirtual 71	android/os/Bundle:writeToParcel	(Landroid/os/Parcel;I)V
        //   65: aload_0
        //   66: getfield 18	com/google/android/gms/common/internal/l$a$a:lb	Landroid/os/IBinder;
        //   69: bipush 43
        //   71: aload 5
        //   73: aload 6
        //   75: iconst_0
        //   76: invokeinterface 53 5 0
        //   81: pop
        //   82: aload 6
        //   84: invokevirtual 56	android/os/Parcel:readException	()V
        //   87: aload 6
        //   89: invokevirtual 59	android/os/Parcel:recycle	()V
        //   92: aload 5
        //   94: invokevirtual 59	android/os/Parcel:recycle	()V
        //   97: return
        //   98: aconst_null
        //   99: astore_1
        //   100: goto -72 -> 28
        //   103: aload 5
        //   105: iconst_0
        //   106: invokevirtual 47	android/os/Parcel:writeInt	(I)V
        //   109: goto -44 -> 65
        //   112: astore_1
        //   113: aload 6
        //   115: invokevirtual 59	android/os/Parcel:recycle	()V
        //   118: aload 5
        //   120: invokevirtual 59	android/os/Parcel:recycle	()V
        //   123: aload_1
        //   124: athrow
        // Local variable table:
        //   start	length	slot	name	signature
        //   0	125	0	this	a
        //   0	125	1	paramk	k
        //   0	125	2	paramInt	int
        //   0	125	3	paramString	String
        //   0	125	4	paramBundle	Bundle
        //   3	116	5	localParcel1	Parcel
        //   8	106	6	localParcel2	Parcel
        // Exception table:
        //   from	to	target	type
        //   10	17	112	finally
        //   21	28	112	finally
        //   28	46	112	finally
        //   51	65	112	finally
        //   65	87	112	finally
        //   103	109	112	finally
      }
    }
  }
}


/* Location:              C:\tools\androidhack\marvel_bitva_chempionov_v11.1.0_mod_lenov.ru\classes.jar!\com\google\android\gms\common\internal\l.class
 * Java compiler version: 6 (50.0)
 * JD-Core Version:       0.7.1
 */