package com.mobileapptracker;

import android.net.Uri;
import android.net.Uri.Builder;
import java.io.BufferedReader;
import java.io.IOException;
import java.io.InputStream;
import java.io.InputStreamReader;
import java.net.HttpURLConnection;
import java.net.URL;

final class g
{
  public static String a(int paramInt)
  {
    Object localObject6 = null;
    String str3 = null;
    Uri.Builder localBuilder = new Uri.Builder();
    Object localObject4 = localBuilder.scheme("https").authority(b.a() + ".deeplink.mobileapptracking.com").appendPath("v1").appendPath("link.txt").appendQueryParameter("platform", "android").appendQueryParameter("advertiser_id", b.a()).appendQueryParameter("ver", "3.9.1").appendQueryParameter("package_name", b.c());
    Object localObject1;
    Object localObject5;
    if (b.e() != null)
    {
      localObject1 = b.e();
      ((Uri.Builder)localObject4).appendQueryParameter("ad_id", (String)localObject1).appendQueryParameter("user_agent", b.d());
      if (b.e() != null) {
        localBuilder.appendQueryParameter("google_ad_tracking_disabled", Integer.toString(b.f()));
      }
      localObject5 = str3;
      localObject4 = localObject6;
    }
    for (;;)
    {
      try
      {
        localObject1 = new java/net/URL;
        localObject5 = str3;
        localObject4 = localObject6;
        ((URL)localObject1).<init>(localBuilder.build().toString());
        localObject5 = str3;
        localObject4 = localObject6;
        localObject1 = (HttpURLConnection)((URL)localObject1).openConnection();
        localObject5 = str3;
        localObject4 = localObject6;
        ((HttpURLConnection)localObject1).setReadTimeout(paramInt);
        localObject5 = str3;
        localObject4 = localObject6;
        ((HttpURLConnection)localObject1).setConnectTimeout(paramInt);
        localObject5 = str3;
        localObject4 = localObject6;
        ((HttpURLConnection)localObject1).setRequestProperty("X-MAT-Key", b.b());
        localObject5 = str3;
        localObject4 = localObject6;
        ((HttpURLConnection)localObject1).setRequestMethod("GET");
        localObject5 = str3;
        localObject4 = localObject6;
        ((HttpURLConnection)localObject1).setDoInput(true);
        localObject5 = str3;
        localObject4 = localObject6;
        ((HttpURLConnection)localObject1).connect();
        localObject5 = str3;
        localObject4 = localObject6;
        if (((HttpURLConnection)localObject1).getResponseCode() == 200)
        {
          localObject5 = str3;
          localObject4 = localObject6;
          localObject1 = ((HttpURLConnection)localObject1).getInputStream();
          localObject5 = localObject1;
          localObject4 = localObject1;
          str3 = a((InputStream)localObject1);
          localObject4 = str3;
        }
      }
      catch (Exception localException)
      {
        Object localObject2;
        localException = localException;
        localObject4 = localObject5;
        localException.printStackTrace();
        try
        {
          ((InputStream)localObject5).close();
          String str1 = "";
        }
        catch (IOException localIOException2)
        {
          localIOException2.printStackTrace();
          String str2 = "";
        }
        continue;
      }
      finally {}
      try
      {
        ((InputStream)localObject1).close();
        localObject1 = localObject4;
      }
      catch (IOException localIOException1)
      {
        localIOException1.printStackTrace();
        localObject2 = localObject4;
        continue;
      }
      return (String)localObject1;
      localObject1 = b.g();
      break;
      localObject5 = str3;
      localObject4 = localObject6;
      localObject1 = ((HttpURLConnection)localObject1).getErrorStream();
    }
    try
    {
      ((InputStream)localObject4).close();
      throw ((Throwable)localObject3);
    }
    catch (IOException localIOException3)
    {
      for (;;)
      {
        localIOException3.printStackTrace();
      }
    }
  }
  
  private static String a(InputStream paramInputStream)
  {
    StringBuilder localStringBuilder;
    if (paramInputStream != null)
    {
      paramInputStream = new BufferedReader(new InputStreamReader(paramInputStream, "UTF-8"));
      localStringBuilder = new StringBuilder();
      for (;;)
      {
        String str = paramInputStream.readLine();
        if (str == null) {
          break;
        }
        localStringBuilder.append(str).append("\n");
      }
      paramInputStream.close();
    }
    for (paramInputStream = localStringBuilder.toString();; paramInputStream = "") {
      return paramInputStream;
    }
  }
  
  /* Error */
  protected static org.json.JSONObject a(String paramString, org.json.JSONObject paramJSONObject, boolean paramBoolean)
  {
    // Byte code:
    //   0: aconst_null
    //   1: astore 6
    //   3: new 92	java/net/URL
    //   6: astore 5
    //   8: aload 5
    //   10: aload_0
    //   11: invokespecial 102	java/net/URL:<init>	(Ljava/lang/String;)V
    //   14: aload 5
    //   16: invokevirtual 106	java/net/URL:openConnection	()Ljava/net/URLConnection;
    //   19: checkcast 108	java/net/HttpURLConnection
    //   22: astore 8
    //   24: aload 8
    //   26: ldc -71
    //   28: invokevirtual 112	java/net/HttpURLConnection:setReadTimeout	(I)V
    //   31: aload 8
    //   33: ldc -71
    //   35: invokevirtual 115	java/net/HttpURLConnection:setConnectTimeout	(I)V
    //   38: aload 8
    //   40: iconst_1
    //   41: invokevirtual 133	java/net/HttpURLConnection:setDoInput	(Z)V
    //   44: aload_1
    //   45: ifnull +10 -> 55
    //   48: aload_1
    //   49: invokevirtual 190	org/json/JSONObject:length	()I
    //   52: ifne +247 -> 299
    //   55: aload 8
    //   57: ldc 126
    //   59: invokevirtual 129	java/net/HttpURLConnection:setRequestMethod	(Ljava/lang/String;)V
    //   62: aload 8
    //   64: invokevirtual 136	java/net/HttpURLConnection:connect	()V
    //   67: aload 8
    //   69: invokevirtual 139	java/net/HttpURLConnection:getResponseCode	()I
    //   72: istore 4
    //   74: iload_2
    //   75: ifeq +28 -> 103
    //   78: new 26	java/lang/StringBuilder
    //   81: astore_1
    //   82: aload_1
    //   83: ldc -64
    //   85: invokespecial 193	java/lang/StringBuilder:<init>	(Ljava/lang/String;)V
    //   88: ldc -61
    //   90: aload_1
    //   91: iload 4
    //   93: invokevirtual 198	java/lang/StringBuilder:append	(I)Ljava/lang/StringBuilder;
    //   96: invokevirtual 41	java/lang/StringBuilder:toString	()Ljava/lang/String;
    //   99: invokestatic 203	android/util/Log:d	(Ljava/lang/String;Ljava/lang/String;)I
    //   102: pop
    //   103: iload 4
    //   105: sipush 200
    //   108: if_icmpne +312 -> 420
    //   111: aload 8
    //   113: invokevirtual 143	java/net/HttpURLConnection:getInputStream	()Ljava/io/InputStream;
    //   116: astore 5
    //   118: aload 5
    //   120: invokestatic 146	com/mobileapptracker/g:a	(Ljava/io/InputStream;)Ljava/lang/String;
    //   123: astore_1
    //   124: iload_2
    //   125: ifeq +30 -> 155
    //   128: new 26	java/lang/StringBuilder
    //   131: astore 6
    //   133: aload 6
    //   135: ldc -51
    //   137: invokespecial 193	java/lang/StringBuilder:<init>	(Ljava/lang/String;)V
    //   140: ldc -61
    //   142: aload 6
    //   144: aload_1
    //   145: invokevirtual 36	java/lang/StringBuilder:append	(Ljava/lang/String;)Ljava/lang/StringBuilder;
    //   148: invokevirtual 41	java/lang/StringBuilder:toString	()Ljava/lang/String;
    //   151: invokestatic 203	android/util/Log:d	(Ljava/lang/String;Ljava/lang/String;)I
    //   154: pop
    //   155: new 187	org/json/JSONObject
    //   158: astore 7
    //   160: aload 7
    //   162: invokespecial 206	org/json/JSONObject:<init>	()V
    //   165: new 208	org/json/JSONTokener
    //   168: astore 6
    //   170: aload 6
    //   172: aload_1
    //   173: invokespecial 209	org/json/JSONTokener:<init>	(Ljava/lang/String;)V
    //   176: new 187	org/json/JSONObject
    //   179: astore_1
    //   180: aload_1
    //   181: aload 6
    //   183: invokespecial 212	org/json/JSONObject:<init>	(Lorg/json/JSONTokener;)V
    //   186: iload_2
    //   187: ifeq +507 -> 694
    //   190: aload_1
    //   191: invokevirtual 190	org/json/JSONObject:length	()I
    //   194: istore_3
    //   195: iload_3
    //   196: ifle +498 -> 694
    //   199: aload_1
    //   200: ldc -42
    //   202: invokevirtual 218	org/json/JSONObject:has	(Ljava/lang/String;)Z
    //   205: ifeq +225 -> 430
    //   208: aload_1
    //   209: ldc -42
    //   211: invokevirtual 222	org/json/JSONObject:getJSONArray	(Ljava/lang/String;)Lorg/json/JSONArray;
    //   214: invokevirtual 225	org/json/JSONArray:length	()I
    //   217: ifeq +213 -> 430
    //   220: aload_1
    //   221: ldc -42
    //   223: invokevirtual 222	org/json/JSONObject:getJSONArray	(Ljava/lang/String;)Lorg/json/JSONArray;
    //   226: iconst_0
    //   227: invokevirtual 228	org/json/JSONArray:getString	(I)Ljava/lang/String;
    //   230: astore 6
    //   232: new 26	java/lang/StringBuilder
    //   235: astore 7
    //   237: aload 7
    //   239: ldc -26
    //   241: invokespecial 193	java/lang/StringBuilder:<init>	(Ljava/lang/String;)V
    //   244: ldc -61
    //   246: aload 7
    //   248: aload 6
    //   250: invokevirtual 36	java/lang/StringBuilder:append	(Ljava/lang/String;)Ljava/lang/StringBuilder;
    //   253: invokevirtual 41	java/lang/StringBuilder:toString	()Ljava/lang/String;
    //   256: invokestatic 203	android/util/Log:d	(Ljava/lang/String;Ljava/lang/String;)I
    //   259: pop
    //   260: aload 8
    //   262: ldc -24
    //   264: invokevirtual 236	java/net/HttpURLConnection:getHeaderField	(Ljava/lang/String;)Ljava/lang/String;
    //   267: astore 6
    //   269: iload 4
    //   271: sipush 200
    //   274: if_icmplt +444 -> 718
    //   277: iload 4
    //   279: sipush 300
    //   282: if_icmpge +436 -> 718
    //   285: aload 5
    //   287: ifnull +8 -> 295
    //   290: aload 5
    //   292: invokevirtual 151	java/io/InputStream:close	()V
    //   295: aload_1
    //   296: astore_0
    //   297: aload_0
    //   298: areturn
    //   299: aload 8
    //   301: iconst_1
    //   302: invokevirtual 239	java/net/HttpURLConnection:setDoOutput	(Z)V
    //   305: aload 8
    //   307: ldc -15
    //   309: ldc -13
    //   311: invokevirtual 124	java/net/HttpURLConnection:setRequestProperty	(Ljava/lang/String;Ljava/lang/String;)V
    //   314: aload 8
    //   316: ldc -11
    //   318: ldc -13
    //   320: invokevirtual 124	java/net/HttpURLConnection:setRequestProperty	(Ljava/lang/String;Ljava/lang/String;)V
    //   323: aload 8
    //   325: ldc -9
    //   327: invokevirtual 129	java/net/HttpURLConnection:setRequestMethod	(Ljava/lang/String;)V
    //   330: aload 8
    //   332: invokevirtual 251	java/net/HttpURLConnection:getOutputStream	()Ljava/io/OutputStream;
    //   335: astore 5
    //   337: aload 5
    //   339: aload_1
    //   340: invokevirtual 252	org/json/JSONObject:toString	()Ljava/lang/String;
    //   343: ldc -87
    //   345: invokevirtual 258	java/lang/String:getBytes	(Ljava/lang/String;)[B
    //   348: invokevirtual 264	java/io/OutputStream:write	([B)V
    //   351: aload 5
    //   353: invokevirtual 265	java/io/OutputStream:close	()V
    //   356: goto -294 -> 62
    //   359: astore 5
    //   361: aload 6
    //   363: astore_1
    //   364: iload_2
    //   365: ifeq +31 -> 396
    //   368: new 26	java/lang/StringBuilder
    //   371: astore 6
    //   373: aload 6
    //   375: ldc_w 267
    //   378: invokespecial 193	java/lang/StringBuilder:<init>	(Ljava/lang/String;)V
    //   381: ldc -61
    //   383: aload 6
    //   385: aload_0
    //   386: invokevirtual 36	java/lang/StringBuilder:append	(Ljava/lang/String;)Ljava/lang/StringBuilder;
    //   389: invokevirtual 41	java/lang/StringBuilder:toString	()Ljava/lang/String;
    //   392: invokestatic 203	android/util/Log:d	(Ljava/lang/String;Ljava/lang/String;)I
    //   395: pop
    //   396: aload 5
    //   398: invokevirtual 161	java/lang/Exception:printStackTrace	()V
    //   401: aload_1
    //   402: ifnull +7 -> 409
    //   405: aload_1
    //   406: invokevirtual 151	java/io/InputStream:close	()V
    //   409: new 187	org/json/JSONObject
    //   412: dup
    //   413: invokespecial 206	org/json/JSONObject:<init>	()V
    //   416: astore_0
    //   417: goto -120 -> 297
    //   420: aload 8
    //   422: invokevirtual 157	java/net/HttpURLConnection:getErrorStream	()Ljava/io/InputStream;
    //   425: astore 5
    //   427: goto -309 -> 118
    //   430: aload_1
    //   431: ldc_w 269
    //   434: invokevirtual 218	org/json/JSONObject:has	(Ljava/lang/String;)Z
    //   437: ifeq +163 -> 600
    //   440: aload_1
    //   441: ldc_w 269
    //   444: invokevirtual 271	org/json/JSONObject:getString	(Ljava/lang/String;)Ljava/lang/String;
    //   447: ldc_w 273
    //   450: invokevirtual 277	java/lang/String:equals	(Ljava/lang/Object;)Z
    //   453: ifne +147 -> 600
    //   456: aload_1
    //   457: ldc_w 269
    //   460: invokevirtual 271	org/json/JSONObject:getString	(Ljava/lang/String;)Ljava/lang/String;
    //   463: ldc_w 279
    //   466: invokevirtual 277	java/lang/String:equals	(Ljava/lang/Object;)Z
    //   469: ifne +131 -> 600
    //   472: aload_1
    //   473: ldc_w 269
    //   476: invokevirtual 271	org/json/JSONObject:getString	(Ljava/lang/String;)Ljava/lang/String;
    //   479: ldc_w 281
    //   482: invokevirtual 277	java/lang/String:equals	(Ljava/lang/Object;)Z
    //   485: ifne +115 -> 600
    //   488: aload_1
    //   489: ldc_w 269
    //   492: invokevirtual 285	org/json/JSONObject:getJSONObject	(Ljava/lang/String;)Lorg/json/JSONObject;
    //   495: astore 6
    //   497: aload 6
    //   499: ldc_w 287
    //   502: invokevirtual 218	org/json/JSONObject:has	(Ljava/lang/String;)Z
    //   505: ifeq +92 -> 597
    //   508: aload 6
    //   510: ldc_w 287
    //   513: invokevirtual 285	org/json/JSONObject:getJSONObject	(Ljava/lang/String;)Lorg/json/JSONObject;
    //   516: astore 6
    //   518: aload 6
    //   520: ldc_w 289
    //   523: invokevirtual 218	org/json/JSONObject:has	(Ljava/lang/String;)Z
    //   526: ifeq +71 -> 597
    //   529: aload 6
    //   531: ldc_w 289
    //   534: invokevirtual 271	org/json/JSONObject:getString	(Ljava/lang/String;)Ljava/lang/String;
    //   537: ldc_w 291
    //   540: invokevirtual 277	java/lang/String:equals	(Ljava/lang/Object;)Z
    //   543: ifeq +45 -> 588
    //   546: aload 6
    //   548: ldc_w 293
    //   551: invokevirtual 271	org/json/JSONObject:getString	(Ljava/lang/String;)Ljava/lang/String;
    //   554: astore 6
    //   556: new 26	java/lang/StringBuilder
    //   559: astore 7
    //   561: aload 7
    //   563: ldc_w 295
    //   566: invokespecial 193	java/lang/StringBuilder:<init>	(Ljava/lang/String;)V
    //   569: ldc -61
    //   571: aload 7
    //   573: aload 6
    //   575: invokevirtual 36	java/lang/StringBuilder:append	(Ljava/lang/String;)Ljava/lang/StringBuilder;
    //   578: invokevirtual 41	java/lang/StringBuilder:toString	()Ljava/lang/String;
    //   581: invokestatic 203	android/util/Log:d	(Ljava/lang/String;Ljava/lang/String;)I
    //   584: pop
    //   585: goto -325 -> 260
    //   588: ldc -61
    //   590: ldc_w 297
    //   593: invokestatic 203	android/util/Log:d	(Ljava/lang/String;Ljava/lang/String;)I
    //   596: pop
    //   597: goto -337 -> 260
    //   600: aload_1
    //   601: ldc_w 299
    //   604: invokevirtual 218	org/json/JSONObject:has	(Ljava/lang/String;)Z
    //   607: ifeq +68 -> 675
    //   610: aload_1
    //   611: ldc_w 299
    //   614: invokevirtual 285	org/json/JSONObject:getJSONObject	(Ljava/lang/String;)Lorg/json/JSONObject;
    //   617: astore 6
    //   619: aload 6
    //   621: ldc_w 301
    //   624: invokevirtual 218	org/json/JSONObject:has	(Ljava/lang/String;)Z
    //   627: ifeq +48 -> 675
    //   630: aload 6
    //   632: ldc_w 301
    //   635: invokevirtual 271	org/json/JSONObject:getString	(Ljava/lang/String;)Ljava/lang/String;
    //   638: astore 7
    //   640: new 26	java/lang/StringBuilder
    //   643: astore 6
    //   645: aload 6
    //   647: ldc_w 303
    //   650: invokespecial 193	java/lang/StringBuilder:<init>	(Ljava/lang/String;)V
    //   653: ldc -61
    //   655: aload 6
    //   657: aload 7
    //   659: invokevirtual 36	java/lang/StringBuilder:append	(Ljava/lang/String;)Ljava/lang/StringBuilder;
    //   662: ldc_w 305
    //   665: invokevirtual 36	java/lang/StringBuilder:append	(Ljava/lang/String;)Ljava/lang/StringBuilder;
    //   668: invokevirtual 41	java/lang/StringBuilder:toString	()Ljava/lang/String;
    //   671: invokestatic 203	android/util/Log:d	(Ljava/lang/String;Ljava/lang/String;)I
    //   674: pop
    //   675: goto -415 -> 260
    //   678: astore 6
    //   680: ldc -61
    //   682: ldc_w 307
    //   685: invokestatic 203	android/util/Log:d	(Ljava/lang/String;Ljava/lang/String;)I
    //   688: pop
    //   689: aload 6
    //   691: invokevirtual 308	org/json/JSONException:printStackTrace	()V
    //   694: goto -434 -> 260
    //   697: astore 6
    //   699: aload 7
    //   701: astore_1
    //   702: aload 6
    //   704: invokevirtual 161	java/lang/Exception:printStackTrace	()V
    //   707: goto -447 -> 260
    //   710: astore_0
    //   711: aload_0
    //   712: invokevirtual 160	java/io/IOException:printStackTrace	()V
    //   715: goto -420 -> 295
    //   718: iload 4
    //   720: sipush 400
    //   723: if_icmpne +44 -> 767
    //   726: aload 6
    //   728: ifnull +39 -> 767
    //   731: iload_2
    //   732: ifeq +12 -> 744
    //   735: ldc -61
    //   737: ldc_w 310
    //   740: invokestatic 203	android/util/Log:d	(Ljava/lang/String;Ljava/lang/String;)I
    //   743: pop
    //   744: aload 5
    //   746: ifnull +8 -> 754
    //   749: aload 5
    //   751: invokevirtual 151	java/io/InputStream:close	()V
    //   754: aconst_null
    //   755: astore_0
    //   756: goto -459 -> 297
    //   759: astore_0
    //   760: aload_0
    //   761: invokevirtual 160	java/io/IOException:printStackTrace	()V
    //   764: goto -10 -> 754
    //   767: aload 5
    //   769: ifnull -360 -> 409
    //   772: aload 5
    //   774: invokevirtual 151	java/io/InputStream:close	()V
    //   777: goto -368 -> 409
    //   780: astore_0
    //   781: aload_0
    //   782: invokevirtual 160	java/io/IOException:printStackTrace	()V
    //   785: goto -376 -> 409
    //   788: astore_0
    //   789: aload_0
    //   790: invokevirtual 160	java/io/IOException:printStackTrace	()V
    //   793: goto -384 -> 409
    //   796: astore_0
    //   797: aconst_null
    //   798: astore 5
    //   800: aload 5
    //   802: ifnull +8 -> 810
    //   805: aload 5
    //   807: invokevirtual 151	java/io/InputStream:close	()V
    //   810: aload_0
    //   811: athrow
    //   812: astore_1
    //   813: aload_1
    //   814: invokevirtual 160	java/io/IOException:printStackTrace	()V
    //   817: goto -7 -> 810
    //   820: astore_0
    //   821: goto -21 -> 800
    //   824: astore_0
    //   825: aload_1
    //   826: astore 5
    //   828: goto -28 -> 800
    //   831: astore 6
    //   833: aload 5
    //   835: astore_1
    //   836: aload 6
    //   838: astore 5
    //   840: goto -476 -> 364
    //   843: astore 6
    //   845: goto -143 -> 702
    // Local variable table:
    //   start	length	slot	name	signature
    //   0	848	0	paramString	String
    //   0	848	1	paramJSONObject	org.json.JSONObject
    //   0	848	2	paramBoolean	boolean
    //   194	2	3	i	int
    //   72	652	4	j	int
    //   6	346	5	localObject1	Object
    //   359	38	5	localException1	Exception
    //   425	414	5	localObject2	Object
    //   1	655	6	localObject3	Object
    //   678	12	6	localJSONException	org.json.JSONException
    //   697	30	6	localException2	Exception
    //   831	6	6	localException3	Exception
    //   843	1	6	localException4	Exception
    //   158	542	7	localObject4	Object
    //   22	399	8	localHttpURLConnection	HttpURLConnection
    // Exception table:
    //   from	to	target	type
    //   3	44	359	java/lang/Exception
    //   48	55	359	java/lang/Exception
    //   55	62	359	java/lang/Exception
    //   62	74	359	java/lang/Exception
    //   78	103	359	java/lang/Exception
    //   111	118	359	java/lang/Exception
    //   299	356	359	java/lang/Exception
    //   420	427	359	java/lang/Exception
    //   199	260	678	org/json/JSONException
    //   430	585	678	org/json/JSONException
    //   588	597	678	org/json/JSONException
    //   600	675	678	org/json/JSONException
    //   165	186	697	java/lang/Exception
    //   290	295	710	java/io/IOException
    //   749	754	759	java/io/IOException
    //   772	777	780	java/io/IOException
    //   405	409	788	java/io/IOException
    //   3	44	796	finally
    //   48	55	796	finally
    //   55	62	796	finally
    //   62	74	796	finally
    //   78	103	796	finally
    //   111	118	796	finally
    //   299	356	796	finally
    //   420	427	796	finally
    //   805	810	812	java/io/IOException
    //   118	124	820	finally
    //   128	155	820	finally
    //   155	165	820	finally
    //   165	186	820	finally
    //   190	195	820	finally
    //   199	260	820	finally
    //   260	269	820	finally
    //   430	585	820	finally
    //   588	597	820	finally
    //   600	675	820	finally
    //   680	694	820	finally
    //   702	707	820	finally
    //   735	744	820	finally
    //   368	396	824	finally
    //   396	401	824	finally
    //   118	124	831	java/lang/Exception
    //   128	155	831	java/lang/Exception
    //   155	165	831	java/lang/Exception
    //   260	269	831	java/lang/Exception
    //   702	707	831	java/lang/Exception
    //   735	744	831	java/lang/Exception
    //   190	195	843	java/lang/Exception
    //   199	260	843	java/lang/Exception
    //   430	585	843	java/lang/Exception
    //   588	597	843	java/lang/Exception
    //   600	675	843	java/lang/Exception
    //   680	694	843	java/lang/Exception
  }
}


/* Location:              C:\tools\androidhack\marvel_bitva_chempionov_v11.1.0_mod_lenov.ru\classes.jar!\com\mobileapptracker\g.class
 * Java compiler version: 6 (50.0)
 * JD-Core Version:       0.7.1
 */