package com.sec.android.iap;

import android.os.Binder;
import android.os.Bundle;
import android.os.IBinder;
import android.os.IInterface;
import android.os.Parcel;
import android.os.Parcelable.Creator;
import android.os.RemoteException;

public abstract interface IAPServiceCallback
  extends IInterface
{
  public abstract void responseCallback(Bundle paramBundle)
    throws RemoteException;
  
  public static abstract class Stub
    extends Binder
    implements IAPServiceCallback
  {
    private static final String DESCRIPTOR = "com.sec.android.iap.IAPServiceCallback";
    static final int TRANSACTION_responseCallback = 1;
    
    public Stub()
    {
      attachInterface(this, "com.sec.android.iap.IAPServiceCallback");
    }
    
    public static IAPServiceCallback asInterface(IBinder paramIBinder)
    {
      if (paramIBinder == null) {
        paramIBinder = null;
      }
      for (;;)
      {
        return paramIBinder;
        IInterface localIInterface = paramIBinder.queryLocalInterface("com.sec.android.iap.IAPServiceCallback");
        if ((localIInterface != null) && ((localIInterface instanceof IAPServiceCallback))) {
          paramIBinder = (IAPServiceCallback)localIInterface;
        } else {
          paramIBinder = new Proxy(paramIBinder);
        }
      }
    }
    
    public IBinder asBinder()
    {
      return this;
    }
    
    public boolean onTransact(int paramInt1, Parcel paramParcel1, Parcel paramParcel2, int paramInt2)
      throws RemoteException
    {
      boolean bool = true;
      switch (paramInt1)
      {
      default: 
        bool = super.onTransact(paramInt1, paramParcel1, paramParcel2, paramInt2);
      case 1598968902: 
        for (;;)
        {
          return bool;
          paramParcel2.writeString("com.sec.android.iap.IAPServiceCallback");
        }
      }
      paramParcel1.enforceInterface("com.sec.android.iap.IAPServiceCallback");
      if (paramParcel1.readInt() != 0) {}
      for (paramParcel1 = (Bundle)Bundle.CREATOR.createFromParcel(paramParcel1);; paramParcel1 = null)
      {
        responseCallback(paramParcel1);
        break;
      }
    }
    
    private static class Proxy
      implements IAPServiceCallback
    {
      private IBinder mRemote;
      
      Proxy(IBinder paramIBinder)
      {
        this.mRemote = paramIBinder;
      }
      
      public IBinder asBinder()
      {
        return this.mRemote;
      }
      
      public String getInterfaceDescriptor()
      {
        return "com.sec.android.iap.IAPServiceCallback";
      }
      
      /* Error */
      public void responseCallback(Bundle paramBundle)
        throws RemoteException
      {
        // Byte code:
        //   0: invokestatic 36	android/os/Parcel:obtain	()Landroid/os/Parcel;
        //   3: astore_2
        //   4: aload_2
        //   5: ldc 26
        //   7: invokevirtual 40	android/os/Parcel:writeInterfaceToken	(Ljava/lang/String;)V
        //   10: aload_1
        //   11: ifnull +33 -> 44
        //   14: aload_2
        //   15: iconst_1
        //   16: invokevirtual 44	android/os/Parcel:writeInt	(I)V
        //   19: aload_1
        //   20: aload_2
        //   21: iconst_0
        //   22: invokevirtual 50	android/os/Bundle:writeToParcel	(Landroid/os/Parcel;I)V
        //   25: aload_0
        //   26: getfield 19	com/sec/android/iap/IAPServiceCallback$Stub$Proxy:mRemote	Landroid/os/IBinder;
        //   29: iconst_1
        //   30: aload_2
        //   31: aconst_null
        //   32: iconst_1
        //   33: invokeinterface 56 5 0
        //   38: pop
        //   39: aload_2
        //   40: invokevirtual 59	android/os/Parcel:recycle	()V
        //   43: return
        //   44: aload_2
        //   45: iconst_0
        //   46: invokevirtual 44	android/os/Parcel:writeInt	(I)V
        //   49: goto -24 -> 25
        //   52: astore_1
        //   53: aload_2
        //   54: invokevirtual 59	android/os/Parcel:recycle	()V
        //   57: aload_1
        //   58: athrow
        // Local variable table:
        //   start	length	slot	name	signature
        //   0	59	0	this	Proxy
        //   0	59	1	paramBundle	Bundle
        //   3	51	2	localParcel	Parcel
        // Exception table:
        //   from	to	target	type
        //   4	10	52	finally
        //   14	25	52	finally
        //   25	39	52	finally
        //   44	49	52	finally
      }
    }
  }
}


/* Location:              C:\tools\androidhack\marvel_bitva_chempionov_v11.1.0_mod_lenov.ru\classes.jar!\com\sec\android\iap\IAPServiceCallback.class
 * Java compiler version: 6 (50.0)
 * JD-Core Version:       0.7.1
 */