package com.google.android.gms.internal;

import android.os.Binder;
import android.os.IBinder;
import android.os.IInterface;
import android.os.Parcel;
import android.os.RemoteException;
import com.google.android.gms.dynamic.d;
import com.google.android.gms.dynamic.d.a;

public abstract interface bd
  extends IInterface
{
  public abstract d X()
    throws RemoteException;
  
  public abstract ay Y()
    throws RemoteException;
  
  public abstract void a(ay paramay)
    throws RemoteException;
  
  public abstract void a(bc parambc)
    throws RemoteException;
  
  public abstract void a(bf parambf)
    throws RemoteException;
  
  public abstract void a(eh parameh)
    throws RemoteException;
  
  public abstract void a(el paramel, String paramString)
    throws RemoteException;
  
  public abstract void a(et paramet)
    throws RemoteException;
  
  public abstract void a(eu parameu)
    throws RemoteException;
  
  public abstract boolean a(av paramav)
    throws RemoteException;
  
  public abstract void aj()
    throws RemoteException;
  
  public abstract void destroy()
    throws RemoteException;
  
  public abstract String getMediationAdapterClassName()
    throws RemoteException;
  
  public abstract boolean isReady()
    throws RemoteException;
  
  public abstract void pause()
    throws RemoteException;
  
  public abstract void resume()
    throws RemoteException;
  
  public abstract void showInterstitial()
    throws RemoteException;
  
  public abstract void stopLoading()
    throws RemoteException;
  
  public static abstract class a
    extends Binder
    implements bd
  {
    public a()
    {
      attachInterface(this, "com.google.android.gms.ads.internal.client.IAdManager");
    }
    
    public static bd f(IBinder paramIBinder)
    {
      if (paramIBinder == null) {
        paramIBinder = null;
      }
      for (;;)
      {
        return paramIBinder;
        IInterface localIInterface = paramIBinder.queryLocalInterface("com.google.android.gms.ads.internal.client.IAdManager");
        if ((localIInterface != null) && ((localIInterface instanceof bd))) {
          paramIBinder = (bd)localIInterface;
        } else {
          paramIBinder = new a(paramIBinder);
        }
      }
    }
    
    public IBinder asBinder()
    {
      return this;
    }
    
    public boolean onTransact(int paramInt1, Parcel paramParcel1, Parcel paramParcel2, int paramInt2)
      throws RemoteException
    {
      d locald = null;
      Object localObject2 = null;
      Object localObject1 = null;
      int i = 0;
      boolean bool1 = true;
      switch (paramInt1)
      {
      default: 
        bool1 = super.onTransact(paramInt1, paramParcel1, paramParcel2, paramInt2);
      }
      for (;;)
      {
        return bool1;
        paramParcel2.writeString("com.google.android.gms.ads.internal.client.IAdManager");
        continue;
        paramParcel1.enforceInterface("com.google.android.gms.ads.internal.client.IAdManager");
        locald = X();
        paramParcel2.writeNoException();
        paramParcel1 = (Parcel)localObject1;
        if (locald != null) {
          paramParcel1 = locald.asBinder();
        }
        paramParcel2.writeStrongBinder(paramParcel1);
        continue;
        paramParcel1.enforceInterface("com.google.android.gms.ads.internal.client.IAdManager");
        destroy();
        paramParcel2.writeNoException();
        continue;
        paramParcel1.enforceInterface("com.google.android.gms.ads.internal.client.IAdManager");
        boolean bool2 = isReady();
        paramParcel2.writeNoException();
        if (bool2) {}
        for (paramInt1 = 1;; paramInt1 = 0)
        {
          paramParcel2.writeInt(paramInt1);
          break;
        }
        paramParcel1.enforceInterface("com.google.android.gms.ads.internal.client.IAdManager");
        localObject1 = locald;
        if (paramParcel1.readInt() != 0) {
          localObject1 = av.CREATOR.b(paramParcel1);
        }
        bool2 = a((av)localObject1);
        paramParcel2.writeNoException();
        paramInt1 = i;
        if (bool2) {
          paramInt1 = 1;
        }
        paramParcel2.writeInt(paramInt1);
        continue;
        paramParcel1.enforceInterface("com.google.android.gms.ads.internal.client.IAdManager");
        pause();
        paramParcel2.writeNoException();
        continue;
        paramParcel1.enforceInterface("com.google.android.gms.ads.internal.client.IAdManager");
        resume();
        paramParcel2.writeNoException();
        continue;
        paramParcel1.enforceInterface("com.google.android.gms.ads.internal.client.IAdManager");
        a(bc.a.e(paramParcel1.readStrongBinder()));
        paramParcel2.writeNoException();
        continue;
        paramParcel1.enforceInterface("com.google.android.gms.ads.internal.client.IAdManager");
        a(bf.a.h(paramParcel1.readStrongBinder()));
        paramParcel2.writeNoException();
        continue;
        paramParcel1.enforceInterface("com.google.android.gms.ads.internal.client.IAdManager");
        showInterstitial();
        paramParcel2.writeNoException();
        continue;
        paramParcel1.enforceInterface("com.google.android.gms.ads.internal.client.IAdManager");
        stopLoading();
        paramParcel2.writeNoException();
        continue;
        paramParcel1.enforceInterface("com.google.android.gms.ads.internal.client.IAdManager");
        aj();
        paramParcel2.writeNoException();
        continue;
        paramParcel1.enforceInterface("com.google.android.gms.ads.internal.client.IAdManager");
        paramParcel1 = Y();
        paramParcel2.writeNoException();
        if (paramParcel1 != null)
        {
          paramParcel2.writeInt(1);
          paramParcel1.writeToParcel(paramParcel2, 1);
        }
        else
        {
          paramParcel2.writeInt(0);
          continue;
          paramParcel1.enforceInterface("com.google.android.gms.ads.internal.client.IAdManager");
          localObject1 = localObject2;
          if (paramParcel1.readInt() != 0) {
            localObject1 = ay.CREATOR.c(paramParcel1);
          }
          a((ay)localObject1);
          paramParcel2.writeNoException();
          continue;
          paramParcel1.enforceInterface("com.google.android.gms.ads.internal.client.IAdManager");
          a(eh.a.t(paramParcel1.readStrongBinder()));
          paramParcel2.writeNoException();
          continue;
          paramParcel1.enforceInterface("com.google.android.gms.ads.internal.client.IAdManager");
          a(el.a.x(paramParcel1.readStrongBinder()), paramParcel1.readString());
          paramParcel2.writeNoException();
          continue;
          paramParcel1.enforceInterface("com.google.android.gms.ads.internal.client.IAdManager");
          a(et.a.A(paramParcel1.readStrongBinder()));
          paramParcel2.writeNoException();
          continue;
          paramParcel1.enforceInterface("com.google.android.gms.ads.internal.client.IAdManager");
          a(eu.a.B(paramParcel1.readStrongBinder()));
          paramParcel2.writeNoException();
          continue;
          paramParcel1.enforceInterface("com.google.android.gms.ads.internal.client.IAdManager");
          paramParcel1 = getMediationAdapterClassName();
          paramParcel2.writeNoException();
          paramParcel2.writeString(paramParcel1);
        }
      }
    }
    
    private static class a
      implements bd
    {
      private IBinder lb;
      
      a(IBinder paramIBinder)
      {
        this.lb = paramIBinder;
      }
      
      public d X()
        throws RemoteException
      {
        Parcel localParcel2 = Parcel.obtain();
        Parcel localParcel1 = Parcel.obtain();
        try
        {
          localParcel2.writeInterfaceToken("com.google.android.gms.ads.internal.client.IAdManager");
          this.lb.transact(1, localParcel2, localParcel1, 0);
          localParcel1.readException();
          d locald = d.a.am(localParcel1.readStrongBinder());
          return locald;
        }
        finally
        {
          localParcel1.recycle();
          localParcel2.recycle();
        }
      }
      
      /* Error */
      public ay Y()
        throws RemoteException
      {
        // Byte code:
        //   0: invokestatic 29	android/os/Parcel:obtain	()Landroid/os/Parcel;
        //   3: astore_2
        //   4: invokestatic 29	android/os/Parcel:obtain	()Landroid/os/Parcel;
        //   7: astore_3
        //   8: aload_2
        //   9: ldc 31
        //   11: invokevirtual 35	android/os/Parcel:writeInterfaceToken	(Ljava/lang/String;)V
        //   14: aload_0
        //   15: getfield 18	com/google/android/gms/internal/bd$a$a:lb	Landroid/os/IBinder;
        //   18: bipush 12
        //   20: aload_2
        //   21: aload_3
        //   22: iconst_0
        //   23: invokeinterface 41 5 0
        //   28: pop
        //   29: aload_3
        //   30: invokevirtual 44	android/os/Parcel:readException	()V
        //   33: aload_3
        //   34: invokevirtual 64	android/os/Parcel:readInt	()I
        //   37: ifeq +21 -> 58
        //   40: getstatic 70	com/google/android/gms/internal/ay:CREATOR	Lcom/google/android/gms/internal/az;
        //   43: aload_3
        //   44: invokevirtual 76	com/google/android/gms/internal/az:c	(Landroid/os/Parcel;)Lcom/google/android/gms/internal/ay;
        //   47: astore_1
        //   48: aload_3
        //   49: invokevirtual 57	android/os/Parcel:recycle	()V
        //   52: aload_2
        //   53: invokevirtual 57	android/os/Parcel:recycle	()V
        //   56: aload_1
        //   57: areturn
        //   58: aconst_null
        //   59: astore_1
        //   60: goto -12 -> 48
        //   63: astore_1
        //   64: aload_3
        //   65: invokevirtual 57	android/os/Parcel:recycle	()V
        //   68: aload_2
        //   69: invokevirtual 57	android/os/Parcel:recycle	()V
        //   72: aload_1
        //   73: athrow
        // Local variable table:
        //   start	length	slot	name	signature
        //   0	74	0	this	a
        //   47	13	1	localay	ay
        //   63	10	1	localObject	Object
        //   3	66	2	localParcel1	Parcel
        //   7	58	3	localParcel2	Parcel
        // Exception table:
        //   from	to	target	type
        //   8	48	63	finally
      }
      
      /* Error */
      public void a(ay paramay)
        throws RemoteException
      {
        // Byte code:
        //   0: invokestatic 29	android/os/Parcel:obtain	()Landroid/os/Parcel;
        //   3: astore_3
        //   4: invokestatic 29	android/os/Parcel:obtain	()Landroid/os/Parcel;
        //   7: astore_2
        //   8: aload_3
        //   9: ldc 31
        //   11: invokevirtual 35	android/os/Parcel:writeInterfaceToken	(Ljava/lang/String;)V
        //   14: aload_1
        //   15: ifnull +42 -> 57
        //   18: aload_3
        //   19: iconst_1
        //   20: invokevirtual 81	android/os/Parcel:writeInt	(I)V
        //   23: aload_1
        //   24: aload_3
        //   25: iconst_0
        //   26: invokevirtual 85	com/google/android/gms/internal/ay:writeToParcel	(Landroid/os/Parcel;I)V
        //   29: aload_0
        //   30: getfield 18	com/google/android/gms/internal/bd$a$a:lb	Landroid/os/IBinder;
        //   33: bipush 13
        //   35: aload_3
        //   36: aload_2
        //   37: iconst_0
        //   38: invokeinterface 41 5 0
        //   43: pop
        //   44: aload_2
        //   45: invokevirtual 44	android/os/Parcel:readException	()V
        //   48: aload_2
        //   49: invokevirtual 57	android/os/Parcel:recycle	()V
        //   52: aload_3
        //   53: invokevirtual 57	android/os/Parcel:recycle	()V
        //   56: return
        //   57: aload_3
        //   58: iconst_0
        //   59: invokevirtual 81	android/os/Parcel:writeInt	(I)V
        //   62: goto -33 -> 29
        //   65: astore_1
        //   66: aload_2
        //   67: invokevirtual 57	android/os/Parcel:recycle	()V
        //   70: aload_3
        //   71: invokevirtual 57	android/os/Parcel:recycle	()V
        //   74: aload_1
        //   75: athrow
        // Local variable table:
        //   start	length	slot	name	signature
        //   0	76	0	this	a
        //   0	76	1	paramay	ay
        //   7	60	2	localParcel1	Parcel
        //   3	68	3	localParcel2	Parcel
        // Exception table:
        //   from	to	target	type
        //   8	14	65	finally
        //   18	29	65	finally
        //   29	48	65	finally
        //   57	62	65	finally
      }
      
      /* Error */
      public void a(bc parambc)
        throws RemoteException
      {
        // Byte code:
        //   0: invokestatic 29	android/os/Parcel:obtain	()Landroid/os/Parcel;
        //   3: astore_3
        //   4: invokestatic 29	android/os/Parcel:obtain	()Landroid/os/Parcel;
        //   7: astore_2
        //   8: aload_3
        //   9: ldc 31
        //   11: invokevirtual 35	android/os/Parcel:writeInterfaceToken	(Ljava/lang/String;)V
        //   14: aload_1
        //   15: ifnull +43 -> 58
        //   18: aload_1
        //   19: invokeinterface 91 1 0
        //   24: astore_1
        //   25: aload_3
        //   26: aload_1
        //   27: invokevirtual 94	android/os/Parcel:writeStrongBinder	(Landroid/os/IBinder;)V
        //   30: aload_0
        //   31: getfield 18	com/google/android/gms/internal/bd$a$a:lb	Landroid/os/IBinder;
        //   34: bipush 7
        //   36: aload_3
        //   37: aload_2
        //   38: iconst_0
        //   39: invokeinterface 41 5 0
        //   44: pop
        //   45: aload_2
        //   46: invokevirtual 44	android/os/Parcel:readException	()V
        //   49: aload_2
        //   50: invokevirtual 57	android/os/Parcel:recycle	()V
        //   53: aload_3
        //   54: invokevirtual 57	android/os/Parcel:recycle	()V
        //   57: return
        //   58: aconst_null
        //   59: astore_1
        //   60: goto -35 -> 25
        //   63: astore_1
        //   64: aload_2
        //   65: invokevirtual 57	android/os/Parcel:recycle	()V
        //   68: aload_3
        //   69: invokevirtual 57	android/os/Parcel:recycle	()V
        //   72: aload_1
        //   73: athrow
        // Local variable table:
        //   start	length	slot	name	signature
        //   0	74	0	this	a
        //   0	74	1	parambc	bc
        //   7	58	2	localParcel1	Parcel
        //   3	66	3	localParcel2	Parcel
        // Exception table:
        //   from	to	target	type
        //   8	14	63	finally
        //   18	25	63	finally
        //   25	49	63	finally
      }
      
      /* Error */
      public void a(bf parambf)
        throws RemoteException
      {
        // Byte code:
        //   0: invokestatic 29	android/os/Parcel:obtain	()Landroid/os/Parcel;
        //   3: astore_3
        //   4: invokestatic 29	android/os/Parcel:obtain	()Landroid/os/Parcel;
        //   7: astore_2
        //   8: aload_3
        //   9: ldc 31
        //   11: invokevirtual 35	android/os/Parcel:writeInterfaceToken	(Ljava/lang/String;)V
        //   14: aload_1
        //   15: ifnull +43 -> 58
        //   18: aload_1
        //   19: invokeinterface 98 1 0
        //   24: astore_1
        //   25: aload_3
        //   26: aload_1
        //   27: invokevirtual 94	android/os/Parcel:writeStrongBinder	(Landroid/os/IBinder;)V
        //   30: aload_0
        //   31: getfield 18	com/google/android/gms/internal/bd$a$a:lb	Landroid/os/IBinder;
        //   34: bipush 8
        //   36: aload_3
        //   37: aload_2
        //   38: iconst_0
        //   39: invokeinterface 41 5 0
        //   44: pop
        //   45: aload_2
        //   46: invokevirtual 44	android/os/Parcel:readException	()V
        //   49: aload_2
        //   50: invokevirtual 57	android/os/Parcel:recycle	()V
        //   53: aload_3
        //   54: invokevirtual 57	android/os/Parcel:recycle	()V
        //   57: return
        //   58: aconst_null
        //   59: astore_1
        //   60: goto -35 -> 25
        //   63: astore_1
        //   64: aload_2
        //   65: invokevirtual 57	android/os/Parcel:recycle	()V
        //   68: aload_3
        //   69: invokevirtual 57	android/os/Parcel:recycle	()V
        //   72: aload_1
        //   73: athrow
        // Local variable table:
        //   start	length	slot	name	signature
        //   0	74	0	this	a
        //   0	74	1	parambf	bf
        //   7	58	2	localParcel1	Parcel
        //   3	66	3	localParcel2	Parcel
        // Exception table:
        //   from	to	target	type
        //   8	14	63	finally
        //   18	25	63	finally
        //   25	49	63	finally
      }
      
      /* Error */
      public void a(eh parameh)
        throws RemoteException
      {
        // Byte code:
        //   0: invokestatic 29	android/os/Parcel:obtain	()Landroid/os/Parcel;
        //   3: astore_3
        //   4: invokestatic 29	android/os/Parcel:obtain	()Landroid/os/Parcel;
        //   7: astore_2
        //   8: aload_3
        //   9: ldc 31
        //   11: invokevirtual 35	android/os/Parcel:writeInterfaceToken	(Ljava/lang/String;)V
        //   14: aload_1
        //   15: ifnull +43 -> 58
        //   18: aload_1
        //   19: invokeinterface 102 1 0
        //   24: astore_1
        //   25: aload_3
        //   26: aload_1
        //   27: invokevirtual 94	android/os/Parcel:writeStrongBinder	(Landroid/os/IBinder;)V
        //   30: aload_0
        //   31: getfield 18	com/google/android/gms/internal/bd$a$a:lb	Landroid/os/IBinder;
        //   34: bipush 14
        //   36: aload_3
        //   37: aload_2
        //   38: iconst_0
        //   39: invokeinterface 41 5 0
        //   44: pop
        //   45: aload_2
        //   46: invokevirtual 44	android/os/Parcel:readException	()V
        //   49: aload_2
        //   50: invokevirtual 57	android/os/Parcel:recycle	()V
        //   53: aload_3
        //   54: invokevirtual 57	android/os/Parcel:recycle	()V
        //   57: return
        //   58: aconst_null
        //   59: astore_1
        //   60: goto -35 -> 25
        //   63: astore_1
        //   64: aload_2
        //   65: invokevirtual 57	android/os/Parcel:recycle	()V
        //   68: aload_3
        //   69: invokevirtual 57	android/os/Parcel:recycle	()V
        //   72: aload_1
        //   73: athrow
        // Local variable table:
        //   start	length	slot	name	signature
        //   0	74	0	this	a
        //   0	74	1	parameh	eh
        //   7	58	2	localParcel1	Parcel
        //   3	66	3	localParcel2	Parcel
        // Exception table:
        //   from	to	target	type
        //   8	14	63	finally
        //   18	25	63	finally
        //   25	49	63	finally
      }
      
      /* Error */
      public void a(el paramel, String paramString)
        throws RemoteException
      {
        // Byte code:
        //   0: invokestatic 29	android/os/Parcel:obtain	()Landroid/os/Parcel;
        //   3: astore 4
        //   5: invokestatic 29	android/os/Parcel:obtain	()Landroid/os/Parcel;
        //   8: astore_3
        //   9: aload 4
        //   11: ldc 31
        //   13: invokevirtual 35	android/os/Parcel:writeInterfaceToken	(Ljava/lang/String;)V
        //   16: aload_1
        //   17: ifnull +52 -> 69
        //   20: aload_1
        //   21: invokeinterface 106 1 0
        //   26: astore_1
        //   27: aload 4
        //   29: aload_1
        //   30: invokevirtual 94	android/os/Parcel:writeStrongBinder	(Landroid/os/IBinder;)V
        //   33: aload 4
        //   35: aload_2
        //   36: invokevirtual 109	android/os/Parcel:writeString	(Ljava/lang/String;)V
        //   39: aload_0
        //   40: getfield 18	com/google/android/gms/internal/bd$a$a:lb	Landroid/os/IBinder;
        //   43: bipush 15
        //   45: aload 4
        //   47: aload_3
        //   48: iconst_0
        //   49: invokeinterface 41 5 0
        //   54: pop
        //   55: aload_3
        //   56: invokevirtual 44	android/os/Parcel:readException	()V
        //   59: aload_3
        //   60: invokevirtual 57	android/os/Parcel:recycle	()V
        //   63: aload 4
        //   65: invokevirtual 57	android/os/Parcel:recycle	()V
        //   68: return
        //   69: aconst_null
        //   70: astore_1
        //   71: goto -44 -> 27
        //   74: astore_1
        //   75: aload_3
        //   76: invokevirtual 57	android/os/Parcel:recycle	()V
        //   79: aload 4
        //   81: invokevirtual 57	android/os/Parcel:recycle	()V
        //   84: aload_1
        //   85: athrow
        // Local variable table:
        //   start	length	slot	name	signature
        //   0	86	0	this	a
        //   0	86	1	paramel	el
        //   0	86	2	paramString	String
        //   8	68	3	localParcel1	Parcel
        //   3	77	4	localParcel2	Parcel
        // Exception table:
        //   from	to	target	type
        //   9	16	74	finally
        //   20	27	74	finally
        //   27	59	74	finally
      }
      
      /* Error */
      public void a(et paramet)
        throws RemoteException
      {
        // Byte code:
        //   0: invokestatic 29	android/os/Parcel:obtain	()Landroid/os/Parcel;
        //   3: astore_3
        //   4: invokestatic 29	android/os/Parcel:obtain	()Landroid/os/Parcel;
        //   7: astore_2
        //   8: aload_3
        //   9: ldc 31
        //   11: invokevirtual 35	android/os/Parcel:writeInterfaceToken	(Ljava/lang/String;)V
        //   14: aload_1
        //   15: ifnull +43 -> 58
        //   18: aload_1
        //   19: invokeinterface 113 1 0
        //   24: astore_1
        //   25: aload_3
        //   26: aload_1
        //   27: invokevirtual 94	android/os/Parcel:writeStrongBinder	(Landroid/os/IBinder;)V
        //   30: aload_0
        //   31: getfield 18	com/google/android/gms/internal/bd$a$a:lb	Landroid/os/IBinder;
        //   34: bipush 16
        //   36: aload_3
        //   37: aload_2
        //   38: iconst_0
        //   39: invokeinterface 41 5 0
        //   44: pop
        //   45: aload_2
        //   46: invokevirtual 44	android/os/Parcel:readException	()V
        //   49: aload_2
        //   50: invokevirtual 57	android/os/Parcel:recycle	()V
        //   53: aload_3
        //   54: invokevirtual 57	android/os/Parcel:recycle	()V
        //   57: return
        //   58: aconst_null
        //   59: astore_1
        //   60: goto -35 -> 25
        //   63: astore_1
        //   64: aload_2
        //   65: invokevirtual 57	android/os/Parcel:recycle	()V
        //   68: aload_3
        //   69: invokevirtual 57	android/os/Parcel:recycle	()V
        //   72: aload_1
        //   73: athrow
        // Local variable table:
        //   start	length	slot	name	signature
        //   0	74	0	this	a
        //   0	74	1	paramet	et
        //   7	58	2	localParcel1	Parcel
        //   3	66	3	localParcel2	Parcel
        // Exception table:
        //   from	to	target	type
        //   8	14	63	finally
        //   18	25	63	finally
        //   25	49	63	finally
      }
      
      /* Error */
      public void a(eu parameu)
        throws RemoteException
      {
        // Byte code:
        //   0: invokestatic 29	android/os/Parcel:obtain	()Landroid/os/Parcel;
        //   3: astore_3
        //   4: invokestatic 29	android/os/Parcel:obtain	()Landroid/os/Parcel;
        //   7: astore_2
        //   8: aload_3
        //   9: ldc 31
        //   11: invokevirtual 35	android/os/Parcel:writeInterfaceToken	(Ljava/lang/String;)V
        //   14: aload_1
        //   15: ifnull +43 -> 58
        //   18: aload_1
        //   19: invokeinterface 117 1 0
        //   24: astore_1
        //   25: aload_3
        //   26: aload_1
        //   27: invokevirtual 94	android/os/Parcel:writeStrongBinder	(Landroid/os/IBinder;)V
        //   30: aload_0
        //   31: getfield 18	com/google/android/gms/internal/bd$a$a:lb	Landroid/os/IBinder;
        //   34: bipush 17
        //   36: aload_3
        //   37: aload_2
        //   38: iconst_0
        //   39: invokeinterface 41 5 0
        //   44: pop
        //   45: aload_2
        //   46: invokevirtual 44	android/os/Parcel:readException	()V
        //   49: aload_2
        //   50: invokevirtual 57	android/os/Parcel:recycle	()V
        //   53: aload_3
        //   54: invokevirtual 57	android/os/Parcel:recycle	()V
        //   57: return
        //   58: aconst_null
        //   59: astore_1
        //   60: goto -35 -> 25
        //   63: astore_1
        //   64: aload_2
        //   65: invokevirtual 57	android/os/Parcel:recycle	()V
        //   68: aload_3
        //   69: invokevirtual 57	android/os/Parcel:recycle	()V
        //   72: aload_1
        //   73: athrow
        // Local variable table:
        //   start	length	slot	name	signature
        //   0	74	0	this	a
        //   0	74	1	parameu	eu
        //   7	58	2	localParcel1	Parcel
        //   3	66	3	localParcel2	Parcel
        // Exception table:
        //   from	to	target	type
        //   8	14	63	finally
        //   18	25	63	finally
        //   25	49	63	finally
      }
      
      public boolean a(av paramav)
        throws RemoteException
      {
        boolean bool = true;
        Parcel localParcel1 = Parcel.obtain();
        Parcel localParcel2 = Parcel.obtain();
        for (;;)
        {
          try
          {
            localParcel1.writeInterfaceToken("com.google.android.gms.ads.internal.client.IAdManager");
            if (paramav != null)
            {
              localParcel1.writeInt(1);
              paramav.writeToParcel(localParcel1, 0);
              this.lb.transact(4, localParcel1, localParcel2, 0);
              localParcel2.readException();
              int i = localParcel2.readInt();
              if (i != 0) {
                return bool;
              }
            }
            else
            {
              localParcel1.writeInt(0);
              continue;
            }
            bool = false;
          }
          finally
          {
            localParcel2.recycle();
            localParcel1.recycle();
          }
        }
      }
      
      public void aj()
        throws RemoteException
      {
        Parcel localParcel1 = Parcel.obtain();
        Parcel localParcel2 = Parcel.obtain();
        try
        {
          localParcel1.writeInterfaceToken("com.google.android.gms.ads.internal.client.IAdManager");
          this.lb.transact(11, localParcel1, localParcel2, 0);
          localParcel2.readException();
          return;
        }
        finally
        {
          localParcel2.recycle();
          localParcel1.recycle();
        }
      }
      
      public IBinder asBinder()
      {
        return this.lb;
      }
      
      public void destroy()
        throws RemoteException
      {
        Parcel localParcel1 = Parcel.obtain();
        Parcel localParcel2 = Parcel.obtain();
        try
        {
          localParcel1.writeInterfaceToken("com.google.android.gms.ads.internal.client.IAdManager");
          this.lb.transact(2, localParcel1, localParcel2, 0);
          localParcel2.readException();
          return;
        }
        finally
        {
          localParcel2.recycle();
          localParcel1.recycle();
        }
      }
      
      public String getMediationAdapterClassName()
        throws RemoteException
      {
        Parcel localParcel2 = Parcel.obtain();
        Parcel localParcel1 = Parcel.obtain();
        try
        {
          localParcel2.writeInterfaceToken("com.google.android.gms.ads.internal.client.IAdManager");
          this.lb.transact(18, localParcel2, localParcel1, 0);
          localParcel1.readException();
          String str = localParcel1.readString();
          return str;
        }
        finally
        {
          localParcel1.recycle();
          localParcel2.recycle();
        }
      }
      
      public boolean isReady()
        throws RemoteException
      {
        boolean bool = false;
        Parcel localParcel1 = Parcel.obtain();
        Parcel localParcel2 = Parcel.obtain();
        try
        {
          localParcel1.writeInterfaceToken("com.google.android.gms.ads.internal.client.IAdManager");
          this.lb.transact(3, localParcel1, localParcel2, 0);
          localParcel2.readException();
          int i = localParcel2.readInt();
          if (i != 0) {
            bool = true;
          }
          return bool;
        }
        finally
        {
          localParcel2.recycle();
          localParcel1.recycle();
        }
      }
      
      public void pause()
        throws RemoteException
      {
        Parcel localParcel1 = Parcel.obtain();
        Parcel localParcel2 = Parcel.obtain();
        try
        {
          localParcel1.writeInterfaceToken("com.google.android.gms.ads.internal.client.IAdManager");
          this.lb.transact(5, localParcel1, localParcel2, 0);
          localParcel2.readException();
          return;
        }
        finally
        {
          localParcel2.recycle();
          localParcel1.recycle();
        }
      }
      
      public void resume()
        throws RemoteException
      {
        Parcel localParcel2 = Parcel.obtain();
        Parcel localParcel1 = Parcel.obtain();
        try
        {
          localParcel2.writeInterfaceToken("com.google.android.gms.ads.internal.client.IAdManager");
          this.lb.transact(6, localParcel2, localParcel1, 0);
          localParcel1.readException();
          return;
        }
        finally
        {
          localParcel1.recycle();
          localParcel2.recycle();
        }
      }
      
      public void showInterstitial()
        throws RemoteException
      {
        Parcel localParcel1 = Parcel.obtain();
        Parcel localParcel2 = Parcel.obtain();
        try
        {
          localParcel1.writeInterfaceToken("com.google.android.gms.ads.internal.client.IAdManager");
          this.lb.transact(9, localParcel1, localParcel2, 0);
          localParcel2.readException();
          return;
        }
        finally
        {
          localParcel2.recycle();
          localParcel1.recycle();
        }
      }
      
      public void stopLoading()
        throws RemoteException
      {
        Parcel localParcel2 = Parcel.obtain();
        Parcel localParcel1 = Parcel.obtain();
        try
        {
          localParcel2.writeInterfaceToken("com.google.android.gms.ads.internal.client.IAdManager");
          this.lb.transact(10, localParcel2, localParcel1, 0);
          localParcel1.readException();
          return;
        }
        finally
        {
          localParcel1.recycle();
          localParcel2.recycle();
        }
      }
    }
  }
}


/* Location:              C:\tools\androidhack\marvel_bitva_chempionov_v11.1.0_mod_lenov.ru\classes.jar!\com\google\android\gms\internal\bd.class
 * Java compiler version: 6 (50.0)
 * JD-Core Version:       0.7.1
 */